Workbook

Sheet Form127_Raw
A1: Airport_Code | B1: Airport_Name | C1: City | D1: State | E1: Hub_Size | F1: Year | G1: Enplanements | H1: Total_Operating_Revenue | I1: Total_Aeronautical_Revenue | J1: Total_Commercial_Revenue | K1: Food_Beverage_Revenue | L1: Retail_Revenue | M1: Rental_Car_Revenue | N1: Parking_Ground_Revenue | O1: Land_Lease_Revenue | P1: Terminal_Service_Revenue | Q1: Hotel_Revenue | R1: Other_Commercial_Revenue | S1: Operating_Expenses | T1: Operating_Income | U1: Total_Capex | V1: Total_Debt | W1: Passenger_Aero_Revenue | X1: Data_Source | Y1: Source_URL | Z1: Verification_Status | AA1: Verification_Note
A2: ATL | B2: Hartsfield/Jackson Atlanta International | C2: Atlanta | D2: GA | E2: Large | F2: 2019 | G2: 54531948 | H2: 568507000 | K2: 55845000 | L2: 52259000 | M2: 43607000 | N2: 159640000 | P2: 12955000 | S2: 316189000 | T2: -5195000 | U2: 1077677000 | V2: 3148793000 | W2: 157871000 | X2: DWU transcription of FAA CATS Form 127 | Y2: https://dwuconsulting.com/airports/ATL | Z2: Pilot - verified subset | AA2: FAA CATS portal is under scheduled maintenance (Sep 23-30, 2026). Verified multi-year CATS fields populated; detailed Form 127 fields not visible in the indexed summary are intentionally left blank pending direct FAA export.
A3: ATL | B3: Hartsfield/Jackson Atlanta International | C3: Atlanta | D3: GA | E3: Large | F3: 2020 | G3: 39747596 | H3: 442318000 | K3: 42960000 | L3: 32688000 | M3: 32001000 | N3: 117313000 | P3: 12239000 | S3: 323202000 | T3: -153378000 | U3: 793389000 | V3: 3417948000 | W3: 132337000 | X3: DWU transcription of FAA CATS Form 127 | Y3: https://dwuconsulting.com/airports/ATL | Z3: Pilot - verified subset | AA3: FAA CATS portal is under scheduled maintenance (Sep 23-30, 2026). Verified multi-year CATS fields populated; detailed Form 127 fields not visible in the indexed summary are intentionally left blank pending direct FAA export.
A4: ATL | B4: Hartsfield/Jackson Atlanta International | C4: Atlanta | D4: GA | E4: Large | F4: 2021 | G4: 24928472 | H4: 354470000 | K4: 15375000 | L4: 9696000 | M4: 33423000 | N4: 71047000 | P4: 3468000 | S4: 318621000 | T4: -249958000 | U4: 741487000 | V4: 3366052000 | W4: 142332000 | X4: DWU transcription of FAA CATS Form 127 | Y4: https://dwuconsulting.com/airports/ATL | Z4: Pilot - verified subset | AA4: FAA CATS portal is under scheduled maintenance (Sep 23-30, 2026). Verified multi-year CATS fields populated; detailed Form 127 fields not visible in the indexed summary are intentionally left blank pending direct FAA export.
A5: ATL | B5: Hartsfield/Jackson Atlanta International | C5: Atlanta | D5: GA | E5: Large | F5: 2022 | G5: 44860920 | H5: 379356000 | K5: 17315000 | L5: 11485000 | M5: 45636000 | N5: 158141000 | P5: 4690000 | S5: 308864000 | T5: -221088000 | U5: 1081124000 | V5: 3809061000 | W5: 46714000 | X5: DWU transcription of FAA CATS Form 127 | Y5: https://dwuconsulting.com/airports/ATL | Z5: Pilot - verified subset | AA5: FAA CATS portal is under scheduled maintenance (Sep 23-30, 2026). Verified multi-year CATS fields populated; detailed Form 127 fields not visible in the indexed summary are intentionally left blank pending direct FAA export.
A6: ATL | B6: Hartsfield/Jackson Atlanta International | C6: Atlanta | D6: GA | E6: Large | F6: 2023 | G6: 49691940 | H6: 508301000 | K6: 33455000 | L6: 21847000 | M6: 53039000 | N6: 176694000 | P6: 6131000 | S6: 371155000 | T6: -167133000 | U6: 1081740000 | V6: 3471964000 | W6: 112705000 | X6: DWU transcription of FAA CATS Form 127 | Y6: https://dwuconsulting.com/airports/ATL | Z6: Pilot - verified subset | AA6: FAA CATS portal is under scheduled maintenance (Sep 23-30, 2026). Verified multi-year CATS fields populated; detailed Form 127 fields not visible in the indexed summary are intentionally left blank pending direct FAA export.
A7: ATL | B7: Hartsfield/Jackson Atlanta International | C7: Atlanta | D7: GA | E7: Large | F7: 2024 | G7: 53681363 | H7: 682121000 | K7: 65475000 | L7: 47319000 | M7: 54030000 | N7: 179454000 | P7: 14575000 | S7: 403204000 | T7: -40446000 | U7: 1593429000 | V7: 4407374000 | W7: 211157000 | X7: DWU transcription of FAA CATS Form 127 | Y7: https://dwuconsulting.com/airports/ATL | Z7: Pilot - verified subset | AA7: FAA CATS portal is under scheduled maintenance (Sep 23-30, 2026). Verified multi-year CATS fields populated; detailed Form 127 fields not visible in the indexed summary are intentionally left blank pending direct FAA export.
A8: DFW | B8: Dallas-Fort Worth International | C8: Fort Worth | D8: TX | E8: Large | F8: 2019 | G8: 36623417 | H8: 1023927000 | K8: 40135000 | L8: 24775000 | M8: 47480000 | N8: 184414000 | P8: 26888000 | S8: 571918000 | T8: 148812000 | U8: 407893000 | V8: 6272280000 | W8: 474389000 | X8: DWU transcription of FAA CATS Form 127 | Y8: https://dwuconsulting.com/airports/DFW | Z8: Pilot - verified subset | AA8: FAA CATS portal is under scheduled maintenance (Sep 23-30, 2026). Verified multi-year CATS fields populated; detailed Form 127 fields not visible in the indexed summary are intentionally left blank pending direct FAA export.
A9: DFW | B9: Dallas-Fort Worth International | C9: Fort Worth | D9: TX | E9: Large | F9: 2020 | G9: 23661724 | H9: 786181000 | K9: 25733000 | L9: 12071000 | M9: 32367000 | N9: 103714000 | P9: 22189000 | S9: 537558000 | T9: -61538000 | U9: 484581000 | V9: 6175800000 | W9: 432726000 | X9: DWU transcription of FAA CATS Form 127 | Y9: https://dwuconsulting.com/airports/DFW | Z9: Pilot - verified subset | AA9: FAA CATS portal is under scheduled maintenance (Sep 23-30, 2026). Verified multi-year CATS fields populated; detailed Form 127 fields not visible in the indexed summary are intentionally left blank pending direct FAA export.
A10: DFW | B10: Dallas-Fort Worth International | C10: Fort Worth | D10: TX | E10: Large | F10: 2021 | G10: 27633567 | H10: 791802000 | K10: 30979000 | L10: 12873000 | M10: 40503000 | N10: 116564000 | P10: 20929000 | S10: 511736000 | T10: 280066000 | U10: 642523000 | V10: 6321955000 | W10: 431828000 | X10: DWU transcription of FAA CATS Form 127 | Y10: https://dwuconsulting.com/airports/DFW | Z10: Pilot - verified subset | AA10: FAA CATS portal is under scheduled maintenance (Sep 23-30, 2026). Verified multi-year CATS fields populated; detailed Form 127 fields not visible in the indexed summary are intentionally left blank pending direct FAA export.
A11: DFW | B11: Dallas-Fort Worth International | C11: Fort Worth | D11: TX | E11: Large | F11: 2022 | G11: 36057362 | H11: 977955000 | K11: 27667000 | L11: 24176000 | M11: 52908000 | N11: 195997000 | P11: 33495000 | S11: 612684000 | T11: 30681000 | U11: 496883000 | V11: 7491495000 | W11: 439592000 | X11: DWU transcription of FAA CATS Form 127 | Y11: https://dwuconsulting.com/airports/DFW | Z11: Pilot - verified subset | AA11: FAA CATS portal is under scheduled maintenance (Sep 23-30, 2026). Verified multi-year CATS fields populated; detailed Form 127 fields not visible in the indexed summary are intentionally left blank pending direct FAA export.
A12: DFW | B12: Dallas-Fort Worth International | C12: Fort Worth | D12: TX | E12: Large | F12: 2023 | G12: 39755000 | H12: 1070890000 | K12: 54072000 | L12: 23073000 | M12: 58416000 | N12: 224105000 | P12: 36309000 | S12: 696079000 | T12: 18478000 | U12: 601365000 | V12: 7476675000 | W12: 459427000 | X12: DWU transcription of FAA CATS Form 127 | Y12: https://dwuconsulting.com/airports/DFW | Z12: Pilot - verified subset | AA12: FAA CATS portal is under scheduled maintenance (Sep 23-30, 2026). Verified multi-year CATS fields populated; detailed Form 127 fields not visible in the indexed summary are intentionally left blank pending direct FAA export.
A13: DFW | B13: Dallas-Fort Worth International | C13: Fort Worth | D13: TX | E13: Large | F13: 2024 | G13: 43370826 | H13: 1248691000 | K13: 61356000 | L13: 26017000 | M13: 64571000 | N13: 251054000 | P13: 38715000 | S13: 755329000 | T13: 119158000 | U13: 1064961000 | V13: 7948300000 | W13: 582834000 | X13: DWU transcription of FAA CATS Form 127 | Y13: https://dwuconsulting.com/airports/DFW | Z13: Pilot - verified subset | AA13: FAA CATS portal is under scheduled maintenance (Sep 23-30, 2026). Verified multi-year CATS fields populated; detailed Form 127 fields not visible in the indexed summary are intentionally left blank pending direct FAA export.
... A159: JFK | B159: John F Kennedy International | C159: New York | D159: NY | E159: Large | F159: 2020 | G159: 8329975 | H159: 920388000 | K159: 1676000 | L159: 9800000 | M159: 17147000 | N159: 36201000 | P159: 1806000 | S159: 816449000 | T159: -116729000 | U159: 234752000 | V159: 0 | W159: 553625000 | X159: DWU transcription of FAA CATS Form 127 | Y159: https://dwuconsulting.com/airports/JFK | Z159: Large-hub review - verified CATS subset | AA159: Airport-level CATS operating/commercial data are usable. Debt/credit metrics are system-linked and should not be benchmarked against stand-alone airports.
A160: JFK | B160: John F Kennedy International | C160: New York | D160: NY | E160: Large | F160: 2021 | G160: 15311865 | H160: 1087199000 | K160: 2634000 | L160: 11304000 | M160: 24858000 | N160: 80659000 | P160: 2987000 | S160: 722016000 | T160: 145646000 | U160: 128182000 | W160: 718440000 | X160: DWU transcription of FAA CATS Form 127 | Y160: https://dwuconsulting.com/airports/JFK | Z160: Large-hub review - verified CATS subset | AA160: Airport-level CATS operating/commercial data are usable. Debt/credit metrics are system-linked and should not be benchmarked against stand-alone airports.
A161: JFK | B161: John F Kennedy International | C161: New York | D161: NY | E161: Large | F161: 2022 | G161: 27459554 | H161: 1486589000 | K161: 10443000 | L161: 22210000 | M161: 34122000 | N161: 135362000 | P161: 3680000 | S161: 839989000 | T161: 425762000 | U161: 235006000 | W161: 897200000 | X161: DWU transcription of FAA CATS Form 127 | Y161: https://dwuconsulting.com/airports/JFK | Z161: Large-hub review - verified CATS subset | AA161: Airport-level CATS operating/commercial data are usable. Debt/credit metrics are system-linked and should not be benchmarked against stand-alone airports.
A162: JFK | B162: John F Kennedy International | C162: New York | D162: NY | E162: Large | F162: 2023 | G162: 31025194 | H162: 1679745000 | K162: 5992000 | L162: 32974000 | M162: 35315000 | N162: 151458000 | P162: 5231000 | S162: 944776000 | T162: 521580000 | U162: 558920000 | W162: 1044113000 | X162: DWU transcription of FAA CATS Form 127 | Y162: https://dwuconsulting.com/airports/JFK | Z162: Large-hub review - verified CATS subset | AA162: Airport-level CATS operating/commercial data are usable. Debt/credit metrics are system-linked and should not be benchmarked against stand-alone airports.
A163: JFK | B163: John F Kennedy International | C163: New York | D163: NY | E163: Large | F163: 2024 | G163: 31632992 | H163: 1898669000 | K163: 4954000 | L163: 35744000 | M163: 39060000 | N163: 140686000 | P163: 5192000 | S163: 1018209000 | T163: 676106000 | U163: 779180000 | W163: 1139224000 | X163: DWU transcription of FAA CATS Form 127 | Y163: https://dwuconsulting.com/airports/JFK | Z163: Large-hub review - verified CATS subset | AA163: Airport-level CATS operating/commercial data are usable. Debt/credit metrics are system-linked and should not be benchmarked against stand-alone airports.
A164: EWR | B164: Newark Liberty International | C164: Newark | D164: NJ | E164: Large | F164: 2019 | G164: 23168226 | H164: 1052070000 | K164: 6532000 | L164: 33853000 | M164: 41086000 | N164: 107437000 | P164: 1171000 | S164: 591802000 | T164: 311728000 | U164: 719703000 | W164: 634915000 | X164: DWU transcription of FAA CATS Form 127 | Y164: https://dwuconsulting.com/airports/EWR | Z164: Large-hub review - verified CATS subset | AA164: Airport-level CATS operating/commercial data are usable. Debt/credit metrics are reported at the PANYNJ system level.
A165: EWR | B165: Newark Liberty International | C165: Newark | D165: NJ | E165: Large | F165: 2020 | G165: 7973879 | H165: 739600000 | K165: 962000 | L165: 9224000 | M165: 17527000 | N165: 39875000 | P165: 689000 | S165: 544024000 | T165: 43945000 | U165: 690772000 | W165: 472747000 | X165: DWU transcription of FAA CATS Form 127 | Y165: https://dwuconsulting.com/airports/EWR | Z165: Large-hub review - verified CATS subset | AA165: Airport-level CATS operating/commercial data are usable. Debt/credit metrics are reported at the PANYNJ system level.
A166: EWR | B166: Newark Liberty International | C166: Newark | D166: NJ | E166: Large | F166: 2021 | G166: 14472936 | H166: 976598000 | K166: 4614000 | L166: 12009000 | M166: 28383000 | N166: 91758000 | P166: 1121000 | S166: 531396000 | T166: 289823000 | U166: 654193000 | W166: 634594000 | X166: DWU transcription of FAA CATS Form 127 | Y166: https://dwuconsulting.com/airports/EWR | Z166: Large-hub review - verified CATS subset | AA166: Airport-level CATS operating/commercial data are usable. Debt/credit metrics are reported at the PANYNJ system level.
A167: EWR | B167: Newark Liberty International | C167: Newark | D167: NJ | E167: Large | F167: 2022 | G167: 21796929 | H167: 1142687000 | K167: 6379000 | L167: 19635000 | M167: 44041000 | N167: 146273000 | P167: 1204000 | S167: 628688000 | T167: 340431000 | U167: 515522000 | W167: 637335000 | X167: DWU transcription of FAA CATS Form 127 | Y167: https://dwuconsulting.com/airports/EWR | Z167: Large-hub review - verified CATS subset | AA167: Airport-level CATS operating/commercial data are usable. Debt/credit metrics are reported at the PANYNJ system level.
A168: EWR | B168: Newark Liberty International | C168: Newark | D168: NJ | E168: Large | F168: 2023 | G168: 24556503 | H168: 1357187000 | K168: 22009000 | L168: 35905000 | M168: 51928000 | N168: 166997000 | P168: 1212000 | S168: 749584000 | T168: 367792000 | U168: 225818000 | W168: 751529000 | X168: DWU transcription of FAA CATS Form 127 | Y168: https://dwuconsulting.com/airports/EWR | Z168: Large-hub review - verified CATS subset | AA168: Airport-level CATS operating/commercial data are usable. Debt/credit metrics are reported at the PANYNJ system level.
A169: EWR | B169: Newark Liberty International | C169: Newark | D169: NJ | E169: Large | F169: 2024 | G169: 24426685 | H169: 1391598000 | K169: 24876000 | L169: 46193000 | M169: 57221000 | N169: 159208000 | P169: 1217000 | S169: 785968000 | T169: 364605000 | U169: 429118000 | W169: 773528000 | X169: DWU transcription of FAA CATS Form 127 | Y169: https://dwuconsulting.com/airports/EWR | Z169: Large-hub review - verified CATS subset | AA169: Airport-level CATS operating/commercial data are usable. Debt/credit metrics are reported at the PANYNJ system level.
A170: LGA | B170: La Guardia | C170: New York | D170: NY | E170: Large | F170: 2019 | G170: 15542447 | H170: 429046000 | K170: 1351000 | L170: 3005000 | M170: 15476000 | N170: 41928000 | P170: 234000 | S170: 370045000 | T170: -65008000 | U170: 732177000 | W170: 318825000 | X170: DWU transcription of FAA CATS Form 127 | Y170: https://dwuconsulting.com/airports/LGA | Z170: Large-hub review - verified CATS subset | AA170: Airport-level CATS operating/commercial data are usable. Debt/credit metrics are reported at the PANYNJ system level.
A171: LGA | B171: La Guardia | C171: New York | D171: NY | E171: Large | F171: 2020 | G171: 4184418 | H171: 326552000 | K171: 559000 | L171: 988000 | M171: 9386000 | N171: 23878000 | P171: 606000 | S171: 342727000 | T171: -184847000 | U171: 433558000 | W171: 259370000 | X171: DWU transcription of FAA CATS Form 127 | Y171: https://dwuconsulting.com/airports/LGA | Z171: Large-hub review - verified CATS subset | AA171: Airport-level CATS operating/commercial data are usable. Debt/credit metrics are reported at the PANYNJ system level.
... A175: LGA | B175: La Guardia | C175: New York | D175: NY | E175: Large | F175: 2024 | G175: 16771972 | H175: 579390000 | K175: 7327000 | L175: 3313000 | M175: 19271000 | N175: 94983000 | P175: 287000 | S175: 461223000 | T175: -104238000 | U175: 80847000 | W175: 389160000 | X175: DWU transcription of FAA CATS Form 127 | Y175: https://dwuconsulting.com/airports/LGA | Z175: Large-hub review - verified CATS subset | AA175: Airport-level CATS operating/commercial data are usable. Debt/credit metrics are reported at the PANYNJ system level.
A176: IAD | B176: Washington Dulles International | C176: Dulles | D176: VA | E176: Large | F176: 2019 | G176: 12326926 | H176: 458719000 | K176: 17170000 | L176: 23729000 | M176: 15777000 | N176: 89254000 | P176: 13800000 | S176: 248208000 | T176: 36710000 | U176: 38118000 | V176: 3084545000 | W176: 182652000 | X176: DWU transcription of FAA CATS Form 127 | Y176: https://dwuconsulting.com/airports/IAD | Z176: Large-hub review - verified CATS subset | AA176: Airport-level CATS operating/commercial data are usable. Bond/credit context is MWAA system-level; do not use debt metrics for peer ranking.
A177: IAD | B177: Washington Dulles International | C177: Dulles | D177: VA | E177: Large | F177: 2020 | G177: 4083437 | H177: 298447000 | K177: 5025000 | L177: 5875000 | M177: 7343000 | N177: 25394000 | P177: 7414000 | S177: 214139000 | T177: -88559000 | U177: 62327000 | V177: 3403451000 | W177: 153504000 | X177: DWU transcription of FAA CATS Form 127 | Y177: https://dwuconsulting.com/airports/IAD | Z177: Large-hub review - verified CATS subset | AA177: Airport-level CATS operating/commercial data are usable. Bond/credit context is MWAA system-level; do not use debt metrics for peer ranking.
A178: IAD | B178: Washington Dulles International | C178: Dulles | D178: VA | E178: Large | F178: 2021 | G178: 7385023 | H178: 317813000 | K178: 7074000 | L178: 5756000 | M178: 12464000 | N178: 47860000 | P178: 8093000 | S178: 215067000 | T178: -67360000 | U178: 167127000 | V178: 3451951000 | W178: 125587000 | X178: DWU transcription of FAA CATS Form 127 | Y178: https://dwuconsulting.com/airports/IAD | Z178: Large-hub review - verified CATS subset | AA178: Airport-level CATS operating/commercial data are usable. Bond/credit context is MWAA system-level; do not use debt metrics for peer ranking.
A179: IAD | B179: Washington Dulles International | C179: Dulles | D179: VA | E179: Large | F179: 2022 | G179: 10586011 | H179: 446818000 | K179: 9386000 | L179: 4807000 | M179: 17848000 | N179: 87747000 | P179: 10584000 | S179: 242055000 | T179: 32873000 | U179: 318307000 | V179: 3354221000 | W179: 187267000 | X179: DWU transcription of FAA CATS Form 127 | Y179: https://dwuconsulting.com/airports/IAD | Z179: Large-hub review - verified CATS subset | AA179: Airport-level CATS operating/commercial data are usable. Bond/credit context is MWAA system-level; do not use debt metrics for peer ranking.
A180: IAD | B180: Washington Dulles International | C180: Dulles | D180: VA | E180: Large | F180: 2023 | G180: 12385245 | H180: 515667000 | K180: 10793000 | L180: 12417000 | M180: 18763000 | N180: 111786000 | P180: 17116000 | S180: 259340000 | T180: 82322000 | U180: 100579000 | V180: 3398283000 | W180: 194548000 | X180: DWU transcription of FAA CATS Form 127 | Y180: https://dwuconsulting.com/airports/IAD | Z180: Large-hub review - verified CATS subset | AA180: Airport-level CATS operating/commercial data are usable. Bond/credit context is MWAA system-level; do not use debt metrics for peer ranking.
A181: IAD | B181: Washington Dulles International | C181: Dulles | D181: VA | E181: Large | F181: 2024 | G181: 13454238 | H181: 531826000 | K181: 21115000 | L181: 18163000 | M181: 19491000 | N181: 124692000 | P181: 18044000 | S181: 298305000 | T181: 62654000 | U181: 282519000 | V181: 3455469000 | W181: 173308000 | X181: DWU transcription of FAA CATS Form 127 | Y181: https://dwuconsulting.com/airports/IAD | Z181: Large-hub review - verified CATS subset | AA181: Airport-level CATS operating/commercial data are usable. Bond/credit context is MWAA system-level; do not use debt metrics for peer ranking.
A182: DCA | B182: Ronald Reagan Washington Ntl | C182: Arlington | D182: VA | E182: Large | F182: 2019 | G182: 11949040 | H182: 294890000 | K182: 18393000 | L182: 6016000 | M182: 17531000 | N182: 83276000 | P182: 9547000 | S182: 193136000 | T182: 52483000 | U182: 187041000 | V182: 1158295000 | W182: 137313000 | X182: DWU transcription of FAA CATS Form 127 | Y182: https://dwuconsulting.com/airports/DCA | Z182: Large-hub review - verified CATS subset | AA182: Airport-level CATS operating/commercial data are usable. Bond/credit context is MWAA system-level; do not use debt metrics for peer ranking.
A183: DCA | B183: Ronald Reagan Washington Ntl | C183: Arlington | D183: VA | E183: Large | F183: 2020 | G183: 3767537 | H183: 177685000 | K183: 5647000 | L183: 2044000 | M183: 6870000 | N183: 28936000 | P183: 5556000 | S183: 163594000 | T183: -38061000 | U183: 279088000 | V183: 1136262000 | W183: 107977000 | X183: DWU transcription of FAA CATS Form 127 | Y183: https://dwuconsulting.com/airports/DCA | Z183: Large-hub review - verified CATS subset | AA183: Airport-level CATS operating/commercial data are usable. Bond/credit context is MWAA system-level; do not use debt metrics for peer ranking.
A184: DCA | B184: Ronald Reagan Washington Ntl | C184: Arlington | D184: VA | E184: Large | F184: 2021 | G184: 7048963 | H184: 233919000 | K184: 7352000 | L184: 2684000 | M184: 16271000 | N184: 52546000 | P184: 7389000 | S184: 159719000 | T184: 6608000 | U184: 1270067000 | V184: 1409668000 | W184: 126862000 | X184: DWU transcription of FAA CATS Form 127 | Y184: https://dwuconsulting.com/airports/DCA | Z184: Large-hub review - verified CATS subset | AA184: Airport-level CATS operating/commercial data are usable. Bond/credit context is MWAA system-level; do not use debt metrics for peer ranking.
A185: DCA | B185: Ronald Reagan Washington Ntl | C185: Arlington | D185: VA | E185: Large | F185: 2022 | G185: 11969485 | H185: 303578000 | K185: 10619000 | L185: 3244000 | M185: 19476000 | N185: 95969000 | P185: 10544000 | S185: 188225000 | T185: 30962000 | U185: 58199000 | V185: 1258301000 | W185: 133293000 | X185: DWU transcription of FAA CATS Form 127 | Y185: https://dwuconsulting.com/airports/DCA | Z185: Large-hub review - verified CATS subset | AA185: Airport-level CATS operating/commercial data are usable. Bond/credit context is MWAA system-level; do not use debt metrics for peer ranking.
A186: DCA | B186: Ronald Reagan Washington Ntl | C186: Arlington | D186: VA | E186: Large | F186: 2023 | G186: 12735187 | H186: 318176000 | K186: 15323000 | L186: 4030000 | M186: 21820000 | N186: 106656000 | P186: 16144000 | S186: 196699000 | T186: 32858000 | U186: 126530000 | V186: 1258056000 | W186: 119456000 | X186: DWU transcription of FAA CATS Form 127 | Y186: https://dwuconsulting.com/airports/DCA | Z186: Large-hub review - verified CATS subset | AA186: Airport-level CATS operating/commercial data are usable. Bond/credit context is MWAA system-level; do not use debt metrics for peer ranking.
A187: DCA | B187: Ronald Reagan Washington Ntl | C187: Arlington | D187: VA | E187: Large | F187: 2024 | G187: 13113084 | H187: 316019000 | K187: 25511000 | L187: 4719000 | M187: 22890000 | N187: 110355000 | P187: 16112000 | S187: 225208000 | T187: 423000 | U187: 95547000 | V187: 1369652000 | W187: 101424000 | X187: DWU transcription of FAA CATS Form 127 | Y187: https://dwuconsulting.com/airports/DCA | Z187: Large-hub review - verified CATS subset | AA187: Airport-level CATS operating/commercial data are usable. Bond/credit context is MWAA system-level; do not use debt metrics for peer ranking.
... A199: MDW | B199: Chicago Midway International | C199: Chicago | D199: IL | E199: Large | F199: 2024 | G199: 10707000 | H199: 288948000 | K199: 14840000 | L199: 7802000 | M199: 10561000 | N199: 38467000 | P199: 76000 | S199: 197953000 | T199: 35131000 | U199: 18876000 | V199: 1412373000 | W199: 166924000 | X199: DWU transcription of FAA CATS Form 127 | Y199: https://dwuconsulting.com/airports/MDW | Z199: Large-hub review - verified CATS subset | AA199: Clean airport-level FAA CATS series; suitable for commercial and operating comparisons.

Sheet Data_Dictionary
A1: Column_Name | B1: FAA_Source_Field | C1: Purpose / Notes
A2: Airport_Code | B2: Location ID | C2: Primary airport identifier / join key
A3: Airport_Name | B3: Airport Name | C3: Airport display name
A4: City | B4: Airport metadata | C4: City used for labels and mapping
A5: State | B5: Airport metadata | C5: State used for mapping and filtering
A6: Hub_Size | B6: FAA hub classification | C6: Large / Medium hub peer benchmarking
A7: Year | B7: Reporting / fiscal year | C7: 2019–2024 project period
A8: Enplanements | B8: Form 127 Line 16.1 | C8: Fiscal-year passenger enplanements; denominator for per-passenger KPIs
A9: Total_Operating_Revenue | B9: Form 127 Line 5.0 | C9: Total airport operating revenue
A10: Total_Aeronautical_Revenue | B10: Form 127 Line 3.0 | C10: Total aeronautical revenue
A11: Total_Commercial_Revenue | B11: Form 127 Line 4.9 | C11: Total non-aeronautical / commercial revenue; major KPI
A12: Food_Beverage_Revenue | B12: Form 127 Line 4.2 | C12: Food and beverage concession revenue
... A23: Total_Debt | B23: Form 127 Line 11.4 | C23: Total debt

Sheet Project_Setup
A1: U.S. Airport Commercial Revenue & Passenger Monetization Analytics
A3: Item | B3: Value | C3: Notes | D3: Source
A4: Project Period | B4: 2019–2024 | C4: Use final full-year data
A5: Initial Scope | B5: All large + medium U.S. hub airports | C5: Final 25–30 airports selected after completeness checks
A6: Primary Source | B6: FAA Form 5100-127 | C6: Operating & Financial Summary | D6: https://cats.airports.faa.gov/reports/form_127/
A7: Primary KPI | B7: Commercial Revenue per Passenger | C7: Total Commercial Revenue / Fiscal-Year Enplanements
A8: Core Business Question | B8: How effectively are major U.S. airports converting passenger traffic into commercial revenue? | C8: Benchmark against comparable peers and diagnose revenue-stream gaps
A10: Airport Master | B10: Value | C10: Source Basis | D10: Source
A11: Large Hubs | B11: 31 | C11: Final CY2024 FAA classification | D11: https://www.faa.gov/airports/planning_capacity/passenger_allcargo_stats/passenger/arp-cy2024-commercial-service-enplanements.pdf
A12: Medium Hubs | B12: 32 | C12: Final CY2024 FAA classification | D12: https://www.faa.gov/airports/planning_capacity/passenger_allcargo_stats/passenger/arp-cy2024-commercial-service-enplanements.pdf
A13: Total Candidate Airports | B13: 63 | C13: Large + Medium hubs | D13: https://www.faa.gov/airports/planning_capacity/passenger_allcargo_stats/passenger/arp-cy2024-commercial-service-enplanements.pdf
A15: Pilot Extraction | B15: Value | C15: Status | D15: Notes
A16: Airports tested | B16: 5 | C16: Complete | D16: ATL, DFW, LAX, SEA, CLE
A17: Airport-years loaded | B17: 30 | C17: Complete | D17: 2019-2024 for each airport
A18: Detailed FAA line backfill | B18: 5 | C18: Pending | D18: Total aero/non-aero and land/hotel/other fields await direct FAA CATS export after maintenance.
A20: Data Quality Scoring | B20: Value | C20: Weight / Threshold | D20: Notes
A21: Core financial coverage | B21: 4 fields × 6 years | C21: 60% | D21: Enplanements, operating revenue, operating expenses, operating income
A22: Commercial detail coverage | B22: 5 fields × 6 years | C22: 40% | D22: Parking, rental car, food & beverage, retail, terminal service
A23: Excellent | B23: Current completeness | C23: >=90% | D23: Preferred for final shortlist
A24: Good / Review | B24: Current completeness | C24: 70–89% | D24: Inspect missingness before selection
A25: Pending FAA fields | B25: 5 fields × 6 years | C25: Not scored yet | D25: Tracked separately until direct FAA CATS export is available
A27: Working Set Expansion | B27: Value | C27: Status | D27: Notes
A28: Airports loaded | B28: 25 | C28: Complete | D28: 5 pilot + 20 additional airports
A29: Airport-year records | B29: 150 | C29: Complete | D29: 25 airports × 6 years (2019-2024)
A30: Current verified fields | B30: 14 | C30: Complete | D30: Core financial + commercial detail + passenger aeronautical revenue
A31: Pending FAA detail fields | B31: 5 | C31: Pending | D31: Total Aero, Total Commercial, Land Lease, Hotel, Other Commercial
A32: Remaining candidates | B32: 38 | C32: Reserve | D32: Only extract if final quality/comparability review requires replacements
A34: Large Hub Review | B34: Value | C34: Status | D34: Notes
A35: Missing large hubs reviewed | B35: 8 | C35: Complete | D35: CLT, JFK, EWR, LGA, IAD, DCA, HNL, MDW
A36: New airport-year rows | B36: 48 | C36: Complete | D36: 8 airports × 6 years
A37: Total loaded airports | B37: 33 | C37: Complete | D37: All 31 Large Hubs + CLE and DAL as Medium-Hub comparison candidates
A38: Pooled-authority airports | B38: 6 | C38: Flagged | D38: JFK, EWR, LGA, IAD, DCA, HNL
A39: Peer finance rule | B39: Commercial/operating yes | C39: Locked | D39: Do not rank pooled-authority airports on debt/credit metrics.
A41: Final Analysis Population | B41: Value | C41: Status | D41: Notes
A42: Final airports | B42: 31 | C42: Locked | D42: All FAA Large Hub airports
A43: Analysis period | B43: 2019–2024 | C43: Locked | D43: 6 fiscal years per airport
A44: Final airport-year rows | B44: 186 | C44: Locked | D44: 31 Large Hubs × 6 years
A45: Reserve airports | B45: 2 | C45: Retained | D45: CLE and DAL; Medium Hubs, QA / fallback only
A46: Debt/credit ranking | B46: Excluded | C46: Locked | D46: Not comparable for pooled-authority airports
A47: Primary analysis focus | B47: Commercial monetization | C47: Locked | D47: Passengers, operating revenue, commercial categories, expenses, operating income
A49: Data Cleaning | B49: Value | C49: Status | D49: Notes
A50: Final cleaned population | B50: 31 Large Hubs | C50: Complete | D50: CLE and DAL excluded from analysis table
A51: Clean airport-year rows | B51: 186 | C51: Complete | D51: 2019–2024
A52: Core missing rows | B52: 0 | C52: Pass | D52: No imputation needed for core fields
A53: Flagged commercial-detail rows | B53: 8 | C53: Review | D53: 5 PHX zero rows + 3 MSP negative rows
A54: Negative operating-income rows | B54: 82 | C54: Preserved | D54: Valid reported values, not treated as errors
A55: Direct FAA backfill | B55: 5 fields | C55: Pending | D55: Tracked explicitly; no values invented

Sheet Airport_Master
A1: Airport_Code | B1: Airport_Name | C1: City | D1: State | E1: Hub_Size | F1: FAA_Region_Code | G1: FAA_Region | H1: CY2024_Enplanements | I1: CY2023_Enplanements | J1: YoY_Change | K1: CY2024_Rank | L1: Source_URL
A2: ATL | B2: Hartsfield/Jackson Atlanta International | C2: Atlanta | D2: GA | E2: Large | F2: SO | G2: Southern | H2: 52511402 | I2: 50950068 | J2: 0.0306 | K2: 1 | L2: https://www.faa.gov/airports/planning_capacity/passenger_allcargo_stats/passenger/arp-cy2024-commercial-service-enplanements.pdf
A3: DFW | B3: Dallas-Fort Worth International | C3: Fort Worth | D3: TX | E3: Large | F3: SW | G3: Southwest | H3: 42351316 | I3: 39246212 | J3: 0.0791 | K3: 2 | L3: https://www.faa.gov/airports/planning_capacity/passenger_allcargo_stats/passenger/arp-cy2024-commercial-service-enplanements.pdf
A4: DEN | B4: Denver International | C4: Denver | D4: CO | E4: Large | F4: NM | G4: Northwest Mountain | H4: 40012895 | I4: 37863967 | J4: 0.0568 | K4: 3 | L4: https://www.faa.gov/airports/planning_capacity/passenger_allcargo_stats/passenger/arp-cy2024-commercial-service-enplanements.pdf
A5: ORD | B5: Chicago O'Hare International | C5: Chicago | D5: IL | E5: Large | F5: GL | G5: Great Lakes | H5: 38575693 | I5: 35843104 | J5: 0.0762 | K5: 4 | L5: https://www.faa.gov/airports/planning_capacity/passenger_allcargo_stats/passenger/arp-cy2024-commercial-service-enplanements.pdf
A6: LAX | B6: Los Angeles International | C6: Los Angeles | D6: CA | E6: Large | F6: WP | G6: Western-Pacific | H6: 37760834 | I6: 40956673 | J6: -0.078 | K6: 5 | L6: https://www.faa.gov/airports/planning_capacity/passenger_allcargo_stats/passenger/arp-cy2024-commercial-service-enplanements.pdf
A7: JFK | B7: John F Kennedy International | C7: New York | D7: NY | E7: Large | F7: EA | G7: Eastern | H7: 31466102 | I7: 30804355 | J7: 0.0215 | K7: 6 | L7: https://www.faa.gov/airports/planning_capacity/passenger_allcargo_stats/passenger/arp-cy2024-commercial-service-enplanements.pdf
A8: CLT | B8: Charlotte/Douglas International | C8: Charlotte | D8: NC | E8: Large | F8: SO | G8: Southern | H8: 28523822 | I8: 25896224 | J8: 0.1015 | K8: 7 | L8: https://www.faa.gov/airports/planning_capacity/passenger_allcargo_stats/passenger/arp-cy2024-commercial-service-enplanements.pdf
A9: LAS | B9: Harry Reid International | C9: Las Vegas | D9: NV | E9: Large | F9: WP | G9: Western-Pacific | H9: 28244966 | I9: 27896199 | J9: 0.0125 | K9: 8 | L9: https://www.faa.gov/airports/planning_capacity/passenger_allcargo_stats/passenger/arp-cy2024-commercial-service-enplanements.pdf
A10: MCO | B10: Orlando International | C10: Orlando | D10: FL | E10: Large | F10: SO | G10: Southern | H10: 27859783 | I10: 28033205 | J10: -0.0062 | K10: 9 | L10: https://www.faa.gov/airports/planning_capacity/passenger_allcargo_stats/passenger/arp-cy2024-commercial-service-enplanements.pdf
A11: MIA | B11: Miami International | C11: Miami | D11: FL | E11: Large | F11: SO | G11: Southern | H11: 26588002 | I11: 24717048 | J11: 0.0757 | K11: 10 | L11: https://www.faa.gov/airports/planning_capacity/passenger_allcargo_stats/passenger/arp-cy2024-commercial-service-enplanements.pdf
A12: PHX | B12: Phoenix Sky Harbor International | C12: Phoenix | D12: AZ | E12: Large | F12: WP | G12: Western-Pacific | H12: 25595723 | I12: 23880504 | J12: 0.0718 | K12: 11 | L12: https://www.faa.gov/airports/planning_capacity/passenger_allcargo_stats/passenger/arp-cy2024-commercial-service-enplanements.pdf
A13: SEA | B13: Seattle-Tacoma International | C13: Seattle | D13: WA | E13: Large | F13: NM | G13: Northwest Mountain | H13: 25414592 | I13: 24594210 | J13: 0.0334 | K13: 12 | L13: https://www.faa.gov/airports/planning_capacity/passenger_allcargo_stats/passenger/arp-cy2024-commercial-service-enplanements.pdf
... A64: BOI | B64: Boise Air Trml/Gowen Field | C64: Boise | D64: ID | E64: Medium | F64: NM | G64: Northwest Mountain | H64: 2475370 | I64: 2369164 | J64: 0.0448 | K64: 63 | L64: https://www.faa.gov/airports/planning_capacity/passenger_allcargo_stats/passenger/arp-cy2024-commercial-service-enplanements.pdf

Sheet Pilot_Validation
A1: Airport_Code | B1: Airport_Name | C1: Hub_Size | D1: Years_Loaded | E1: Enplanements | F1: Total_Operating_Revenue | G1: Operating_Expenses | H1: Operating_Income | I1: Parking | J1: Rental_Car | K1: Food_Beverage | L1: Retail | M1: Terminal_Service | N1: Passenger_Aero | O1: Total_Aero | P1: Total_Commercial | Q1: Land_Lease | R1: Hotel | S1: Other_Commercial | T1: Pilot_Result | U1: Next_Action
A2: ATL | B2: Hartsfield/Jackson Atlanta International | C2: Large | D2: 2019-2024 | E2: Complete | F2: Complete | G2: Complete | H2: Complete | I2: Complete | J2: Complete | K2: Complete | L2: Complete | M2: Complete | N2: Complete | O2: Pending direct FAA | P2: Pending direct FAA | Q2: Pending direct FAA | R2: Pending direct FAA | S2: Pending direct FAA | T2: PASS - core trend fields verified | U2: Backfill detailed Form 127 revenue lines after FAA CATS maintenance; then run full 63-airport completeness test.
A3: DFW | B3: Dallas-Fort Worth International | C3: Large | D3: 2019-2024 | E3: Complete | F3: Complete | G3: Complete | H3: Complete | I3: Complete | J3: Complete | K3: Complete | L3: Complete | M3: Complete | N3: Complete | O3: Pending direct FAA | P3: Pending direct FAA | Q3: Pending direct FAA | R3: Pending direct FAA | S3: Pending direct FAA | T3: PASS - core trend fields verified | U3: Backfill detailed Form 127 revenue lines after FAA CATS maintenance; then run full 63-airport completeness test.
A4: LAX | B4: Los Angeles International | C4: Large | D4: 2019-2024 | E4: Complete | F4: Complete | G4: Complete | H4: Complete | I4: Complete | J4: Complete | K4: Complete | L4: Complete | M4: Complete | N4: Complete | O4: Pending direct FAA | P4: Pending direct FAA | Q4: Pending direct FAA | R4: Pending direct FAA | S4: Pending direct FAA | T4: PASS - core trend fields verified | U4: Backfill detailed Form 127 revenue lines after FAA CATS maintenance; then run full 63-airport completeness test.
A5: SEA | B5: Seattle-Tacoma International | C5: Large | D5: 2019-2024 | E5: Complete | F5: Complete | G5: Complete | H5: Complete | I5: Complete | J5: Complete | K5: Complete | L5: Complete | M5: Complete | N5: Complete | O5: Pending direct FAA | P5: Pending direct FAA | Q5: Pending direct FAA | R5: Pending direct FAA | S5: Pending direct FAA | T5: PASS - core trend fields verified | U5: Backfill detailed Form 127 revenue lines after FAA CATS maintenance; then run full 63-airport completeness test.
A6: CLE | B6: Cleveland-Hopkins International | C6: Medium | D6: 2019-2024 | E6: Complete | F6: Complete | G6: Complete | H6: Complete | I6: Complete | J6: Complete | K6: Complete | L6: Complete | M6: Complete | N6: Complete | O6: Pending direct FAA | P6: Pending direct FAA | Q6: Pending direct FAA | R6: Pending direct FAA | S6: Pending direct FAA | T6: PASS - core trend fields verified | U6: Backfill detailed Form 127 revenue lines after FAA CATS maintenance; then run full 63-airport completeness test.

Sheet Data_Quality
A1: Airport Data Quality & Completeness Scorecard
A2: Purpose: select airports with reliable 2019–2024 data. Zeros count as reported values; blanks count as missing. Pending FAA Form 127 fields are tracked separately and do not reduce the current completeness score.
A4: Candidate Airports | B4: Loaded Airports | C4: 6-Year Coverage | D4: Excellent (>=90%) | E4: Good (80-89%) | F4: Review (70-79%) | G4: Exclude (<70%) | H4: FAA Backfill Pending | J4: Scoring Component | K4: Fields | L4: Weight | M4: Rule | N4: Interpretation
A5: =COUNTA(Airport_Master!$A$2:$A$64) -> 63 | B5: =COUNTIF($D$9:$D$71,">0") -> 33 | C5: =COUNTIF($D$9:$D$71,6) -> 33 | D5: =COUNTIF($R$9:$R$71,">=0.9") -> 33 | E5: =COUNTIFS($R$9:$R$71,">=0.8",$R$9:$R$71,"<0.9") -> 0 | F5: =COUNTIFS($R$9:$R$71,">=0.7",$R$9:$R$71,"<0.8") -> 0 | G5: =COUNTIFS($D$9:$D$71,">0",$R$9:$R$71,"<0.7") -> 0 | H5: =COUNTIFS($D$9:$D$71,">0",$S$9:$S$71,"<1") -> 33 | J5: Core financial coverage | K5: Enplanements, Operating Revenue, Operating Expenses, Operating Income | L5: 0.6 | M5: Nonblank years / 24 expected cells | N5: Required for reliable trend and financial analysis
J6: Commercial detail coverage | K6: Parking, Rental Car, Food & Beverage, Retail, Terminal Service | L6: 0.4 | M6: Nonblank years / 30 expected cells | N6: Required for passenger-monetization diagnosis
J7: Pending FAA backfill | K7: Total Aero, Total Commercial, Land Lease, Hotel, Other Commercial | M7: Tracked separately; not scored yet | N7: Will be added after direct FAA CATS export is available
A8: Airport_Code | B8: Airport_Name | C8: Hub_Size | D8: Years_Loaded | E8: Year_Coverage_% | F8: Enplanements_Yrs | G8: Operating_Revenue_Yrs | H8: Operating_Expenses_Yrs | I8: Operating_Income_Yrs | J8: Parking_Yrs | K8: Rental_Car_Yrs | L8: Food_Beverage_Yrs | M8: Retail_Yrs | N8: Terminal_Service_Yrs | O8: Core_Coverage_% | P8: Commercial_Detail_% | Q8: Zero_Value_Flag_Count | R8: Current_Completeness_% | S8: Pending_FAA_Coverage_% | T8: Selection_Status
A9: =Airport_Master!A2 -> ATL | B9: =Airport_Master!B2 -> Hartsfield/Jackson Atlanta International | C9: =Airport_Master!E2 -> Large | D9: =COUNTIFS(Form127_Raw!$A$2:$A$1000,$A9,Form127_Raw!$F$2:$F$1000,">=2019",Form127_Raw!$F$2:$F$1000,"<=2024") -> 6 | E9: =D9/6 -> 1 | F9: =COUNTIFS(Form127_Raw!$A$2:$A$1000,$A9,Form127_Raw!$F$2:$F$1000,">=2019",Form127_Raw!$F$2:$F$1000,"<=2024",Form127_Raw!$G$2:$G$1000,"<>") -> 6 | G9: =COUNTIFS(Form127_Raw!$A$2:$A$1000,$A9,Form127_Raw!$F$2:$F$1000,">=2019",Form127_Raw!$F$2:$F$1000,"<=2024",Form127_Raw!$H$2:$H$1000,"<>") -> 6 | H9: =COUNTIFS(Form127_Raw!$A$2:$A$1000,$A9,Form127_Raw!$F$2:$F$1000,">=2019",Form127_Raw!$F$2:$F$1000,"<=2024",Form127_Raw!$S$2:$S$1000,"<>") -> 6 | I9: =COUNTIFS(Form127_Raw!$A$2:$A$1000,$A9,Form127_Raw!$F$2:$F$1000,">=2019",Form127_Raw!$F$2:$F$1000,"<=2024",Form127_Raw!$T$2:$T$1000,"<>") -> 6 | J9: =COUNTIFS(Form127_Raw!$A$2:$A$1000,$A9,Form127_Raw!$F$2:$F$1000,">=2019",Form127_Raw!$F$2:$F$1000,"<=2024",Form127_Raw!$N$2:$N$1000,"<>") -> 6 | K9: =COUNTIFS(Form127_Raw!$A$2:$A$1000,$A9,Form127_Raw!$F$2:$F$1000,">=2019",Form127_Raw!$F$2:$F$1000,"<=2024",Form127_Raw!$M$2:$M$1000,"<>") -> 6 | L9: =COUNTIFS(Form127_Raw!$A$2:$A$1000,$A9,Form127_Raw!$F$2:$F$1000,">=2019",Form127_Raw!$F$2:$F$1000,"<=2024",Form127_Raw!$K$2:$K$1000,"<>") -> 6 | M9: =COUNTIFS(Form127_Raw!$A$2:$A$1000,$A9,Form127_Raw!$F$2:$F$1000,">=2019",Form127_Raw!$F$2:$F$1000,"<=2024",Form127_Raw!$L$2:$L$1000,"<>") -> 6 | N9: =COUNTIFS(Form127_Raw!$A$2:$A$1000,$A9,Form127_Raw!$F$2:$F$1000,">=2019",Form127_Raw!$F$2:$F$1000,"<=2024",Form127_Raw!$P$2:$P$1000,"<>") -> 6 | O9: =SUM(F9:I9)/24 -> 1 | P9: =SUM(J9:N9)/30 -> 1 | Q9: =COUNTIFS(Form127_Raw!$A$2:$A$1000,$A9,Form127_Raw!$F$2:$F$1000,">=2019",Form127_Raw!$F$2:$F$1000,"<=2024",Form127_Raw!$N$2:$N$1000,0)+COUNTIFS(Form127_Raw!$A$2:$A$1000,$A9,Form127_Raw!$F$2:$F$1000,">=2019",Form127_Raw!$F$2:$F$1000,"<=2024",Form127_Raw!$M$2:$M$1000,0)+COUNTIFS(Form127_Raw!$A$2:$A$1000,$A9,Form127_Raw!$F$2:$F$1000,">=2019",Form127_Raw!$F$2:$F$1000,"<=2024",Form127_Raw!$K$2:$K$1000,0)+COUNTIFS(Form127_Raw!$A$2:$A$1000,$A9,Form127_Raw!$F$2:$F$1000,">=2019",Form127_Raw!$F$2:$F$1000,"<=2024",Form127_Raw!$L$2:$L$1000,0)+COUNTIFS(Form127_Raw!$A$2:$A$1000,$A9,Form127_Raw!$F$2:$F$1000,">=2019",Form127_Raw!$F$2:$F$1000,"<=2024",Form127_Raw!$P$2:$P$1000,0) -> 0 | R9: =O9*0.6+P9*0.4 -> 1 | S9: =(COUNTIFS(Form127_Raw!$A$2:$A$1000,$A9,Form127_Raw!$F$2:$F$1000,">=2019",Form127_Raw!$F$2:$F$1000,"<=2024",Form127_Raw!$I$2:$I$1000,"<>")+COUNTIFS(Form127_Raw!$A$2:$A$1000,$A9,Form127_Raw!$F$2:$F$1000,">=2019",Form127_Raw!$F$2:$F$1000,"<=2024",Form127_Raw!$J$2:$J$1000,"<>")+COUNTIFS(Form127_Raw!$A$2:$A$1000,$A9,Form127_Raw!$F$2:$F$1000,">=2019",Form127_Raw!$F$2:$F$1000,"<=2024",Form127_Raw!$O$2:$O$1000,"<>")+COUNTIFS(Form127_Raw!$A$2:$A$1000,$A9,Form127_Raw!$F$2:$F$1000,">=2019",Form127_Raw!$F$2:$F$1000,"<=2024",Form127_Raw!$Q$2:$Q$1000,"<>")+COUNTIFS(Form127_Raw!$A$2:$A$1000,$A9,Form127_Raw!$F$2:$F$1000,">=2019",Form127_Raw!$F$2:$F$1000,"<=2024",Form127_Raw!$R$2:$R$1000,"<>"))/30 -> 0 | T9: =IF(D9=0,"Not Loaded",IF(R9>=0.9,IF(S9=1,"Ready for Final Selection","Excellent - FAA Backfill Pending"),IF(R9>=0.8,"Good - Review Missing Fields",IF(R9>=0.7,"Manual Review","Exclude / Incomplete")))) -> Excellent - FAA Backfill Pending
A10: =Airport_Master!A3 -> DFW | B10: =Airport_Master!B3 -> Dallas-Fort Worth International | C10: =Airport_Master!E3 -> Large | D10: =COUNTIFS(Form127_Raw!$A$2:$A$1000,$A10,Form127_Raw!$F$2:$F$1000,">=2019",Form127_Raw!$F$2:$F$1000,"<=2024") -> 6 | E10: =D10/6 -> 1 | F10: =COUNTIFS(Form127_Raw!$A$2:$A$1000,$A10,Form127_Raw!$F$2:$F$1000,">=2019",Form127_Raw!$F$2:$F$1000,"<=2024",Form127_Raw!$G$2:$G$1000,"<>") -> 6 | G10: =COUNTIFS(Form127_Raw!$A$2:$A$1000,$A10,Form127_Raw!$F$2:$F$1000,">=2019",Form127_Raw!$F$2:$F$1000,"<=2024",Form127_Raw!$H$2:$H$1000,"<>") -> 6 | H10: =COUNTIFS(Form127_Raw!$A$2:$A$1000,$A10,Form127_Raw!$F$2:$F$1000,">=2019",Form127_Raw!$F$2:$F$1000,"<=2024",Form127_Raw!$S$2:$S$1000,"<>") -> 6 | I10: =COUNTIFS(Form127_Raw!$A$2:$A$1000,$A10,Form127_Raw!$F$2:$F$1000,">=2019",Form127_Raw!$F$2:$F$1000,"<=2024",Form127_Raw!$T$2:$T$1000,"<>") -> 6 | J10: =COUNTIFS(Form127_Raw!$A$2:$A$1000,$A10,Form127_Raw!$F$2:$F$1000,">=2019",Form127_Raw!$F$2:$F$1000,"<=2024",Form127_Raw!$N$2:$N$1000,"<>") -> 6 | K10: =COUNTIFS(Form127_Raw!$A$2:$A$1000,$A10,Form127_Raw!$F$2:$F$1000,">=2019",Form127_Raw!$F$2:$F$1000,"<=2024",Form127_Raw!$M$2:$M$1000,"<>") -> 6 | L10: =COUNTIFS(Form127_Raw!$A$2:$A$1000,$A10,Form127_Raw!$F$2:$F$1000,">=2019",Form127_Raw!$F$2:$F$1000,"<=2024",Form127_Raw!$K$2:$K$1000,"<>") -> 6 | M10: =COUNTIFS(Form127_Raw!$A$2:$A$1000,$A10,Form127_Raw!$F$2:$F$1000,">=2019",Form127_Raw!$F$2:$F$1000,"<=2024",Form127_Raw!$L$2:$L$1000,"<>") -> 6 | N10: =COUNTIFS(Form127_Raw!$A$2:$A$1000,$A10,Form127_Raw!$F$2:$F$1000,">=2019",Form127_Raw!$F$2:$F$1000,"<=2024",Form127_Raw!$P$2:$P$1000,"<>") -> 6 | O10: =SUM(F10:I10)/24 -> 1 | P10: =SUM(J10:N10)/30 -> 1 | Q10: =COUNTIFS(Form127_Raw!$A$2:$A$1000,$A10,Form127_Raw!$F$2:$F$1000,">=2019",Form127_Raw!$F$2:$F$1000,"<=2024",Form127_Raw!$N$2:$N$1000,0)+COUNTIFS(Form127_Raw!$A$2:$A$1000,$A10,Form127_Raw!$F$2:$F$1000,">=2019",Form127_Raw!$F$2:$F$1000,"<=2024",Form127_Raw!$M$2:$M$1000,0)+COUNTIFS(Form127_Raw!$A$2:$A$1000,$A10,Form127_Raw!$F$2:$F$1000,">=2019",Form127_Raw!$F$2:$F$1000,"<=2024",Form127_Raw!$K$2:$K$1000,0)+COUNTIFS(Form127_Raw!$A$2:$A$1000,$A10,Form127_Raw!$F$2:$F$1000,">=2019",Form127_Raw!$F$2:$F$1000,"<=2024",Form127_Raw!$L$2:$L$1000,0)+COUNTIFS(Form127_Raw!$A$2:$A$1000,$A10,Form127_Raw!$F$2:$F$1000,">=2019",Form127_Raw!$F$2:$F$1000,"<=2024",Form127_Raw!$P$2:$P$1000,0) -> 0 | R10: =O10*0.6+P10*0.4 -> 1 | S10: =(COUNTIFS(Form127_Raw!$A$2:$A$1000,$A10,Form127_Raw!$F$2:$F$1000,">=2019",Form127_Raw!$F$2:$F$1000,"<=2024",Form127_Raw!$I$2:$I$1000,"<>")+COUNTIFS(Form127_Raw!$A$2:$A$1000,$A10,Form127_Raw!$F$2:$F$1000,">=2019",Form127_Raw!$F$2:$F$1000,"<=2024",Form127_Raw!$J$2:$J$1000,"<>")+COUNTIFS(Form127_Raw!$A$2:$A$1000,$A10,Form127_Raw!$F$2:$F$1000,">=2019",Form127_Raw!$F$2:$F$1000,"<=2024",Form127_Raw!$O$2:$O$1000,"<>")+COUNTIFS(Form127_Raw!$A$2:$A$1000,$A10,Form127_Raw!$F$2:$F$1000,">=2019",Form127_Raw!$F$2:$F$1000,"<=2024",Form127_Raw!$Q$2:$Q$1000,"<>")+COUNTIFS(Form127_Raw!$A$2:$A$1000,$A10,Form127_Raw!$F$2:$F$1000,">=2019",Form127_Raw!$F$2:$F$1000,"<=2024",Form127_Raw!$R$2:$R$1000,"<>"))/30 -> 0 | T10: =IF(D10=0,"Not Loaded",IF(R10>=0.9,IF(S10=1,"Ready for Final Selection","Excellent - FAA Backfill Pending"),IF(R10>=0.8,"Good - Review Missing Fields",IF(R10>=0.7,"Manual Review","Exclude / Incomplete")))) -> Excellent - FAA Backfill Pending
A11: =Airport_Master!A4 -> DEN | B11: =Airport_Master!B4 -> Denver International | C11: =Airport_Master!E4 -> Large | D11: =COUNTIFS(Form127_Raw!$A$2:$A$1000,$A11,Form127_Raw!$F$2:$F$1000,">=2019",Form127_Raw!$F$2:$F$1000,"<=2024") -> 6 | E11: =D11/6 -> 1 | F11: =COUNTIFS(Form127_Raw!$A$2:$A$1000,$A11,Form127_Raw!$F$2:$F$1000,">=2019",Form127_Raw!$F$2:$F$1000,"<=2024",Form127_Raw!$G$2:$G$1000,"<>") -> 6 | G11: =COUNTIFS(Form127_Raw!$A$2:$A$1000,$A11,Form127_Raw!$F$2:$F$1000,">=2019",Form127_Raw!$F$2:$F$1000,"<=2024",Form127_Raw!$H$2:$H$1000,"<>") -> 6 | H11: =COUNTIFS(Form127_Raw!$A$2:$A$1000,$A11,Form127_Raw!$F$2:$F$1000,">=2019",Form127_Raw!$F$2:$F$1000,"<=2024",Form127_Raw!$S$2:$S$1000,"<>") -> 6 | I11: =COUNTIFS(Form127_Raw!$A$2:$A$1000,$A11,Form127_Raw!$F$2:$F$1000,">=2019",Form127_Raw!$F$2:$F$1000,"<=2024",Form127_Raw!$T$2:$T$1000,"<>") -> 6 | J11: =COUNTIFS(Form127_Raw!$A$2:$A$1000,$A11,Form127_Raw!$F$2:$F$1000,">=2019",Form127_Raw!$F$2:$F$1000,"<=2024",Form127_Raw!$N$2:$N$1000,"<>") -> 6 | K11: =COUNTIFS(Form127_Raw!$A$2:$A$1000,$A11,Form127_Raw!$F$2:$F$1000,">=2019",Form127_Raw!$F$2:$F$1000,"<=2024",Form127_Raw!$M$2:$M$1000,"<>") -> 6 | L11: =COUNTIFS(Form127_Raw!$A$2:$A$1000,$A11,Form127_Raw!$F$2:$F$1000,">=2019",Form127_Raw!$F$2:$F$1000,"<=2024",Form127_Raw!$K$2:$K$1000,"<>") -> 6 | M11: =COUNTIFS(Form127_Raw!$A$2:$A$1000,$A11,Form127_Raw!$F$2:$F$1000,">=2019",Form127_Raw!$F$2:$F$1000,"<=2024",Form127_Raw!$L$2:$L$1000,"<>") -> 6 | N11: =COUNTIFS(Form127_Raw!$A$2:$A$1000,$A11,Form127_Raw!$F$2:$F$1000,">=2019",Form127_Raw!$F$2:$F$1000,"<=2024",Form127_Raw!$P$2:$P$1000,"<>") -> 6 | O11: =SUM(F11:I11)/24 -> 1 | P11: =SUM(J11:N11)/30 -> 1 | Q11: =COUNTIFS(Form127_Raw!$A$2:$A$1000,$A11,Form127_Raw!$F$2:$F$1000,">=2019",Form127_Raw!$F$2:$F$1000,"<=2024",Form127_Raw!$N$2:$N$1000,0)+COUNTIFS(Form127_Raw!$A$2:$A$1000,$A11,Form127_Raw!$F$2:$F$1000,">=2019",Form127_Raw!$F$2:$F$1000,"<=2024",Form127_Raw!$M$2:$M$1000,0)+COUNTIFS(Form127_Raw!$A$2:$A$1000,$A11,Form127_Raw!$F$2:$F$1000,">=2019",Form127_Raw!$F$2:$F$1000,"<=2024",Form127_Raw!$K$2:$K$1000,0)+COUNTIFS(Form127_Raw!$A$2:$A$1000,$A11,Form127_Raw!$F$2:$F$1000,">=2019",Form127_Raw!$F$2:$F$1000,"<=2024",Form127_Raw!$L$2:$L$1000,0)+COUNTIFS(Form127_Raw!$A$2:$A$1000,$A11,Form127_Raw!$F$2:$F$1000,">=2019",Form127_Raw!$F$2:$F$1000,"<=2024",Form127_Raw!$P$2:$P$1000,0) -> 0 | R11: =O11*0.6+P11*0.4 -> 1 | S11: =(COUNTIFS(Form127_Raw!$A$2:$A$1000,$A11,Form127_Raw!$F$2:$F$1000,">=2019",Form127_Raw!$F$2:$F$1000,"<=2024",Form127_Raw!$I$2:$I$1000,"<>")+COUNTIFS(Form127_Raw!$A$2:$A$1000,$A11,Form127_Raw!$F$2:$F$1000,">=2019",Form127_Raw!$F$2:$F$1000,"<=2024",Form127_Raw!$J$2:$J$1000,"<>")+COUNTIFS(Form127_Raw!$A$2:$A$1000,$A11,Form127_Raw!$F$2:$F$1000,">=2019",Form127_Raw!$F$2:$F$1000,"<=2024",Form127_Raw!$O$2:$O$1000,"<>")+COUNTIFS(Form127_Raw!$A$2:$A$1000,$A11,Form127_Raw!$F$2:$F$1000,">=2019",Form127_Raw!$F$2:$F$1000,"<=2024",Form127_Raw!$Q$2:$Q$1000,"<>")+COUNTIFS(Form127_Raw!$A$2:$A$1000,$A11,Form127_Raw!$F$2:$F$1000,">=2019",Form127_Raw!$F$2:$F$1000,"<=2024",Form127_Raw!$R$2:$R$1000,"<>"))/30 -> 0 | T11: =IF(D11=0,"Not Loaded",IF(R11>=0.9,IF(S11=1,"Ready for Final Selection","Excellent - FAA Backfill Pending"),IF(R11>=0.8,"Good - Review Missing Fields",IF(R11>=0.7,"Manual Review","Exclude / Incomplete")))) -> Excellent - FAA Backfill Pending
A12: =Airport_Master!A5 -> ORD | B12: =Airport_Master!B5 -> Chicago O'Hare International | C12: =Airport_Master!E5 -> Large | D12: =COUNTIFS(Form127_Raw!$A$2:$A$1000,$A12,Form127_Raw!$F$2:$F$1000,">=2019",Form127_Raw!$F$2:$F$1000,"<=2024") -> 6 | E12: =D12/6 -> 1 | F12: =COUNTIFS(Form127_Raw!$A$2:$A$1000,$A12,Form127_Raw!$F$2:$F$1000,">=2019",Form127_Raw!$F$2:$F$1000,"<=2024",Form127_Raw!$G$2:$G$1000,"<>") -> 6 | G12: =COUNTIFS(Form127_Raw!$A$2:$A$1000,$A12,Form127_Raw!$F$2:$F$1000,">=2019",Form127_Raw!$F$2:$F$1000,"<=2024",Form127_Raw!$H$2:$H$1000,"<>") -> 6 | H12: =COUNTIFS(Form127_Raw!$A$2:$A$1000,$A12,Form127_Raw!$F$2:$F$1000,">=2019",Form127_Raw!$F$2:$F$1000,"<=2024",Form127_Raw!$S$2:$S$1000,"<>") -> 6 | I12: =COUNTIFS(Form127_Raw!$A$2:$A$1000,$A12,Form127_Raw!$F$2:$F$1000,">=2019",Form127_Raw!$F$2:$F$1000,"<=2024",Form127_Raw!$T$2:$T$1000,"<>") -> 6 | J12: =COUNTIFS(Form127_Raw!$A$2:$A$1000,$A12,Form127_Raw!$F$2:$F$1000,">=2019",Form127_Raw!$F$2:$F$1000,"<=2024",Form127_Raw!$N$2:$N$1000,"<>") -> 6 | K12: =COUNTIFS(Form127_Raw!$A$2:$A$1000,$A12,Form127_Raw!$F$2:$F$1000,">=2019",Form127_Raw!$F$2:$F$1000,"<=2024",Form127_Raw!$M$2:$M$1000,"<>") -> 6 | L12: =COUNTIFS(Form127_Raw!$A$2:$A$1000,$A12,Form127_Raw!$F$2:$F$1000,">=2019",Form127_Raw!$F$2:$F$1000,"<=2024",Form127_Raw!$K$2:$K$1000,"<>") -> 6 | M12: =COUNTIFS(Form127_Raw!$A$2:$A$1000,$A12,Form127_Raw!$F$2:$F$1000,">=2019",Form127_Raw!$F$2:$F$1000,"<=2024",Form127_Raw!$L$2:$L$1000,"<>") -> 6 | N12: =COUNTIFS(Form127_Raw!$A$2:$A$1000,$A12,Form127_Raw!$F$2:$F$1000,">=2019",Form127_Raw!$F$2:$F$1000,"<=2024",Form127_Raw!$P$2:$P$1000,"<>") -> 6 | O12: =SUM(F12:I12)/24 -> 1 | P12: =SUM(J12:N12)/30 -> 1 | Q12: =COUNTIFS(Form127_Raw!$A$2:$A$1000,$A12,Form127_Raw!$F$2:$F$1000,">=2019",Form127_Raw!$F$2:$F$1000,"<=2024",Form127_Raw!$N$2:$N$1000,0)+COUNTIFS(Form127_Raw!$A$2:$A$1000,$A12,Form127_Raw!$F$2:$F$1000,">=2019",Form127_Raw!$F$2:$F$1000,"<=2024",Form127_Raw!$M$2:$M$1000,0)+COUNTIFS(Form127_Raw!$A$2:$A$1000,$A12,Form127_Raw!$F$2:$F$1000,">=2019",Form127_Raw!$F$2:$F$1000,"<=2024",Form127_Raw!$K$2:$K$1000,0)+COUNTIFS(Form127_Raw!$A$2:$A$1000,$A12,Form127_Raw!$F$2:$F$1000,">=2019",Form127_Raw!$F$2:$F$1000,"<=2024",Form127_Raw!$L$2:$L$1000,0)+COUNTIFS(Form127_Raw!$A$2:$A$1000,$A12,Form127_Raw!$F$2:$F$1000,">=2019",Form127_Raw!$F$2:$F$1000,"<=2024",Form127_Raw!$P$2:$P$1000,0) -> 0 | R12: =O12*0.6+P12*0.4 -> 1 | S12: =(COUNTIFS(Form127_Raw!$A$2:$A$1000,$A12,Form127_Raw!$F$2:$F$1000,">=2019",Form127_Raw!$F$2:$F$1000,"<=2024",Form127_Raw!$I$2:$I$1000,"<>")+COUNTIFS(Form127_Raw!$A$2:$A$1000,$A12,Form127_Raw!$F$2:$F$1000,">=2019",Form127_Raw!$F$2:$F$1000,"<=2024",Form127_Raw!$J$2:$J$1000,"<>")+COUNTIFS(Form127_Raw!$A$2:$A$1000,$A12,Form127_Raw!$F$2:$F$1000,">=2019",Form127_Raw!$F$2:$F$1000,"<=2024",Form127_Raw!$O$2:$O$1000,"<>")+COUNTIFS(Form127_Raw!$A$2:$A$1000,$A12,Form127_Raw!$F$2:$F$1000,">=2019",Form127_Raw!$F$2:$F$1000,"<=2024",Form127_Raw!$Q$2:$Q$1000,"<>")+COUNTIFS(Form127_Raw!$A$2:$A$1000,$A12,Form127_Raw!$F$2:$F$1000,">=2019",Form127_Raw!$F$2:$F$1000,"<=2024",Form127_Raw!$R$2:$R$1000,"<>"))/30 -> 0 | T12: =IF(D12=0,"Not Loaded",IF(R12>=0.9,IF(S12=1,"Ready for Final Selection","Excellent - FAA Backfill Pending"),IF(R12>=0.8,"Good - Review Missing Fields",IF(R12>=0.7,"Manual Review","Exclude / Incomplete")))) -> Excellent - FAA Backfill Pending
A13: =Airport_Master!A6 -> LAX | B13: =Airport_Master!B6 -> Los Angeles International | C13: =Airport_Master!E6 -> Large | D13: =COUNTIFS(Form127_Raw!$A$2:$A$1000,$A13,Form127_Raw!$F$2:$F$1000,">=2019",Form127_Raw!$F$2:$F$1000,"<=2024") -> 6 | E13: =D13/6 -> 1 | F13: =COUNTIFS(Form127_Raw!$A$2:$A$1000,$A13,Form127_Raw!$F$2:$F$1000,">=2019",Form127_Raw!$F$2:$F$1000,"<=2024",Form127_Raw!$G$2:$G$1000,"<>") -> 6 | G13: =COUNTIFS(Form127_Raw!$A$2:$A$1000,$A13,Form127_Raw!$F$2:$F$1000,">=2019",Form127_Raw!$F$2:$F$1000,"<=2024",Form127_Raw!$H$2:$H$1000,"<>") -> 6 | H13: =COUNTIFS(Form127_Raw!$A$2:$A$1000,$A13,Form127_Raw!$F$2:$F$1000,">=2019",Form127_Raw!$F$2:$F$1000,"<=2024",Form127_Raw!$S$2:$S$1000,"<>") -> 6 | I13: =COUNTIFS(Form127_Raw!$A$2:$A$1000,$A13,Form127_Raw!$F$2:$F$1000,">=2019",Form127_Raw!$F$2:$F$1000,"<=2024",Form127_Raw!$T$2:$T$1000,"<>") -> 6 | J13: =COUNTIFS(Form127_Raw!$A$2:$A$1000,$A13,Form127_Raw!$F$2:$F$1000,">=2019",Form127_Raw!$F$2:$F$1000,"<=2024",Form127_Raw!$N$2:$N$1000,"<>") -> 6 | K13: =COUNTIFS(Form127_Raw!$A$2:$A$1000,$A13,Form127_Raw!$F$2:$F$1000,">=2019",Form127_Raw!$F$2:$F$1000,"<=2024",Form127_Raw!$M$2:$M$1000,"<>") -> 6 | L13: =COUNTIFS(Form127_Raw!$A$2:$A$1000,$A13,Form127_Raw!$F$2:$F$1000,">=2019",Form127_Raw!$F$2:$F$1000,"<=2024",Form127_Raw!$K$2:$K$1000,"<>") -> 6 | M13: =COUNTIFS(Form127_Raw!$A$2:$A$1000,$A13,Form127_Raw!$F$2:$F$1000,">=2019",Form127_Raw!$F$2:$F$1000,"<=2024",Form127_Raw!$L$2:$L$1000,"<>") -> 6 | N13: =COUNTIFS(Form127_Raw!$A$2:$A$1000,$A13,Form127_Raw!$F$2:$F$1000,">=2019",Form127_Raw!$F$2:$F$1000,"<=2024",Form127_Raw!$P$2:$P$1000,"<>") -> 6 | O13: =SUM(F13:I13)/24 -> 1 | P13: =SUM(J13:N13)/30 -> 1 | Q13: =COUNTIFS(Form127_Raw!$A$2:$A$1000,$A13,Form127_Raw!$F$2:$F$1000,">=2019",Form127_Raw!$F$2:$F$1000,"<=2024",Form127_Raw!$N$2:$N$1000,0)+COUNTIFS(Form127_Raw!$A$2:$A$1000,$A13,Form127_Raw!$F$2:$F$1000,">=2019",Form127_Raw!$F$2:$F$1000,"<=2024",Form127_Raw!$M$2:$M$1000,0)+COUNTIFS(Form127_Raw!$A$2:$A$1000,$A13,Form127_Raw!$F$2:$F$1000,">=2019",Form127_Raw!$F$2:$F$1000,"<=2024",Form127_Raw!$K$2:$K$1000,0)+COUNTIFS(Form127_Raw!$A$2:$A$1000,$A13,Form127_Raw!$F$2:$F$1000,">=2019",Form127_Raw!$F$2:$F$1000,"<=2024",Form127_Raw!$L$2:$L$1000,0)+COUNTIFS(Form127_Raw!$A$2:$A$1000,$A13,Form127_Raw!$F$2:$F$1000,">=2019",Form127_Raw!$F$2:$F$1000,"<=2024",Form127_Raw!$P$2:$P$1000,0) -> 0 | R13: =O13*0.6+P13*0.4 -> 1 | S13: =(COUNTIFS(Form127_Raw!$A$2:$A$1000,$A13,Form127_Raw!$F$2:$F$1000,">=2019",Form127_Raw!$F$2:$F$1000,"<=2024",Form127_Raw!$I$2:$I$1000,"<>")+COUNTIFS(Form127_Raw!$A$2:$A$1000,$A13,Form127_Raw!$F$2:$F$1000,">=2019",Form127_Raw!$F$2:$F$1000,"<=2024",Form127_Raw!$J$2:$J$1000,"<>")+COUNTIFS(Form127_Raw!$A$2:$A$1000,$A13,Form127_Raw!$F$2:$F$1000,">=2019",Form127_Raw!$F$2:$F$1000,"<=2024",Form127_Raw!$O$2:$O$1000,"<>")+COUNTIFS(Form127_Raw!$A$2:$A$1000,$A13,Form127_Raw!$F$2:$F$1000,">=2019",Form127_Raw!$F$2:$F$1000,"<=2024",Form127_Raw!$Q$2:$Q$1000,"<>")+COUNTIFS(Form127_Raw!$A$2:$A$1000,$A13,Form127_Raw!$F$2:$F$1000,">=2019",Form127_Raw!$F$2:$F$1000,"<=2024",Form127_Raw!$R$2:$R$1000,"<>"))/30 -> 0 | T13: =IF(D13=0,"Not Loaded",IF(R13>=0.9,IF(S13=1,"Ready for Final Selection","Excellent - FAA Backfill Pending"),IF(R13>=0.8,"Good - Review Missing Fields",IF(R13>=0.7,"Manual Review","Exclude / Incomplete")))) -> Excellent - FAA Backfill Pending
A14: =Airport_Master!A7 -> JFK | B14: =Airport_Master!B7 -> John F Kennedy International | C14: =Airport_Master!E7 -> Large | D14: =COUNTIFS(Form127_Raw!$A$2:$A$1000,$A14,Form127_Raw!$F$2:$F$1000,">=2019",Form127_Raw!$F$2:$F$1000,"<=2024") -> 6 | E14: =D14/6 -> 1 | F14: =COUNTIFS(Form127_Raw!$A$2:$A$1000,$A14,Form127_Raw!$F$2:$F$1000,">=2019",Form127_Raw!$F$2:$F$1000,"<=2024",Form127_Raw!$G$2:$G$1000,"<>") -> 6 | G14: =COUNTIFS(Form127_Raw!$A$2:$A$1000,$A14,Form127_Raw!$F$2:$F$1000,">=2019",Form127_Raw!$F$2:$F$1000,"<=2024",Form127_Raw!$H$2:$H$1000,"<>") -> 6 | H14: =COUNTIFS(Form127_Raw!$A$2:$A$1000,$A14,Form127_Raw!$F$2:$F$1000,">=2019",Form127_Raw!$F$2:$F$1000,"<=2024",Form127_Raw!$S$2:$S$1000,"<>") -> 6 | I14: =COUNTIFS(Form127_Raw!$A$2:$A$1000,$A14,Form127_Raw!$F$2:$F$1000,">=2019",Form127_Raw!$F$2:$F$1000,"<=2024",Form127_Raw!$T$2:$T$1000,"<>") -> 6 | J14: =COUNTIFS(Form127_Raw!$A$2:$A$1000,$A14,Form127_Raw!$F$2:$F$1000,">=2019",Form127_Raw!$F$2:$F$1000,"<=2024",Form127_Raw!$N$2:$N$1000,"<>") -> 6 | K14: =COUNTIFS(Form127_Raw!$A$2:$A$1000,$A14,Form127_Raw!$F$2:$F$1000,">=2019",Form127_Raw!$F$2:$F$1000,"<=2024",Form127_Raw!$M$2:$M$1000,"<>") -> 6 | L14: =COUNTIFS(Form127_Raw!$A$2:$A$1000,$A14,Form127_Raw!$F$2:$F$1000,">=2019",Form127_Raw!$F$2:$F$1000,"<=2024",Form127_Raw!$K$2:$K$1000,"<>") -> 6 | M14: =COUNTIFS(Form127_Raw!$A$2:$A$1000,$A14,Form127_Raw!$F$2:$F$1000,">=2019",Form127_Raw!$F$2:$F$1000,"<=2024",Form127_Raw!$L$2:$L$1000,"<>") -> 6 | N14: =COUNTIFS(Form127_Raw!$A$2:$A$1000,$A14,Form127_Raw!$F$2:$F$1000,">=2019",Form127_Raw!$F$2:$F$1000,"<=2024",Form127_Raw!$P$2:$P$1000,"<>") -> 6 | O14: =SUM(F14:I14)/24 -> 1 | P14: =SUM(J14:N14)/30 -> 1 | Q14: =COUNTIFS(Form127_Raw!$A$2:$A$1000,$A14,Form127_Raw!$F$2:$F$1000,">=2019",Form127_Raw!$F$2:$F$1000,"<=2024",Form127_Raw!$N$2:$N$1000,0)+COUNTIFS(Form127_Raw!$A$2:$A$1000,$A14,Form127_Raw!$F$2:$F$1000,">=2019",Form127_Raw!$F$2:$F$1000,"<=2024",Form127_Raw!$M$2:$M$1000,0)+COUNTIFS(Form127_Raw!$A$2:$A$1000,$A14,Form127_Raw!$F$2:$F$1000,">=2019",Form127_Raw!$F$2:$F$1000,"<=2024",Form127_Raw!$K$2:$K$1000,0)+COUNTIFS(Form127_Raw!$A$2:$A$1000,$A14,Form127_Raw!$F$2:$F$1000,">=2019",Form127_Raw!$F$2:$F$1000,"<=2024",Form127_Raw!$L$2:$L$1000,0)+COUNTIFS(Form127_Raw!$A$2:$A$1000,$A14,Form127_Raw!$F$2:$F$1000,">=2019",Form127_Raw!$F$2:$F$1000,"<=2024",Form127_Raw!$P$2:$P$1000,0) -> 0 | R14: =O14*0.6+P14*0.4 -> 1 | S14: =(COUNTIFS(Form127_Raw!$A$2:$A$1000,$A14,Form127_Raw!$F$2:$F$1000,">=2019",Form127_Raw!$F$2:$F$1000,"<=2024",Form127_Raw!$I$2:$I$1000,"<>")+COUNTIFS(Form127_Raw!$A$2:$A$1000,$A14,Form127_Raw!$F$2:$F$1000,">=2019",Form127_Raw!$F$2:$F$1000,"<=2024",Form127_Raw!$J$2:$J$1000,"<>")+COUNTIFS(Form127_Raw!$A$2:$A$1000,$A14,Form127_Raw!$F$2:$F$1000,">=2019",Form127_Raw!$F$2:$F$1000,"<=2024",Form127_Raw!$O$2:$O$1000,"<>")+COUNTIFS(Form127_Raw!$A$2:$A$1000,$A14,Form127_Raw!$F$2:$F$1000,">=2019",Form127_Raw!$F$2:$F$1000,"<=2024",Form127_Raw!$Q$2:$Q$1000,"<>")+COUNTIFS(Form127_Raw!$A$2:$A$1000,$A14,Form127_Raw!$F$2:$F$1000,">=2019",Form127_Raw!$F$2:$F$1000,"<=2024",Form127_Raw!$R$2:$R$1000,"<>"))/30 -> 0 | T14: =IF(D14=0,"Not Loaded",IF(R14>=0.9,IF(S14=1,"Ready for Final Selection","Excellent - FAA Backfill Pending"),IF(R14>=0.8,"Good - Review Missing Fields",IF(R14>=0.7,"Manual Review","Exclude / Incomplete")))) -> Excellent - FAA Backfill Pending
A15: =Airport_Master!A8 -> CLT | B15: =Airport_Master!B8 -> Charlotte/Douglas International | C15: =Airport_Master!E8 -> Large | D15: =COUNTIFS(Form127_Raw!$A$2:$A$1000,$A15,Form127_Raw!$F$2:$F$1000,">=2019",Form127_Raw!$F$2:$F$1000,"<=2024") -> 6 | E15: =D15/6 -> 1 | F15: =COUNTIFS(Form127_Raw!$A$2:$A$1000,$A15,Form127_Raw!$F$2:$F$1000,">=2019",Form127_Raw!$F$2:$F$1000,"<=2024",Form127_Raw!$G$2:$G$1000,"<>") -> 6 | G15: =COUNTIFS(Form127_Raw!$A$2:$A$1000,$A15,Form127_Raw!$F$2:$F$1000,">=2019",Form127_Raw!$F$2:$F$1000,"<=2024",Form127_Raw!$H$2:$H$1000,"<>") -> 6 | H15: =COUNTIFS(Form127_Raw!$A$2:$A$1000,$A15,Form127_Raw!$F$2:$F$1000,">=2019",Form127_Raw!$F$2:$F$1000,"<=2024",Form127_Raw!$S$2:$S$1000,"<>") -> 6 | I15: =COUNTIFS(Form127_Raw!$A$2:$A$1000,$A15,Form127_Raw!$F$2:$F$1000,">=2019",Form127_Raw!$F$2:$F$1000,"<=2024",Form127_Raw!$T$2:$T$1000,"<>") -> 6 | J15: =COUNTIFS(Form127_Raw!$A$2:$A$1000,$A15,Form127_Raw!$F$2:$F$1000,">=2019",Form127_Raw!$F$2:$F$1000,"<=2024",Form127_Raw!$N$2:$N$1000,"<>") -> 6 | K15: =COUNTIFS(Form127_Raw!$A$2:$A$1000,$A15,Form127_Raw!$F$2:$F$1000,">=2019",Form127_Raw!$F$2:$F$1000,"<=2024",Form127_Raw!$M$2:$M$1000,"<>") -> 6 | L15: =COUNTIFS(Form127_Raw!$A$2:$A$1000,$A15,Form127_Raw!$F$2:$F$1000,">=2019",Form127_Raw!$F$2:$F$1000,"<=2024",Form127_Raw!$K$2:$K$1000,"<>") -> 6 | M15: =COUNTIFS(Form127_Raw!$A$2:$A$1000,$A15,Form127_Raw!$F$2:$F$1000,">=2019",Form127_Raw!$F$2:$F$1000,"<=2024",Form127_Raw!$L$2:$L$1000,"<>") -> 6 | N15: =COUNTIFS(Form127_Raw!$A$2:$A$1000,$A15,Form127_Raw!$F$2:$F$1000,">=2019",Form127_Raw!$F$2:$F$1000,"<=2024",Form127_Raw!$P$2:$P$1000,"<>") -> 6 | O15: =SUM(F15:I15)/24 -> 1 | P15: =SUM(J15:N15)/30 -> 1 | Q15: =COUNTIFS(Form127_Raw!$A$2:$A$1000,$A15,Form127_Raw!$F$2:$F$1000,">=2019",Form127_Raw!$F$2:$F$1000,"<=2024",Form127_Raw!$N$2:$N$1000,0)+COUNTIFS(Form127_Raw!$A$2:$A$1000,$A15,Form127_Raw!$F$2:$F$1000,">=2019",Form127_Raw!$F$2:$F$1000,"<=2024",Form127_Raw!$M$2:$M$1000,0)+COUNTIFS(Form127_Raw!$A$2:$A$1000,$A15,Form127_Raw!$F$2:$F$1000,">=2019",Form127_Raw!$F$2:$F$1000,"<=2024",Form127_Raw!$K$2:$K$1000,0)+COUNTIFS(Form127_Raw!$A$2:$A$1000,$A15,Form127_Raw!$F$2:$F$1000,">=2019",Form127_Raw!$F$2:$F$1000,"<=2024",Form127_Raw!$L$2:$L$1000,0)+COUNTIFS(Form127_Raw!$A$2:$A$1000,$A15,Form127_Raw!$F$2:$F$1000,">=2019",Form127_Raw!$F$2:$F$1000,"<=2024",Form127_Raw!$P$2:$P$1000,0) -> 0 | R15: =O15*0.6+P15*0.4 -> 1 | S15: =(COUNTIFS(Form127_Raw!$A$2:$A$1000,$A15,Form127_Raw!$F$2:$F$1000,">=2019",Form127_Raw!$F$2:$F$1000,"<=2024",Form127_Raw!$I$2:$I$1000,"<>")+COUNTIFS(Form127_Raw!$A$2:$A$1000,$A15,Form127_Raw!$F$2:$F$1000,">=2019",Form127_Raw!$F$2:$F$1000,"<=2024",Form127_Raw!$J$2:$J$1000,"<>")+COUNTIFS(Form127_Raw!$A$2:$A$1000,$A15,Form127_Raw!$F$2:$F$1000,">=2019",Form127_Raw!$F$2:$F$1000,"<=2024",Form127_Raw!$O$2:$O$1000,"<>")+COUNTIFS(Form127_Raw!$A$2:$A$1000,$A15,Form127_Raw!$F$2:$F$1000,">=2019",Form127_Raw!$F$2:$F$1000,"<=2024",Form127_Raw!$Q$2:$Q$1000,"<>")+COUNTIFS(Form127_Raw!$A$2:$A$1000,$A15,Form127_Raw!$F$2:$F$1000,">=2019",Form127_Raw!$F$2:$F$1000,"<=2024",Form127_Raw!$R$2:$R$1000,"<>"))/30 -> 0 | T15: =IF(D15=0,"Not Loaded",IF(R15>=0.9,IF(S15=1,"Ready for Final Selection","Excellent - FAA Backfill Pending"),IF(R15>=0.8,"Good - Review Missing Fields",IF(R15>=0.7,"Manual Review","Exclude / Incomplete")))) -> Excellent - FAA Backfill Pending
A16: =Airport_Master!A9 -> LAS | B16: =Airport_Master!B9 -> Harry Reid International | C16: =Airport_Master!E9 -> Large | D16: =COUNTIFS(Form127_Raw!$A$2:$A$1000,$A16,Form127_Raw!$F$2:$F$1000,">=2019",Form127_Raw!$F$2:$F$1000,"<=2024") -> 6 | E16: =D16/6 -> 1 | F16: =COUNTIFS(Form127_Raw!$A$2:$A$1000,$A16,Form127_Raw!$F$2:$F$1000,">=2019",Form127_Raw!$F$2:$F$1000,"<=2024",Form127_Raw!$G$2:$G$1000,"<>") -> 6 | G16: =COUNTIFS(Form127_Raw!$A$2:$A$1000,$A16,Form127_Raw!$F$2:$F$1000,">=2019",Form127_Raw!$F$2:$F$1000,"<=2024",Form127_Raw!$H$2:$H$1000,"<>") -> 6 | H16: =COUNTIFS(Form127_Raw!$A$2:$A$1000,$A16,Form127_Raw!$F$2:$F$1000,">=2019",Form127_Raw!$F$2:$F$1000,"<=2024",Form127_Raw!$S$2:$S$1000,"<>") -> 6 | I16: =COUNTIFS(Form127_Raw!$A$2:$A$1000,$A16,Form127_Raw!$F$2:$F$1000,">=2019",Form127_Raw!$F$2:$F$1000,"<=2024",Form127_Raw!$T$2:$T$1000,"<>") -> 6 | J16: =COUNTIFS(Form127_Raw!$A$2:$A$1000,$A16,Form127_Raw!$F$2:$F$1000,">=2019",Form127_Raw!$F$2:$F$1000,"<=2024",Form127_Raw!$N$2:$N$1000,"<>") -> 6 | K16: =COUNTIFS(Form127_Raw!$A$2:$A$1000,$A16,Form127_Raw!$F$2:$F$1000,">=2019",Form127_Raw!$F$2:$F$1000,"<=2024",Form127_Raw!$M$2:$M$1000,"<>") -> 6 | L16: =COUNTIFS(Form127_Raw!$A$2:$A$1000,$A16,Form127_Raw!$F$2:$F$1000,">=2019",Form127_Raw!$F$2:$F$1000,"<=2024",Form127_Raw!$K$2:$K$1000,"<>") -> 6 | M16: =COUNTIFS(Form127_Raw!$A$2:$A$1000,$A16,Form127_Raw!$F$2:$F$1000,">=2019",Form127_Raw!$F$2:$F$1000,"<=2024",Form127_Raw!$L$2:$L$1000,"<>") -> 6 | N16: =COUNTIFS(Form127_Raw!$A$2:$A$1000,$A16,Form127_Raw!$F$2:$F$1000,">=2019",Form127_Raw!$F$2:$F$1000,"<=2024",Form127_Raw!$P$2:$P$1000,"<>") -> 6 | O16: =SUM(F16:I16)/24 -> 1 | P16: =SUM(J16:N16)/30 -> 1 | Q16: =COUNTIFS(Form127_Raw!$A$2:$A$1000,$A16,Form127_Raw!$F$2:$F$1000,">=2019",Form127_Raw!$F$2:$F$1000,"<=2024",Form127_Raw!$N$2:$N$1000,0)+COUNTIFS(Form127_Raw!$A$2:$A$1000,$A16,Form127_Raw!$F$2:$F$1000,">=2019",Form127_Raw!$F$2:$F$1000,"<=2024",Form127_Raw!$M$2:$M$1000,0)+COUNTIFS(Form127_Raw!$A$2:$A$1000,$A16,Form127_Raw!$F$2:$F$1000,">=2019",Form127_Raw!$F$2:$F$1000,"<=2024",Form127_Raw!$K$2:$K$1000,0)+COUNTIFS(Form127_Raw!$A$2:$A$1000,$A16,Form127_Raw!$F$2:$F$1000,">=2019",Form127_Raw!$F$2:$F$1000,"<=2024",Form127_Raw!$L$2:$L$1000,0)+COUNTIFS(Form127_Raw!$A$2:$A$1000,$A16,Form127_Raw!$F$2:$F$1000,">=2019",Form127_Raw!$F$2:$F$1000,"<=2024",Form127_Raw!$P$2:$P$1000,0) -> 0 | R16: =O16*0.6+P16*0.4 -> 1 | S16: =(COUNTIFS(Form127_Raw!$A$2:$A$1000,$A16,Form127_Raw!$F$2:$F$1000,">=2019",Form127_Raw!$F$2:$F$1000,"<=2024",Form127_Raw!$I$2:$I$1000,"<>")+COUNTIFS(Form127_Raw!$A$2:$A$1000,$A16,Form127_Raw!$F$2:$F$1000,">=2019",Form127_Raw!$F$2:$F$1000,"<=2024",Form127_Raw!$J$2:$J$1000,"<>")+COUNTIFS(Form127_Raw!$A$2:$A$1000,$A16,Form127_Raw!$F$2:$F$1000,">=2019",Form127_Raw!$F$2:$F$1000,"<=2024",Form127_Raw!$O$2:$O$1000,"<>")+COUNTIFS(Form127_Raw!$A$2:$A$1000,$A16,Form127_Raw!$F$2:$F$1000,">=2019",Form127_Raw!$F$2:$F$1000,"<=2024",Form127_Raw!$Q$2:$Q$1000,"<>")+COUNTIFS(Form127_Raw!$A$2:$A$1000,$A16,Form127_Raw!$F$2:$F$1000,">=2019",Form127_Raw!$F$2:$F$1000,"<=2024",Form127_Raw!$R$2:$R$1000,"<>"))/30 -> 0 | T16: =IF(D16=0,"Not Loaded",IF(R16>=0.9,IF(S16=1,"Ready for Final Selection","Excellent - FAA Backfill Pending"),IF(R16>=0.8,"Good - Review Missing Fields",IF(R16>=0.7,"Manual Review","Exclude / Incomplete")))) -> Excellent - FAA Backfill Pending
A17: =Airport_Master!A10 -> MCO | B17: =Airport_Master!B10 -> Orlando International | C17: =Airport_Master!E10 -> Large | D17: =COUNTIFS(Form127_Raw!$A$2:$A$1000,$A17,Form127_Raw!$F$2:$F$1000,">=2019",Form127_Raw!$F$2:$F$1000,"<=2024") -> 6 | E17: =D17/6 -> 1 | F17: =COUNTIFS(Form127_Raw!$A$2:$A$1000,$A17,Form127_Raw!$F$2:$F$1000,">=2019",Form127_Raw!$F$2:$F$1000,"<=2024",Form127_Raw!$G$2:$G$1000,"<>") -> 6 | G17: =COUNTIFS(Form127_Raw!$A$2:$A$1000,$A17,Form127_Raw!$F$2:$F$1000,">=2019",Form127_Raw!$F$2:$F$1000,"<=2024",Form127_Raw!$H$2:$H$1000,"<>") -> 6 | H17: =COUNTIFS(Form127_Raw!$A$2:$A$1000,$A17,Form127_Raw!$F$2:$F$1000,">=2019",Form127_Raw!$F$2:$F$1000,"<=2024",Form127_Raw!$S$2:$S$1000,"<>") -> 6 | I17: =COUNTIFS(Form127_Raw!$A$2:$A$1000,$A17,Form127_Raw!$F$2:$F$1000,">=2019",Form127_Raw!$F$2:$F$1000,"<=2024",Form127_Raw!$T$2:$T$1000,"<>") -> 6 | J17: =COUNTIFS(Form127_Raw!$A$2:$A$1000,$A17,Form127_Raw!$F$2:$F$1000,">=2019",Form127_Raw!$F$2:$F$1000,"<=2024",Form127_Raw!$N$2:$N$1000,"<>") -> 6 | K17: =COUNTIFS(Form127_Raw!$A$2:$A$1000,$A17,Form127_Raw!$F$2:$F$1000,">=2019",Form127_Raw!$F$2:$F$1000,"<=2024",Form127_Raw!$M$2:$M$1000,"<>") -> 6 | L17: =COUNTIFS(Form127_Raw!$A$2:$A$1000,$A17,Form127_Raw!$F$2:$F$1000,">=2019",Form127_Raw!$F$2:$F$1000,"<=2024",Form127_Raw!$K$2:$K$1000,"<>") -> 6 | M17: =COUNTIFS(Form127_Raw!$A$2:$A$1000,$A17,Form127_Raw!$F$2:$F$1000,">=2019",Form127_Raw!$F$2:$F$1000,"<=2024",Form127_Raw!$L$2:$L$1000,"<>") -> 6 | N17: =COUNTIFS(Form127_Raw!$A$2:$A$1000,$A17,Form127_Raw!$F$2:$F$1000,">=2019",Form127_Raw!$F$2:$F$1000,"<=2024",Form127_Raw!$P$2:$P$1000,"<>") -> 6 | O17: =SUM(F17:I17)/24 -> 1 | P17: =SUM(J17:N17)/30 -> 1 | Q17: =COUNTIFS(Form127_Raw!$A$2:$A$1000,$A17,Form127_Raw!$F$2:$F$1000,">=2019",Form127_Raw!$F$2:$F$1000,"<=2024",Form127_Raw!$N$2:$N$1000,0)+COUNTIFS(Form127_Raw!$A$2:$A$1000,$A17,Form127_Raw!$F$2:$F$1000,">=2019",Form127_Raw!$F$2:$F$1000,"<=2024",Form127_Raw!$M$2:$M$1000,0)+COUNTIFS(Form127_Raw!$A$2:$A$1000,$A17,Form127_Raw!$F$2:$F$1000,">=2019",Form127_Raw!$F$2:$F$1000,"<=2024",Form127_Raw!$K$2:$K$1000,0)+COUNTIFS(Form127_Raw!$A$2:$A$1000,$A17,Form127_Raw!$F$2:$F$1000,">=2019",Form127_Raw!$F$2:$F$1000,"<=2024",Form127_Raw!$L$2:$L$1000,0)+COUNTIFS(Form127_Raw!$A$2:$A$1000,$A17,Form127_Raw!$F$2:$F$1000,">=2019",Form127_Raw!$F$2:$F$1000,"<=2024",Form127_Raw!$P$2:$P$1000,0) -> 0 | R17: =O17*0.6+P17*0.4 -> 1 | S17: =(COUNTIFS(Form127_Raw!$A$2:$A$1000,$A17,Form127_Raw!$F$2:$F$1000,">=2019",Form127_Raw!$F$2:$F$1000,"<=2024",Form127_Raw!$I$2:$I$1000,"<>")+COUNTIFS(Form127_Raw!$A$2:$A$1000,$A17,Form127_Raw!$F$2:$F$1000,">=2019",Form127_Raw!$F$2:$F$1000,"<=2024",Form127_Raw!$J$2:$J$1000,"<>")+COUNTIFS(Form127_Raw!$A$2:$A$1000,$A17,Form127_Raw!$F$2:$F$1000,">=2019",Form127_Raw!$F$2:$F$1000,"<=2024",Form127_Raw!$O$2:$O$1000,"<>")+COUNTIFS(Form127_Raw!$A$2:$A$1000,$A17,Form127_Raw!$F$2:$F$1000,">=2019",Form127_Raw!$F$2:$F$1000,"<=2024",Form127_Raw!$Q$2:$Q$1000,"<>")+COUNTIFS(Form127_Raw!$A$2:$A$1000,$A17,Form127_Raw!$F$2:$F$1000,">=2019",Form127_Raw!$F$2:$F$1000,"<=2024",Form127_Raw!$R$2:$R$1000,"<>"))/30 -> 0 | T17: =IF(D17=0,"Not Loaded",IF(R17>=0.9,IF(S17=1,"Ready for Final Selection","Excellent - FAA Backfill Pending"),IF(R17>=0.8,"Good - Review Missing Fields",IF(R17>=0.7,"Manual Review","Exclude / Incomplete")))) -> Excellent - FAA Backfill Pending
A18: =Airport_Master!A11 -> MIA | B18: =Airport_Master!B11 -> Miami International | C18: =Airport_Master!E11 -> Large | D18: =COUNTIFS(Form127_Raw!$A$2:$A$1000,$A18,Form127_Raw!$F$2:$F$1000,">=2019",Form127_Raw!$F$2:$F$1000,"<=2024") -> 6 | E18: =D18/6 -> 1 | F18: =COUNTIFS(Form127_Raw!$A$2:$A$1000,$A18,Form127_Raw!$F$2:$F$1000,">=2019",Form127_Raw!$F$2:$F$1000,"<=2024",Form127_Raw!$G$2:$G$1000,"<>") -> 6 | G18: =COUNTIFS(Form127_Raw!$A$2:$A$1000,$A18,Form127_Raw!$F$2:$F$1000,">=2019",Form127_Raw!$F$2:$F$1000,"<=2024",Form127_Raw!$H$2:$H$1000,"<>") -> 6 | H18: =COUNTIFS(Form127_Raw!$A$2:$A$1000,$A18,Form127_Raw!$F$2:$F$1000,">=2019",Form127_Raw!$F$2:$F$1000,"<=2024",Form127_Raw!$S$2:$S$1000,"<>") -> 6 | I18: =COUNTIFS(Form127_Raw!$A$2:$A$1000,$A18,Form127_Raw!$F$2:$F$1000,">=2019",Form127_Raw!$F$2:$F$1000,"<=2024",Form127_Raw!$T$2:$T$1000,"<>") -> 6 | J18: =COUNTIFS(Form127_Raw!$A$2:$A$1000,$A18,Form127_Raw!$F$2:$F$1000,">=2019",Form127_Raw!$F$2:$F$1000,"<=2024",Form127_Raw!$N$2:$N$1000,"<>") -> 6 | K18: =COUNTIFS(Form127_Raw!$A$2:$A$1000,$A18,Form127_Raw!$F$2:$F$1000,">=2019",Form127_Raw!$F$2:$F$1000,"<=2024",Form127_Raw!$M$2:$M$1000,"<>") -> 6 | L18: =COUNTIFS(Form127_Raw!$A$2:$A$1000,$A18,Form127_Raw!$F$2:$F$1000,">=2019",Form127_Raw!$F$2:$F$1000,"<=2024",Form127_Raw!$K$2:$K$1000,"<>") -> 6 | M18: =COUNTIFS(Form127_Raw!$A$2:$A$1000,$A18,Form127_Raw!$F$2:$F$1000,">=2019",Form127_Raw!$F$2:$F$1000,"<=2024",Form127_Raw!$L$2:$L$1000,"<>") -> 6 | N18: =COUNTIFS(Form127_Raw!$A$2:$A$1000,$A18,Form127_Raw!$F$2:$F$1000,">=2019",Form127_Raw!$F$2:$F$1000,"<=2024",Form127_Raw!$P$2:$P$1000,"<>") -> 6 | O18: =SUM(F18:I18)/24 -> 1 | P18: =SUM(J18:N18)/30 -> 1 | Q18: =COUNTIFS(Form127_Raw!$A$2:$A$1000,$A18,Form127_Raw!$F$2:$F$1000,">=2019",Form127_Raw!$F$2:$F$1000,"<=2024",Form127_Raw!$N$2:$N$1000,0)+COUNTIFS(Form127_Raw!$A$2:$A$1000,$A18,Form127_Raw!$F$2:$F$1000,">=2019",Form127_Raw!$F$2:$F$1000,"<=2024",Form127_Raw!$M$2:$M$1000,0)+COUNTIFS(Form127_Raw!$A$2:$A$1000,$A18,Form127_Raw!$F$2:$F$1000,">=2019",Form127_Raw!$F$2:$F$1000,"<=2024",Form127_Raw!$K$2:$K$1000,0)+COUNTIFS(Form127_Raw!$A$2:$A$1000,$A18,Form127_Raw!$F$2:$F$1000,">=2019",Form127_Raw!$F$2:$F$1000,"<=2024",Form127_Raw!$L$2:$L$1000,0)+COUNTIFS(Form127_Raw!$A$2:$A$1000,$A18,Form127_Raw!$F$2:$F$1000,">=2019",Form127_Raw!$F$2:$F$1000,"<=2024",Form127_Raw!$P$2:$P$1000,0) -> 0 | R18: =O18*0.6+P18*0.4 -> 1 | S18: =(COUNTIFS(Form127_Raw!$A$2:$A$1000,$A18,Form127_Raw!$F$2:$F$1000,">=2019",Form127_Raw!$F$2:$F$1000,"<=2024",Form127_Raw!$I$2:$I$1000,"<>")+COUNTIFS(Form127_Raw!$A$2:$A$1000,$A18,Form127_Raw!$F$2:$F$1000,">=2019",Form127_Raw!$F$2:$F$1000,"<=2024",Form127_Raw!$J$2:$J$1000,"<>")+COUNTIFS(Form127_Raw!$A$2:$A$1000,$A18,Form127_Raw!$F$2:$F$1000,">=2019",Form127_Raw!$F$2:$F$1000,"<=2024",Form127_Raw!$O$2:$O$1000,"<>")+COUNTIFS(Form127_Raw!$A$2:$A$1000,$A18,Form127_Raw!$F$2:$F$1000,">=2019",Form127_Raw!$F$2:$F$1000,"<=2024",Form127_Raw!$Q$2:$Q$1000,"<>")+COUNTIFS(Form127_Raw!$A$2:$A$1000,$A18,Form127_Raw!$F$2:$F$1000,">=2019",Form127_Raw!$F$2:$F$1000,"<=2024",Form127_Raw!$R$2:$R$1000,"<>"))/30 -> 0 | T18: =IF(D18=0,"Not Loaded",IF(R18>=0.9,IF(S18=1,"Ready for Final Selection","Excellent - FAA Backfill Pending"),IF(R18>=0.8,"Good - Review Missing Fields",IF(R18>=0.7,"Manual Review","Exclude / Incomplete")))) -> Excellent - FAA Backfill Pending
A19: =Airport_Master!A12 -> PHX | B19: =Airport_Master!B12 -> Phoenix Sky Harbor International | C19: =Airport_Master!E12 -> Large | D19: =COUNTIFS(Form127_Raw!$A$2:$A$1000,$A19,Form127_Raw!$F$2:$F$1000,">=2019",Form127_Raw!$F$2:$F$1000,"<=2024") -> 6 | E19: =D19/6 -> 1 | F19: =COUNTIFS(Form127_Raw!$A$2:$A$1000,$A19,Form127_Raw!$F$2:$F$1000,">=2019",Form127_Raw!$F$2:$F$1000,"<=2024",Form127_Raw!$G$2:$G$1000,"<>") -> 6 | G19: =COUNTIFS(Form127_Raw!$A$2:$A$1000,$A19,Form127_Raw!$F$2:$F$1000,">=2019",Form127_Raw!$F$2:$F$1000,"<=2024",Form127_Raw!$H$2:$H$1000,"<>") -> 6 | H19: =COUNTIFS(Form127_Raw!$A$2:$A$1000,$A19,Form127_Raw!$F$2:$F$1000,">=2019",Form127_Raw!$F$2:$F$1000,"<=2024",Form127_Raw!$S$2:$S$1000,"<>") -> 6 | I19: =COUNTIFS(Form127_Raw!$A$2:$A$1000,$A19,Form127_Raw!$F$2:$F$1000,">=2019",Form127_Raw!$F$2:$F$1000,"<=2024",Form127_Raw!$T$2:$T$1000,"<>") -> 6 | J19: =COUNTIFS(Form127_Raw!$A$2:$A$1000,$A19,Form127_Raw!$F$2:$F$1000,">=2019",Form127_Raw!$F$2:$F$1000,"<=2024",Form127_Raw!$N$2:$N$1000,"<>") -> 6 | K19: =COUNTIFS(Form127_Raw!$A$2:$A$1000,$A19,Form127_Raw!$F$2:$F$1000,">=2019",Form127_Raw!$F$2:$F$1000,"<=2024",Form127_Raw!$M$2:$M$1000,"<>") -> 6 | L19: =COUNTIFS(Form127_Raw!$A$2:$A$1000,$A19,Form127_Raw!$F$2:$F$1000,">=2019",Form127_Raw!$F$2:$F$1000,"<=2024",Form127_Raw!$K$2:$K$1000,"<>") -> 6 | M19: =COUNTIFS(Form127_Raw!$A$2:$A$1000,$A19,Form127_Raw!$F$2:$F$1000,">=2019",Form127_Raw!$F$2:$F$1000,"<=2024",Form127_Raw!$L$2:$L$1000,"<>") -> 6 | N19: =COUNTIFS(Form127_Raw!$A$2:$A$1000,$A19,Form127_Raw!$F$2:$F$1000,">=2019",Form127_Raw!$F$2:$F$1000,"<=2024",Form127_Raw!$P$2:$P$1000,"<>") -> 6 | O19: =SUM(F19:I19)/24 -> 1 | P19: =SUM(J19:N19)/30 -> 1 | Q19: =COUNTIFS(Form127_Raw!$A$2:$A$1000,$A19,Form127_Raw!$F$2:$F$1000,">=2019",Form127_Raw!$F$2:$F$1000,"<=2024",Form127_Raw!$N$2:$N$1000,0)+COUNTIFS(Form127_Raw!$A$2:$A$1000,$A19,Form127_Raw!$F$2:$F$1000,">=2019",Form127_Raw!$F$2:$F$1000,"<=2024",Form127_Raw!$M$2:$M$1000,0)+COUNTIFS(Form127_Raw!$A$2:$A$1000,$A19,Form127_Raw!$F$2:$F$1000,">=2019",Form127_Raw!$F$2:$F$1000,"<=2024",Form127_Raw!$K$2:$K$1000,0)+COUNTIFS(Form127_Raw!$A$2:$A$1000,$A19,Form127_Raw!$F$2:$F$1000,">=2019",Form127_Raw!$F$2:$F$1000,"<=2024",Form127_Raw!$L$2:$L$1000,0)+COUNTIFS(Form127_Raw!$A$2:$A$1000,$A19,Form127_Raw!$F$2:$F$1000,">=2019",Form127_Raw!$F$2:$F$1000,"<=2024",Form127_Raw!$P$2:$P$1000,0) -> 5 | R19: =O19*0.6+P19*0.4 -> 1 | S19: =(COUNTIFS(Form127_Raw!$A$2:$A$1000,$A19,Form127_Raw!$F$2:$F$1000,">=2019",Form127_Raw!$F$2:$F$1000,"<=2024",Form127_Raw!$I$2:$I$1000,"<>")+COUNTIFS(Form127_Raw!$A$2:$A$1000,$A19,Form127_Raw!$F$2:$F$1000,">=2019",Form127_Raw!$F$2:$F$1000,"<=2024",Form127_Raw!$J$2:$J$1000,"<>")+COUNTIFS(Form127_Raw!$A$2:$A$1000,$A19,Form127_Raw!$F$2:$F$1000,">=2019",Form127_Raw!$F$2:$F$1000,"<=2024",Form127_Raw!$O$2:$O$1000,"<>")+COUNTIFS(Form127_Raw!$A$2:$A$1000,$A19,Form127_Raw!$F$2:$F$1000,">=2019",Form127_Raw!$F$2:$F$1000,"<=2024",Form127_Raw!$Q$2:$Q$1000,"<>")+COUNTIFS(Form127_Raw!$A$2:$A$1000,$A19,Form127_Raw!$F$2:$F$1000,">=2019",Form127_Raw!$F$2:$F$1000,"<=2024",Form127_Raw!$R$2:$R$1000,"<>"))/30 -> 0 | T19: =IF(D19=0,"Not Loaded",IF(R19>=0.9,IF(S19=1,"Ready for Final Selection","Excellent - FAA Backfill Pending"),IF(R19>=0.8,"Good - Review Missing Fields",IF(R19>=0.7,"Manual Review","Exclude / Incomplete")))) -> Excellent - FAA Backfill Pending
A20: =Airport_Master!A13 -> SEA | B20: =Airport_Master!B13 -> Seattle-Tacoma International | C20: =Airport_Master!E13 -> Large | D20: =COUNTIFS(Form127_Raw!$A$2:$A$1000,$A20,Form127_Raw!$F$2:$F$1000,">=2019",Form127_Raw!$F$2:$F$1000,"<=2024") -> 6 | E20: =D20/6 -> 1 | F20: =COUNTIFS(Form127_Raw!$A$2:$A$1000,$A20,Form127_Raw!$F$2:$F$1000,">=2019",Form127_Raw!$F$2:$F$1000,"<=2024",Form127_Raw!$G$2:$G$1000,"<>") -> 6 | G20: =COUNTIFS(Form127_Raw!$A$2:$A$1000,$A20,Form127_Raw!$F$2:$F$1000,">=2019",Form127_Raw!$F$2:$F$1000,"<=2024",Form127_Raw!$H$2:$H$1000,"<>") -> 6 | H20: =COUNTIFS(Form127_Raw!$A$2:$A$1000,$A20,Form127_Raw!$F$2:$F$1000,">=2019",Form127_Raw!$F$2:$F$1000,"<=2024",Form127_Raw!$S$2:$S$1000,"<>") -> 6 | I20: =COUNTIFS(Form127_Raw!$A$2:$A$1000,$A20,Form127_Raw!$F$2:$F$1000,">=2019",Form127_Raw!$F$2:$F$1000,"<=2024",Form127_Raw!$T$2:$T$1000,"<>") -> 6 | J20: =COUNTIFS(Form127_Raw!$A$2:$A$1000,$A20,Form127_Raw!$F$2:$F$1000,">=2019",Form127_Raw!$F$2:$F$1000,"<=2024",Form127_Raw!$N$2:$N$1000,"<>") -> 6 | K20: =COUNTIFS(Form127_Raw!$A$2:$A$1000,$A20,Form127_Raw!$F$2:$F$1000,">=2019",Form127_Raw!$F$2:$F$1000,"<=2024",Form127_Raw!$M$2:$M$1000,"<>") -> 6 | L20: =COUNTIFS(Form127_Raw!$A$2:$A$1000,$A20,Form127_Raw!$F$2:$F$1000,">=2019",Form127_Raw!$F$2:$F$1000,"<=2024",Form127_Raw!$K$2:$K$1000,"<>") -> 6 | M20: =COUNTIFS(Form127_Raw!$A$2:$A$1000,$A20,Form127_Raw!$F$2:$F$1000,">=2019",Form127_Raw!$F$2:$F$1000,"<=2024",Form127_Raw!$L$2:$L$1000,"<>") -> 6 | N20: =COUNTIFS(Form127_Raw!$A$2:$A$1000,$A20,Form127_Raw!$F$2:$F$1000,">=2019",Form127_Raw!$F$2:$F$1000,"<=2024",Form127_Raw!$P$2:$P$1000,"<>") -> 6 | O20: =SUM(F20:I20)/24 -> 1 | P20: =SUM(J20:N20)/30 -> 1 | Q20: =COUNTIFS(Form127_Raw!$A$2:$A$1000,$A20,Form127_Raw!$F$2:$F$1000,">=2019",Form127_Raw!$F$2:$F$1000,"<=2024",Form127_Raw!$N$2:$N$1000,0)+COUNTIFS(Form127_Raw!$A$2:$A$1000,$A20,Form127_Raw!$F$2:$F$1000,">=2019",Form127_Raw!$F$2:$F$1000,"<=2024",Form127_Raw!$M$2:$M$1000,0)+COUNTIFS(Form127_Raw!$A$2:$A$1000,$A20,Form127_Raw!$F$2:$F$1000,">=2019",Form127_Raw!$F$2:$F$1000,"<=2024",Form127_Raw!$K$2:$K$1000,0)+COUNTIFS(Form127_Raw!$A$2:$A$1000,$A20,Form127_Raw!$F$2:$F$1000,">=2019",Form127_Raw!$F$2:$F$1000,"<=2024",Form127_Raw!$L$2:$L$1000,0)+COUNTIFS(Form127_Raw!$A$2:$A$1000,$A20,Form127_Raw!$F$2:$F$1000,">=2019",Form127_Raw!$F$2:$F$1000,"<=2024",Form127_Raw!$P$2:$P$1000,0) -> 0 | R20: =O20*0.6+P20*0.4 -> 1 | S20: =(COUNTIFS(Form127_Raw!$A$2:$A$1000,$A20,Form127_Raw!$F$2:$F$1000,">=2019",Form127_Raw!$F$2:$F$1000,"<=2024",Form127_Raw!$I$2:$I$1000,"<>")+COUNTIFS(Form127_Raw!$A$2:$A$1000,$A20,Form127_Raw!$F$2:$F$1000,">=2019",Form127_Raw!$F$2:$F$1000,"<=2024",Form127_Raw!$J$2:$J$1000,"<>")+COUNTIFS(Form127_Raw!$A$2:$A$1000,$A20,Form127_Raw!$F$2:$F$1000,">=2019",Form127_Raw!$F$2:$F$1000,"<=2024",Form127_Raw!$O$2:$O$1000,"<>")+COUNTIFS(Form127_Raw!$A$2:$A$1000,$A20,Form127_Raw!$F$2:$F$1000,">=2019",Form127_Raw!$F$2:$F$1000,"<=2024",Form127_Raw!$Q$2:$Q$1000,"<>")+COUNTIFS(Form127_Raw!$A$2:$A$1000,$A20,Form127_Raw!$F$2:$F$1000,">=2019",Form127_Raw!$F$2:$F$1000,"<=2024",Form127_Raw!$R$2:$R$1000,"<>"))/30 -> 0 | T20: =IF(D20=0,"Not Loaded",IF(R20>=0.9,IF(S20=1,"Ready for Final Selection","Excellent - FAA Backfill Pending"),IF(R20>=0.8,"Good - Review Missing Fields",IF(R20>=0.7,"Manual Review","Exclude / Incomplete")))) -> Excellent - FAA Backfill Pending
... A71: =Airport_Master!A64 -> BOI | B71: =Airport_Master!B64 -> Boise Air Trml/Gowen Field | C71: =Airport_Master!E64 -> Medium | D71: =COUNTIFS(Form127_Raw!$A$2:$A$1000,$A71,Form127_Raw!$F$2:$F$1000,">=2019",Form127_Raw!$F$2:$F$1000,"<=2024") -> 0 | E71: =D71/6 -> 0 | F71: =COUNTIFS(Form127_Raw!$A$2:$A$1000,$A71,Form127_Raw!$F$2:$F$1000,">=2019",Form127_Raw!$F$2:$F$1000,"<=2024",Form127_Raw!$G$2:$G$1000,"<>") -> 0 | G71: =COUNTIFS(Form127_Raw!$A$2:$A$1000,$A71,Form127_Raw!$F$2:$F$1000,">=2019",Form127_Raw!$F$2:$F$1000,"<=2024",Form127_Raw!$H$2:$H$1000,"<>") -> 0 | H71: =COUNTIFS(Form127_Raw!$A$2:$A$1000,$A71,Form127_Raw!$F$2:$F$1000,">=2019",Form127_Raw!$F$2:$F$1000,"<=2024",Form127_Raw!$S$2:$S$1000,"<>") -> 0 | I71: =COUNTIFS(Form127_Raw!$A$2:$A$1000,$A71,Form127_Raw!$F$2:$F$1000,">=2019",Form127_Raw!$F$2:$F$1000,"<=2024",Form127_Raw!$T$2:$T$1000,"<>") -> 0 | J71: =COUNTIFS(Form127_Raw!$A$2:$A$1000,$A71,Form127_Raw!$F$2:$F$1000,">=2019",Form127_Raw!$F$2:$F$1000,"<=2024",Form127_Raw!$N$2:$N$1000,"<>") -> 0 | K71: =COUNTIFS(Form127_Raw!$A$2:$A$1000,$A71,Form127_Raw!$F$2:$F$1000,">=2019",Form127_Raw!$F$2:$F$1000,"<=2024",Form127_Raw!$M$2:$M$1000,"<>") -> 0 | L71: =COUNTIFS(Form127_Raw!$A$2:$A$1000,$A71,Form127_Raw!$F$2:$F$1000,">=2019",Form127_Raw!$F$2:$F$1000,"<=2024",Form127_Raw!$K$2:$K$1000,"<>") -> 0 | M71: =COUNTIFS(Form127_Raw!$A$2:$A$1000,$A71,Form127_Raw!$F$2:$F$1000,">=2019",Form127_Raw!$F$2:$F$1000,"<=2024",Form127_Raw!$L$2:$L$1000,"<>") -> 0 | N71: =COUNTIFS(Form127_Raw!$A$2:$A$1000,$A71,Form127_Raw!$F$2:$F$1000,">=2019",Form127_Raw!$F$2:$F$1000,"<=2024",Form127_Raw!$P$2:$P$1000,"<>") -> 0 | O71: =SUM(F71:I71)/24 -> 0 | P71: =SUM(J71:N71)/30 -> 0 | Q71: =COUNTIFS(Form127_Raw!$A$2:$A$1000,$A71,Form127_Raw!$F$2:$F$1000,">=2019",Form127_Raw!$F$2:$F$1000,"<=2024",Form127_Raw!$N$2:$N$1000,0)+COUNTIFS(Form127_Raw!$A$2:$A$1000,$A71,Form127_Raw!$F$2:$F$1000,">=2019",Form127_Raw!$F$2:$F$1000,"<=2024",Form127_Raw!$M$2:$M$1000,0)+COUNTIFS(Form127_Raw!$A$2:$A$1000,$A71,Form127_Raw!$F$2:$F$1000,">=2019",Form127_Raw!$F$2:$F$1000,"<=2024",Form127_Raw!$K$2:$K$1000,0)+COUNTIFS(Form127_Raw!$A$2:$A$1000,$A71,Form127_Raw!$F$2:$F$1000,">=2019",Form127_Raw!$F$2:$F$1000,"<=2024",Form127_Raw!$L$2:$L$1000,0)+COUNTIFS(Form127_Raw!$A$2:$A$1000,$A71,Form127_Raw!$F$2:$F$1000,">=2019",Form127_Raw!$F$2:$F$1000,"<=2024",Form127_Raw!$P$2:$P$1000,0) -> 0 | R71: =O71*0.6+P71*0.4 -> 0 | S71: =(COUNTIFS(Form127_Raw!$A$2:$A$1000,$A71,Form127_Raw!$F$2:$F$1000,">=2019",Form127_Raw!$F$2:$F$1000,"<=2024",Form127_Raw!$I$2:$I$1000,"<>")+COUNTIFS(Form127_Raw!$A$2:$A$1000,$A71,Form127_Raw!$F$2:$F$1000,">=2019",Form127_Raw!$F$2:$F$1000,"<=2024",Form127_Raw!$J$2:$J$1000,"<>")+COUNTIFS(Form127_Raw!$A$2:$A$1000,$A71,Form127_Raw!$F$2:$F$1000,">=2019",Form127_Raw!$F$2:$F$1000,"<=2024",Form127_Raw!$O$2:$O$1000,"<>")+COUNTIFS(Form127_Raw!$A$2:$A$1000,$A71,Form127_Raw!$F$2:$F$1000,">=2019",Form127_Raw!$F$2:$F$1000,"<=2024",Form127_Raw!$Q$2:$Q$1000,"<>")+COUNTIFS(Form127_Raw!$A$2:$A$1000,$A71,Form127_Raw!$F$2:$F$1000,">=2019",Form127_Raw!$F$2:$F$1000,"<=2024",Form127_Raw!$R$2:$R$1000,"<>"))/30 -> 0 | T71: =IF(D71=0,"Not Loaded",IF(R71>=0.9,IF(S71=1,"Ready for Final Selection","Excellent - FAA Backfill Pending"),IF(R71>=0.8,"Good - Review Missing Fields",IF(R71>=0.7,"Manual Review","Exclude / Incomplete")))) -> Not Loaded
A74: Threshold | B74: Score Range | C74: Meaning | D74: Action | E74: Pending FAA Rule | F74: Zero Rule
A75: Excellent | B75: 90–100% | C75: Strong current data coverage | D75: Keep for final shortlist | E75: Backfill still required before final KPI build | F75: Zero is present, not missing
A76: Good | B76: 80–89% | C76: Minor missingness | D76: Review field gaps | E76: Backfill still required | F76: Review repeated zeros
A77: Manual Review | B77: 70–79% | C77: Material missingness | D77: Inspect manually before keeping | E77: Backfill still required | F77: Check reporting structure
A78: Exclude | B78: <70% | C78: Insufficient current coverage | D78: Remove unless strategically essential | E78: Do not rely on incomplete total commercial fields | F78: N/A

Sheet Working_Set_25
A1: Airport_Code | B1: Airport_Name | C1: Hub_Size | D1: Years_Loaded | E1: Current_Completeness_% | F1: Zero_Flags | G1: FAA_Backfill_% | H1: Status
A2: ="ATL" -> ATL | B2: =IFERROR(INDEX(Data_Quality!$B$9:$B$71,MATCH(A2,Data_Quality!$A$9:$A$71,0)),"") -> Hartsfield/Jackson Atlanta International | C2: =IFERROR(INDEX(Data_Quality!$C$9:$C$71,MATCH(A2,Data_Quality!$A$9:$A$71,0)),"") -> Large | D2: =IFERROR(INDEX(Data_Quality!$D$9:$D$71,MATCH(A2,Data_Quality!$A$9:$A$71,0)),0) -> 6 | E2: =IFERROR(INDEX(Data_Quality!$R$9:$R$71,MATCH(A2,Data_Quality!$A$9:$A$71,0)),0) -> 1 | F2: =IFERROR(INDEX(Data_Quality!$Q$9:$Q$71,MATCH(A2,Data_Quality!$A$9:$A$71,0)),0) -> 0 | G2: =IFERROR(INDEX(Data_Quality!$S$9:$S$71,MATCH(A2,Data_Quality!$A$9:$A$71,0)),0) -> 0 | H2: =IFERROR(INDEX(Data_Quality!$T$9:$T$71,MATCH(A2,Data_Quality!$A$9:$A$71,0)),"") -> Excellent - FAA Backfill Pending
A3: ="DFW" -> DFW | B3: =IFERROR(INDEX(Data_Quality!$B$9:$B$71,MATCH(A3,Data_Quality!$A$9:$A$71,0)),"") -> Dallas-Fort Worth International | C3: =IFERROR(INDEX(Data_Quality!$C$9:$C$71,MATCH(A3,Data_Quality!$A$9:$A$71,0)),"") -> Large | D3: =IFERROR(INDEX(Data_Quality!$D$9:$D$71,MATCH(A3,Data_Quality!$A$9:$A$71,0)),0) -> 6 | E3: =IFERROR(INDEX(Data_Quality!$R$9:$R$71,MATCH(A3,Data_Quality!$A$9:$A$71,0)),0) -> 1 | F3: =IFERROR(INDEX(Data_Quality!$Q$9:$Q$71,MATCH(A3,Data_Quality!$A$9:$A$71,0)),0) -> 0 | G3: =IFERROR(INDEX(Data_Quality!$S$9:$S$71,MATCH(A3,Data_Quality!$A$9:$A$71,0)),0) -> 0 | H3: =IFERROR(INDEX(Data_Quality!$T$9:$T$71,MATCH(A3,Data_Quality!$A$9:$A$71,0)),"") -> Excellent - FAA Backfill Pending
A4: ="LAX" -> LAX | B4: =IFERROR(INDEX(Data_Quality!$B$9:$B$71,MATCH(A4,Data_Quality!$A$9:$A$71,0)),"") -> Los Angeles International | C4: =IFERROR(INDEX(Data_Quality!$C$9:$C$71,MATCH(A4,Data_Quality!$A$9:$A$71,0)),"") -> Large | D4: =IFERROR(INDEX(Data_Quality!$D$9:$D$71,MATCH(A4,Data_Quality!$A$9:$A$71,0)),0) -> 6 | E4: =IFERROR(INDEX(Data_Quality!$R$9:$R$71,MATCH(A4,Data_Quality!$A$9:$A$71,0)),0) -> 1 | F4: =IFERROR(INDEX(Data_Quality!$Q$9:$Q$71,MATCH(A4,Data_Quality!$A$9:$A$71,0)),0) -> 0 | G4: =IFERROR(INDEX(Data_Quality!$S$9:$S$71,MATCH(A4,Data_Quality!$A$9:$A$71,0)),0) -> 0 | H4: =IFERROR(INDEX(Data_Quality!$T$9:$T$71,MATCH(A4,Data_Quality!$A$9:$A$71,0)),"") -> Excellent - FAA Backfill Pending
A5: ="SEA" -> SEA | B5: =IFERROR(INDEX(Data_Quality!$B$9:$B$71,MATCH(A5,Data_Quality!$A$9:$A$71,0)),"") -> Seattle-Tacoma International | C5: =IFERROR(INDEX(Data_Quality!$C$9:$C$71,MATCH(A5,Data_Quality!$A$9:$A$71,0)),"") -> Large | D5: =IFERROR(INDEX(Data_Quality!$D$9:$D$71,MATCH(A5,Data_Quality!$A$9:$A$71,0)),0) -> 6 | E5: =IFERROR(INDEX(Data_Quality!$R$9:$R$71,MATCH(A5,Data_Quality!$A$9:$A$71,0)),0) -> 1 | F5: =IFERROR(INDEX(Data_Quality!$Q$9:$Q$71,MATCH(A5,Data_Quality!$A$9:$A$71,0)),0) -> 0 | G5: =IFERROR(INDEX(Data_Quality!$S$9:$S$71,MATCH(A5,Data_Quality!$A$9:$A$71,0)),0) -> 0 | H5: =IFERROR(INDEX(Data_Quality!$T$9:$T$71,MATCH(A5,Data_Quality!$A$9:$A$71,0)),"") -> Excellent - FAA Backfill Pending
A6: ="CLE" -> CLE | B6: =IFERROR(INDEX(Data_Quality!$B$9:$B$71,MATCH(A6,Data_Quality!$A$9:$A$71,0)),"") -> Cleveland-Hopkins International | C6: =IFERROR(INDEX(Data_Quality!$C$9:$C$71,MATCH(A6,Data_Quality!$A$9:$A$71,0)),"") -> Medium | D6: =IFERROR(INDEX(Data_Quality!$D$9:$D$71,MATCH(A6,Data_Quality!$A$9:$A$71,0)),0) -> 6 | E6: =IFERROR(INDEX(Data_Quality!$R$9:$R$71,MATCH(A6,Data_Quality!$A$9:$A$71,0)),0) -> 1 | F6: =IFERROR(INDEX(Data_Quality!$Q$9:$Q$71,MATCH(A6,Data_Quality!$A$9:$A$71,0)),0) -> 0 | G6: =IFERROR(INDEX(Data_Quality!$S$9:$S$71,MATCH(A6,Data_Quality!$A$9:$A$71,0)),0) -> 0 | H6: =IFERROR(INDEX(Data_Quality!$T$9:$T$71,MATCH(A6,Data_Quality!$A$9:$A$71,0)),"") -> Excellent - FAA Backfill Pending
A7: ="DEN" -> DEN | B7: =IFERROR(INDEX(Data_Quality!$B$9:$B$71,MATCH(A7,Data_Quality!$A$9:$A$71,0)),"") -> Denver International | C7: =IFERROR(INDEX(Data_Quality!$C$9:$C$71,MATCH(A7,Data_Quality!$A$9:$A$71,0)),"") -> Large | D7: =IFERROR(INDEX(Data_Quality!$D$9:$D$71,MATCH(A7,Data_Quality!$A$9:$A$71,0)),0) -> 6 | E7: =IFERROR(INDEX(Data_Quality!$R$9:$R$71,MATCH(A7,Data_Quality!$A$9:$A$71,0)),0) -> 1 | F7: =IFERROR(INDEX(Data_Quality!$Q$9:$Q$71,MATCH(A7,Data_Quality!$A$9:$A$71,0)),0) -> 0 | G7: =IFERROR(INDEX(Data_Quality!$S$9:$S$71,MATCH(A7,Data_Quality!$A$9:$A$71,0)),0) -> 0 | H7: =IFERROR(INDEX(Data_Quality!$T$9:$T$71,MATCH(A7,Data_Quality!$A$9:$A$71,0)),"") -> Excellent - FAA Backfill Pending
A8: ="ORD" -> ORD | B8: =IFERROR(INDEX(Data_Quality!$B$9:$B$71,MATCH(A8,Data_Quality!$A$9:$A$71,0)),"") -> Chicago O'Hare International | C8: =IFERROR(INDEX(Data_Quality!$C$9:$C$71,MATCH(A8,Data_Quality!$A$9:$A$71,0)),"") -> Large | D8: =IFERROR(INDEX(Data_Quality!$D$9:$D$71,MATCH(A8,Data_Quality!$A$9:$A$71,0)),0) -> 6 | E8: =IFERROR(INDEX(Data_Quality!$R$9:$R$71,MATCH(A8,Data_Quality!$A$9:$A$71,0)),0) -> 1 | F8: =IFERROR(INDEX(Data_Quality!$Q$9:$Q$71,MATCH(A8,Data_Quality!$A$9:$A$71,0)),0) -> 0 | G8: =IFERROR(INDEX(Data_Quality!$S$9:$S$71,MATCH(A8,Data_Quality!$A$9:$A$71,0)),0) -> 0 | H8: =IFERROR(INDEX(Data_Quality!$T$9:$T$71,MATCH(A8,Data_Quality!$A$9:$A$71,0)),"") -> Excellent - FAA Backfill Pending
A9: ="LAS" -> LAS | B9: =IFERROR(INDEX(Data_Quality!$B$9:$B$71,MATCH(A9,Data_Quality!$A$9:$A$71,0)),"") -> Harry Reid International | C9: =IFERROR(INDEX(Data_Quality!$C$9:$C$71,MATCH(A9,Data_Quality!$A$9:$A$71,0)),"") -> Large | D9: =IFERROR(INDEX(Data_Quality!$D$9:$D$71,MATCH(A9,Data_Quality!$A$9:$A$71,0)),0) -> 6 | E9: =IFERROR(INDEX(Data_Quality!$R$9:$R$71,MATCH(A9,Data_Quality!$A$9:$A$71,0)),0) -> 1 | F9: =IFERROR(INDEX(Data_Quality!$Q$9:$Q$71,MATCH(A9,Data_Quality!$A$9:$A$71,0)),0) -> 0 | G9: =IFERROR(INDEX(Data_Quality!$S$9:$S$71,MATCH(A9,Data_Quality!$A$9:$A$71,0)),0) -> 0 | H9: =IFERROR(INDEX(Data_Quality!$T$9:$T$71,MATCH(A9,Data_Quality!$A$9:$A$71,0)),"") -> Excellent - FAA Backfill Pending
A10: ="PHX" -> PHX | B10: =IFERROR(INDEX(Data_Quality!$B$9:$B$71,MATCH(A10,Data_Quality!$A$9:$A$71,0)),"") -> Phoenix Sky Harbor International | C10: =IFERROR(INDEX(Data_Quality!$C$9:$C$71,MATCH(A10,Data_Quality!$A$9:$A$71,0)),"") -> Large | D10: =IFERROR(INDEX(Data_Quality!$D$9:$D$71,MATCH(A10,Data_Quality!$A$9:$A$71,0)),0) -> 6 | E10: =IFERROR(INDEX(Data_Quality!$R$9:$R$71,MATCH(A10,Data_Quality!$A$9:$A$71,0)),0) -> 1 | F10: =IFERROR(INDEX(Data_Quality!$Q$9:$Q$71,MATCH(A10,Data_Quality!$A$9:$A$71,0)),0) -> 5 | G10: =IFERROR(INDEX(Data_Quality!$S$9:$S$71,MATCH(A10,Data_Quality!$A$9:$A$71,0)),0) -> 0 | H10: =IFERROR(INDEX(Data_Quality!$T$9:$T$71,MATCH(A10,Data_Quality!$A$9:$A$71,0)),"") -> Excellent - FAA Backfill Pending
A11: ="MIA" -> MIA | B11: =IFERROR(INDEX(Data_Quality!$B$9:$B$71,MATCH(A11,Data_Quality!$A$9:$A$71,0)),"") -> Miami International | C11: =IFERROR(INDEX(Data_Quality!$C$9:$C$71,MATCH(A11,Data_Quality!$A$9:$A$71,0)),"") -> Large | D11: =IFERROR(INDEX(Data_Quality!$D$9:$D$71,MATCH(A11,Data_Quality!$A$9:$A$71,0)),0) -> 6 | E11: =IFERROR(INDEX(Data_Quality!$R$9:$R$71,MATCH(A11,Data_Quality!$A$9:$A$71,0)),0) -> 1 | F11: =IFERROR(INDEX(Data_Quality!$Q$9:$Q$71,MATCH(A11,Data_Quality!$A$9:$A$71,0)),0) -> 0 | G11: =IFERROR(INDEX(Data_Quality!$S$9:$S$71,MATCH(A11,Data_Quality!$A$9:$A$71,0)),0) -> 0 | H11: =IFERROR(INDEX(Data_Quality!$T$9:$T$71,MATCH(A11,Data_Quality!$A$9:$A$71,0)),"") -> Excellent - FAA Backfill Pending
A12: ="SFO" -> SFO | B12: =IFERROR(INDEX(Data_Quality!$B$9:$B$71,MATCH(A12,Data_Quality!$A$9:$A$71,0)),"") -> San Francisco International | C12: =IFERROR(INDEX(Data_Quality!$C$9:$C$71,MATCH(A12,Data_Quality!$A$9:$A$71,0)),"") -> Large | D12: =IFERROR(INDEX(Data_Quality!$D$9:$D$71,MATCH(A12,Data_Quality!$A$9:$A$71,0)),0) -> 6 | E12: =IFERROR(INDEX(Data_Quality!$R$9:$R$71,MATCH(A12,Data_Quality!$A$9:$A$71,0)),0) -> 1 | F12: =IFERROR(INDEX(Data_Quality!$Q$9:$Q$71,MATCH(A12,Data_Quality!$A$9:$A$71,0)),0) -> 0 | G12: =IFERROR(INDEX(Data_Quality!$S$9:$S$71,MATCH(A12,Data_Quality!$A$9:$A$71,0)),0) -> 0 | H12: =IFERROR(INDEX(Data_Quality!$T$9:$T$71,MATCH(A12,Data_Quality!$A$9:$A$71,0)),"") -> Excellent - FAA Backfill Pending
A13: ="IAH" -> IAH | B13: =IFERROR(INDEX(Data_Quality!$B$9:$B$71,MATCH(A13,Data_Quality!$A$9:$A$71,0)),"") -> George Bush Intcntl/Houston | C13: =IFERROR(INDEX(Data_Quality!$C$9:$C$71,MATCH(A13,Data_Quality!$A$9:$A$71,0)),"") -> Large | D13: =IFERROR(INDEX(Data_Quality!$D$9:$D$71,MATCH(A13,Data_Quality!$A$9:$A$71,0)),0) -> 6 | E13: =IFERROR(INDEX(Data_Quality!$R$9:$R$71,MATCH(A13,Data_Quality!$A$9:$A$71,0)),0) -> 1 | F13: =IFERROR(INDEX(Data_Quality!$Q$9:$Q$71,MATCH(A13,Data_Quality!$A$9:$A$71,0)),0) -> 0 | G13: =IFERROR(INDEX(Data_Quality!$S$9:$S$71,MATCH(A13,Data_Quality!$A$9:$A$71,0)),0) -> 0 | H13: =IFERROR(INDEX(Data_Quality!$T$9:$T$71,MATCH(A13,Data_Quality!$A$9:$A$71,0)),"") -> Excellent - FAA Backfill Pending
A14: ="MCO" -> MCO | B14: =IFERROR(INDEX(Data_Quality!$B$9:$B$71,MATCH(A14,Data_Quality!$A$9:$A$71,0)),"") -> Orlando International | C14: =IFERROR(INDEX(Data_Quality!$C$9:$C$71,MATCH(A14,Data_Quality!$A$9:$A$71,0)),"") -> Large | D14: =IFERROR(INDEX(Data_Quality!$D$9:$D$71,MATCH(A14,Data_Quality!$A$9:$A$71,0)),0) -> 6 | E14: =IFERROR(INDEX(Data_Quality!$R$9:$R$71,MATCH(A14,Data_Quality!$A$9:$A$71,0)),0) -> 1 | F14: =IFERROR(INDEX(Data_Quality!$Q$9:$Q$71,MATCH(A14,Data_Quality!$A$9:$A$71,0)),0) -> 0 | G14: =IFERROR(INDEX(Data_Quality!$S$9:$S$71,MATCH(A14,Data_Quality!$A$9:$A$71,0)),0) -> 0 | H14: =IFERROR(INDEX(Data_Quality!$T$9:$T$71,MATCH(A14,Data_Quality!$A$9:$A$71,0)),"") -> Excellent - FAA Backfill Pending
A15: ="DTW" -> DTW | B15: =IFERROR(INDEX(Data_Quality!$B$9:$B$71,MATCH(A15,Data_Quality!$A$9:$A$71,0)),"") -> Detroit Metro Wayne County | C15: =IFERROR(INDEX(Data_Quality!$C$9:$C$71,MATCH(A15,Data_Quality!$A$9:$A$71,0)),"") -> Large | D15: =IFERROR(INDEX(Data_Quality!$D$9:$D$71,MATCH(A15,Data_Quality!$A$9:$A$71,0)),0) -> 6 | E15: =IFERROR(INDEX(Data_Quality!$R$9:$R$71,MATCH(A15,Data_Quality!$A$9:$A$71,0)),0) -> 1 | F15: =IFERROR(INDEX(Data_Quality!$Q$9:$Q$71,MATCH(A15,Data_Quality!$A$9:$A$71,0)),0) -> 0 | G15: =IFERROR(INDEX(Data_Quality!$S$9:$S$71,MATCH(A15,Data_Quality!$A$9:$A$71,0)),0) -> 0 | H15: =IFERROR(INDEX(Data_Quality!$T$9:$T$71,MATCH(A15,Data_Quality!$A$9:$A$71,0)),"") -> Excellent - FAA Backfill Pending
A16: ="BOS" -> BOS | B16: =IFERROR(INDEX(Data_Quality!$B$9:$B$71,MATCH(A16,Data_Quality!$A$9:$A$71,0)),"") -> General Edward Lawrence Logan International | C16: =IFERROR(INDEX(Data_Quality!$C$9:$C$71,MATCH(A16,Data_Quality!$A$9:$A$71,0)),"") -> Large | D16: =IFERROR(INDEX(Data_Quality!$D$9:$D$71,MATCH(A16,Data_Quality!$A$9:$A$71,0)),0) -> 6 | E16: =IFERROR(INDEX(Data_Quality!$R$9:$R$71,MATCH(A16,Data_Quality!$A$9:$A$71,0)),0) -> 1 | F16: =IFERROR(INDEX(Data_Quality!$Q$9:$Q$71,MATCH(A16,Data_Quality!$A$9:$A$71,0)),0) -> 0 | G16: =IFERROR(INDEX(Data_Quality!$S$9:$S$71,MATCH(A16,Data_Quality!$A$9:$A$71,0)),0) -> 0 | H16: =IFERROR(INDEX(Data_Quality!$T$9:$T$71,MATCH(A16,Data_Quality!$A$9:$A$71,0)),"") -> Excellent - FAA Backfill Pending
A17: ="FLL" -> FLL | B17: =IFERROR(INDEX(Data_Quality!$B$9:$B$71,MATCH(A17,Data_Quality!$A$9:$A$71,0)),"") -> Fort Lauderdale/Hollywood International | C17: =IFERROR(INDEX(Data_Quality!$C$9:$C$71,MATCH(A17,Data_Quality!$A$9:$A$71,0)),"") -> Large | D17: =IFERROR(INDEX(Data_Quality!$D$9:$D$71,MATCH(A17,Data_Quality!$A$9:$A$71,0)),0) -> 6 | E17: =IFERROR(INDEX(Data_Quality!$R$9:$R$71,MATCH(A17,Data_Quality!$A$9:$A$71,0)),0) -> 1 | F17: =IFERROR(INDEX(Data_Quality!$Q$9:$Q$71,MATCH(A17,Data_Quality!$A$9:$A$71,0)),0) -> 0 | G17: =IFERROR(INDEX(Data_Quality!$S$9:$S$71,MATCH(A17,Data_Quality!$A$9:$A$71,0)),0) -> 0 | H17: =IFERROR(INDEX(Data_Quality!$T$9:$T$71,MATCH(A17,Data_Quality!$A$9:$A$71,0)),"") -> Excellent - FAA Backfill Pending
A18: ="PHL" -> PHL | B18: =IFERROR(INDEX(Data_Quality!$B$9:$B$71,MATCH(A18,Data_Quality!$A$9:$A$71,0)),"") -> Philadelphia International | C18: =IFERROR(INDEX(Data_Quality!$C$9:$C$71,MATCH(A18,Data_Quality!$A$9:$A$71,0)),"") -> Large | D18: =IFERROR(INDEX(Data_Quality!$D$9:$D$71,MATCH(A18,Data_Quality!$A$9:$A$71,0)),0) -> 6 | E18: =IFERROR(INDEX(Data_Quality!$R$9:$R$71,MATCH(A18,Data_Quality!$A$9:$A$71,0)),0) -> 1 | F18: =IFERROR(INDEX(Data_Quality!$Q$9:$Q$71,MATCH(A18,Data_Quality!$A$9:$A$71,0)),0) -> 0 | G18: =IFERROR(INDEX(Data_Quality!$S$9:$S$71,MATCH(A18,Data_Quality!$A$9:$A$71,0)),0) -> 0 | H18: =IFERROR(INDEX(Data_Quality!$T$9:$T$71,MATCH(A18,Data_Quality!$A$9:$A$71,0)),"") -> Excellent - FAA Backfill Pending
A19: ="MSP" -> MSP | B19: =IFERROR(INDEX(Data_Quality!$B$9:$B$71,MATCH(A19,Data_Quality!$A$9:$A$71,0)),"") -> Minneapolis-St Paul International/Wold-Chamberlain | C19: =IFERROR(INDEX(Data_Quality!$C$9:$C$71,MATCH(A19,Data_Quality!$A$9:$A$71,0)),"") -> Large | D19: =IFERROR(INDEX(Data_Quality!$D$9:$D$71,MATCH(A19,Data_Quality!$A$9:$A$71,0)),0) -> 6 | E19: =IFERROR(INDEX(Data_Quality!$R$9:$R$71,MATCH(A19,Data_Quality!$A$9:$A$71,0)),0) -> 1 | F19: =IFERROR(INDEX(Data_Quality!$Q$9:$Q$71,MATCH(A19,Data_Quality!$A$9:$A$71,0)),0) -> 0 | G19: =IFERROR(INDEX(Data_Quality!$S$9:$S$71,MATCH(A19,Data_Quality!$A$9:$A$71,0)),0) -> 0 | H19: =IFERROR(INDEX(Data_Quality!$T$9:$T$71,MATCH(A19,Data_Quality!$A$9:$A$71,0)),"") -> Excellent - FAA Backfill Pending
A20: ="SLC" -> SLC | B20: =IFERROR(INDEX(Data_Quality!$B$9:$B$71,MATCH(A20,Data_Quality!$A$9:$A$71,0)),"") -> Salt Lake City International | C20: =IFERROR(INDEX(Data_Quality!$C$9:$C$71,MATCH(A20,Data_Quality!$A$9:$A$71,0)),"") -> Large | D20: =IFERROR(INDEX(Data_Quality!$D$9:$D$71,MATCH(A20,Data_Quality!$A$9:$A$71,0)),0) -> 6 | E20: =IFERROR(INDEX(Data_Quality!$R$9:$R$71,MATCH(A20,Data_Quality!$A$9:$A$71,0)),0) -> 1 | F20: =IFERROR(INDEX(Data_Quality!$Q$9:$Q$71,MATCH(A20,Data_Quality!$A$9:$A$71,0)),0) -> 0 | G20: =IFERROR(INDEX(Data_Quality!$S$9:$S$71,MATCH(A20,Data_Quality!$A$9:$A$71,0)),0) -> 0 | H20: =IFERROR(INDEX(Data_Quality!$T$9:$T$71,MATCH(A20,Data_Quality!$A$9:$A$71,0)),"") -> Excellent - FAA Backfill Pending
A21: ="BWI" -> BWI | B21: =IFERROR(INDEX(Data_Quality!$B$9:$B$71,MATCH(A21,Data_Quality!$A$9:$A$71,0)),"") -> Baltimore/Washington International Thurgood Marshall | C21: =IFERROR(INDEX(Data_Quality!$C$9:$C$71,MATCH(A21,Data_Quality!$A$9:$A$71,0)),"") -> Large | D21: =IFERROR(INDEX(Data_Quality!$D$9:$D$71,MATCH(A21,Data_Quality!$A$9:$A$71,0)),0) -> 6 | E21: =IFERROR(INDEX(Data_Quality!$R$9:$R$71,MATCH(A21,Data_Quality!$A$9:$A$71,0)),0) -> 1 | F21: =IFERROR(INDEX(Data_Quality!$Q$9:$Q$71,MATCH(A21,Data_Quality!$A$9:$A$71,0)),0) -> 0 | G21: =IFERROR(INDEX(Data_Quality!$S$9:$S$71,MATCH(A21,Data_Quality!$A$9:$A$71,0)),0) -> 0 | H21: =IFERROR(INDEX(Data_Quality!$T$9:$T$71,MATCH(A21,Data_Quality!$A$9:$A$71,0)),"") -> Excellent - FAA Backfill Pending
A22: ="TPA" -> TPA | B22: =IFERROR(INDEX(Data_Quality!$B$9:$B$71,MATCH(A22,Data_Quality!$A$9:$A$71,0)),"") -> Tampa International | C22: =IFERROR(INDEX(Data_Quality!$C$9:$C$71,MATCH(A22,Data_Quality!$A$9:$A$71,0)),"") -> Large | D22: =IFERROR(INDEX(Data_Quality!$D$9:$D$71,MATCH(A22,Data_Quality!$A$9:$A$71,0)),0) -> 6 | E22: =IFERROR(INDEX(Data_Quality!$R$9:$R$71,MATCH(A22,Data_Quality!$A$9:$A$71,0)),0) -> 1 | F22: =IFERROR(INDEX(Data_Quality!$Q$9:$Q$71,MATCH(A22,Data_Quality!$A$9:$A$71,0)),0) -> 0 | G22: =IFERROR(INDEX(Data_Quality!$S$9:$S$71,MATCH(A22,Data_Quality!$A$9:$A$71,0)),0) -> 0 | H22: =IFERROR(INDEX(Data_Quality!$T$9:$T$71,MATCH(A22,Data_Quality!$A$9:$A$71,0)),"") -> Excellent - FAA Backfill Pending
A23: ="AUS" -> AUS | B23: =IFERROR(INDEX(Data_Quality!$B$9:$B$71,MATCH(A23,Data_Quality!$A$9:$A$71,0)),"") -> Austin-Bergstrom International | C23: =IFERROR(INDEX(Data_Quality!$C$9:$C$71,MATCH(A23,Data_Quality!$A$9:$A$71,0)),"") -> Large | D23: =IFERROR(INDEX(Data_Quality!$D$9:$D$71,MATCH(A23,Data_Quality!$A$9:$A$71,0)),0) -> 6 | E23: =IFERROR(INDEX(Data_Quality!$R$9:$R$71,MATCH(A23,Data_Quality!$A$9:$A$71,0)),0) -> 1 | F23: =IFERROR(INDEX(Data_Quality!$Q$9:$Q$71,MATCH(A23,Data_Quality!$A$9:$A$71,0)),0) -> 0 | G23: =IFERROR(INDEX(Data_Quality!$S$9:$S$71,MATCH(A23,Data_Quality!$A$9:$A$71,0)),0) -> 0 | H23: =IFERROR(INDEX(Data_Quality!$T$9:$T$71,MATCH(A23,Data_Quality!$A$9:$A$71,0)),"") -> Excellent - FAA Backfill Pending
A24: ="SAN" -> SAN | B24: =IFERROR(INDEX(Data_Quality!$B$9:$B$71,MATCH(A24,Data_Quality!$A$9:$A$71,0)),"") -> San Diego International | C24: =IFERROR(INDEX(Data_Quality!$C$9:$C$71,MATCH(A24,Data_Quality!$A$9:$A$71,0)),"") -> Large | D24: =IFERROR(INDEX(Data_Quality!$D$9:$D$71,MATCH(A24,Data_Quality!$A$9:$A$71,0)),0) -> 6 | E24: =IFERROR(INDEX(Data_Quality!$R$9:$R$71,MATCH(A24,Data_Quality!$A$9:$A$71,0)),0) -> 1 | F24: =IFERROR(INDEX(Data_Quality!$Q$9:$Q$71,MATCH(A24,Data_Quality!$A$9:$A$71,0)),0) -> 0 | G24: =IFERROR(INDEX(Data_Quality!$S$9:$S$71,MATCH(A24,Data_Quality!$A$9:$A$71,0)),0) -> 0 | H24: =IFERROR(INDEX(Data_Quality!$T$9:$T$71,MATCH(A24,Data_Quality!$A$9:$A$71,0)),"") -> Excellent - FAA Backfill Pending
A25: ="BNA" -> BNA | B25: =IFERROR(INDEX(Data_Quality!$B$9:$B$71,MATCH(A25,Data_Quality!$A$9:$A$71,0)),"") -> Nashville International | C25: =IFERROR(INDEX(Data_Quality!$C$9:$C$71,MATCH(A25,Data_Quality!$A$9:$A$71,0)),"") -> Large | D25: =IFERROR(INDEX(Data_Quality!$D$9:$D$71,MATCH(A25,Data_Quality!$A$9:$A$71,0)),0) -> 6 | E25: =IFERROR(INDEX(Data_Quality!$R$9:$R$71,MATCH(A25,Data_Quality!$A$9:$A$71,0)),0) -> 1 | F25: =IFERROR(INDEX(Data_Quality!$Q$9:$Q$71,MATCH(A25,Data_Quality!$A$9:$A$71,0)),0) -> 0 | G25: =IFERROR(INDEX(Data_Quality!$S$9:$S$71,MATCH(A25,Data_Quality!$A$9:$A$71,0)),0) -> 0 | H25: =IFERROR(INDEX(Data_Quality!$T$9:$T$71,MATCH(A25,Data_Quality!$A$9:$A$71,0)),"") -> Excellent - FAA Backfill Pending
A26: ="DAL" -> DAL | B26: =IFERROR(INDEX(Data_Quality!$B$9:$B$71,MATCH(A26,Data_Quality!$A$9:$A$71,0)),"") -> Dallas Love Field | C26: =IFERROR(INDEX(Data_Quality!$C$9:$C$71,MATCH(A26,Data_Quality!$A$9:$A$71,0)),"") -> Medium | D26: =IFERROR(INDEX(Data_Quality!$D$9:$D$71,MATCH(A26,Data_Quality!$A$9:$A$71,0)),0) -> 6 | E26: =IFERROR(INDEX(Data_Quality!$R$9:$R$71,MATCH(A26,Data_Quality!$A$9:$A$71,0)),0) -> 1 | F26: =IFERROR(INDEX(Data_Quality!$Q$9:$Q$71,MATCH(A26,Data_Quality!$A$9:$A$71,0)),0) -> 0 | G26: =IFERROR(INDEX(Data_Quality!$S$9:$S$71,MATCH(A26,Data_Quality!$A$9:$A$71,0)),0) -> 0 | H26: =IFERROR(INDEX(Data_Quality!$T$9:$T$71,MATCH(A26,Data_Quality!$A$9:$A$71,0)),"") -> Excellent - FAA Backfill Pending

Sheet Comparability_Review
A1: Large Hub Comparability Review
A2: Commercial/operating comparisons use airport-level FAA CATS data. For pooled-authority airports, system-level bond/debt metrics are not used for peer ranking.
A4: Airport_Code | B4: Airport_Name | C4: Operator / Authority | D4: 2019-2024_Data | E4: Commercial_KPIs | F4: Operating_KPIs | G4: Debt_KPIs | H4: Recommendation | I4: Reason | J4: Source_URL
A5: CLT | B5: Charlotte/Douglas International | C5: City of Charlotte | D5: Complete: 2019-2024 | E5: Use | F5: Use | G5: Usable with normal caution | H5: Include | I5: Clean airport-level FAA CATS series; suitable for commercial and operating comparisons. | J5: https://dwuconsulting.com/airports/CLT
A6: JFK | B6: John F Kennedy International | C6: Port Authority of New York and New Jersey | D6: Complete: 2019-2024 | E6: Use | F6: Use | G6: Do not use for peer ranking | H6: Include with finance caveat | I6: Airport-level CATS operating/commercial data are usable. Debt/credit metrics are system-linked and should not be benchmarked against stand-alone airports. | J6: https://dwuconsulting.com/airports/JFK
A7: EWR | B7: Newark Liberty International | C7: Port Authority of New York and New Jersey | D7: Complete: 2019-2024 | E7: Use | F7: Use | G7: Do not use for peer ranking | H7: Include with finance caveat | I7: Airport-level CATS operating/commercial data are usable. Debt/credit metrics are reported at the PANYNJ system level. | J7: https://dwuconsulting.com/airports/EWR
A8: LGA | B8: La Guardia | C8: Port Authority of New York and New Jersey | D8: Complete: 2019-2024 | E8: Use | F8: Use | G8: Do not use for peer ranking | H8: Include with finance caveat | I8: Airport-level CATS operating/commercial data are usable. Debt/credit metrics are reported at the PANYNJ system level. | J8: https://dwuconsulting.com/airports/LGA
A9: IAD | B9: Washington Dulles International | C9: Metropolitan Washington Airports Authority | D9: Complete: 2019-2024 | E9: Use | F9: Use | G9: Do not use for peer ranking | H9: Include with finance caveat | I9: Airport-level CATS operating/commercial data are usable. Bond/credit context is MWAA system-level; do not use debt metrics for peer ranking. | J9: https://dwuconsulting.com/airports/IAD
A10: DCA | B10: Ronald Reagan Washington Ntl | C10: Metropolitan Washington Airports Authority | D10: Complete: 2019-2024 | E10: Use | F10: Use | G10: Do not use for peer ranking | H10: Include with finance caveat | I10: Airport-level CATS operating/commercial data are usable. Bond/credit context is MWAA system-level; do not use debt metrics for peer ranking. | J10: https://dwuconsulting.com/airports/DCA
A11: HNL | B11: Daniel K Inouye International | C11: Hawaii Airports System | D11: Complete: 2019-2024 | E11: Use | F11: Use | G11: Do not use for peer ranking | H11: Include with finance caveat | I11: Airport-level CATS operating/commercial data are usable. Bond credit is pooled at Hawaii Airports System level; avoid debt-based peer rankings. | J11: https://dwuconsulting.com/airports/HNL
A12: MDW | B12: Chicago Midway International | C12: City of Chicago Department of Aviation | D12: Complete: 2019-2024 | E12: Use | F12: Use | G12: Usable with normal caution | H12: Include | I12: Clean airport-level FAA CATS series; suitable for commercial and operating comparisons. | J12: https://dwuconsulting.com/airports/MDW

Sheet Candidate_Set_33
A1: Airport_Code | B1: Airport_Name | C1: Hub_Size | D1: Years_Loaded | E1: Current_Completeness_% | F1: Zero_Flags | G1: FAA_Backfill_% | H1: Status | I1: Comparability_Note
A2: ATL | B2: =IFERROR(INDEX(Data_Quality!$B$9:$B$71,MATCH($A2,Data_Quality!$A$9:$A$71,0)),"") -> Hartsfield/Jackson Atlanta International | C2: =IFERROR(INDEX(Data_Quality!$C$9:$C$71,MATCH($A2,Data_Quality!$A$9:$A$71,0)),"") -> Large | D2: =IFERROR(INDEX(Data_Quality!$D$9:$D$71,MATCH($A2,Data_Quality!$A$9:$A$71,0)),0) -> 6 | E2: =IFERROR(INDEX(Data_Quality!$R$9:$R$71,MATCH($A2,Data_Quality!$A$9:$A$71,0)),0) -> 1 | F2: =IFERROR(INDEX(Data_Quality!$Q$9:$Q$71,MATCH($A2,Data_Quality!$A$9:$A$71,0)),0) -> 0 | G2: =IFERROR(INDEX(Data_Quality!$S$9:$S$71,MATCH($A2,Data_Quality!$A$9:$A$71,0)),0) -> 0 | H2: =IFERROR(INDEX(Data_Quality!$T$9:$T$71,MATCH($A2,Data_Quality!$A$9:$A$71,0)),"") -> Excellent - FAA Backfill Pending | I2: Previously loaded airport; standard airport-level comparability review still applies.
A3: DFW | B3: =IFERROR(INDEX(Data_Quality!$B$9:$B$71,MATCH($A3,Data_Quality!$A$9:$A$71,0)),"") -> Dallas-Fort Worth International | C3: =IFERROR(INDEX(Data_Quality!$C$9:$C$71,MATCH($A3,Data_Quality!$A$9:$A$71,0)),"") -> Large | D3: =IFERROR(INDEX(Data_Quality!$D$9:$D$71,MATCH($A3,Data_Quality!$A$9:$A$71,0)),0) -> 6 | E3: =IFERROR(INDEX(Data_Quality!$R$9:$R$71,MATCH($A3,Data_Quality!$A$9:$A$71,0)),0) -> 1 | F3: =IFERROR(INDEX(Data_Quality!$Q$9:$Q$71,MATCH($A3,Data_Quality!$A$9:$A$71,0)),0) -> 0 | G3: =IFERROR(INDEX(Data_Quality!$S$9:$S$71,MATCH($A3,Data_Quality!$A$9:$A$71,0)),0) -> 0 | H3: =IFERROR(INDEX(Data_Quality!$T$9:$T$71,MATCH($A3,Data_Quality!$A$9:$A$71,0)),"") -> Excellent - FAA Backfill Pending | I3: Previously loaded airport; standard airport-level comparability review still applies.
A4: LAX | B4: =IFERROR(INDEX(Data_Quality!$B$9:$B$71,MATCH($A4,Data_Quality!$A$9:$A$71,0)),"") -> Los Angeles International | C4: =IFERROR(INDEX(Data_Quality!$C$9:$C$71,MATCH($A4,Data_Quality!$A$9:$A$71,0)),"") -> Large | D4: =IFERROR(INDEX(Data_Quality!$D$9:$D$71,MATCH($A4,Data_Quality!$A$9:$A$71,0)),0) -> 6 | E4: =IFERROR(INDEX(Data_Quality!$R$9:$R$71,MATCH($A4,Data_Quality!$A$9:$A$71,0)),0) -> 1 | F4: =IFERROR(INDEX(Data_Quality!$Q$9:$Q$71,MATCH($A4,Data_Quality!$A$9:$A$71,0)),0) -> 0 | G4: =IFERROR(INDEX(Data_Quality!$S$9:$S$71,MATCH($A4,Data_Quality!$A$9:$A$71,0)),0) -> 0 | H4: =IFERROR(INDEX(Data_Quality!$T$9:$T$71,MATCH($A4,Data_Quality!$A$9:$A$71,0)),"") -> Excellent - FAA Backfill Pending | I4: Previously loaded airport; standard airport-level comparability review still applies.
A5: SEA | B5: =IFERROR(INDEX(Data_Quality!$B$9:$B$71,MATCH($A5,Data_Quality!$A$9:$A$71,0)),"") -> Seattle-Tacoma International | C5: =IFERROR(INDEX(Data_Quality!$C$9:$C$71,MATCH($A5,Data_Quality!$A$9:$A$71,0)),"") -> Large | D5: =IFERROR(INDEX(Data_Quality!$D$9:$D$71,MATCH($A5,Data_Quality!$A$9:$A$71,0)),0) -> 6 | E5: =IFERROR(INDEX(Data_Quality!$R$9:$R$71,MATCH($A5,Data_Quality!$A$9:$A$71,0)),0) -> 1 | F5: =IFERROR(INDEX(Data_Quality!$Q$9:$Q$71,MATCH($A5,Data_Quality!$A$9:$A$71,0)),0) -> 0 | G5: =IFERROR(INDEX(Data_Quality!$S$9:$S$71,MATCH($A5,Data_Quality!$A$9:$A$71,0)),0) -> 0 | H5: =IFERROR(INDEX(Data_Quality!$T$9:$T$71,MATCH($A5,Data_Quality!$A$9:$A$71,0)),"") -> Excellent - FAA Backfill Pending | I5: Previously loaded airport; standard airport-level comparability review still applies.
A6: CLE | B6: =IFERROR(INDEX(Data_Quality!$B$9:$B$71,MATCH($A6,Data_Quality!$A$9:$A$71,0)),"") -> Cleveland-Hopkins International | C6: =IFERROR(INDEX(Data_Quality!$C$9:$C$71,MATCH($A6,Data_Quality!$A$9:$A$71,0)),"") -> Medium | D6: =IFERROR(INDEX(Data_Quality!$D$9:$D$71,MATCH($A6,Data_Quality!$A$9:$A$71,0)),0) -> 6 | E6: =IFERROR(INDEX(Data_Quality!$R$9:$R$71,MATCH($A6,Data_Quality!$A$9:$A$71,0)),0) -> 1 | F6: =IFERROR(INDEX(Data_Quality!$Q$9:$Q$71,MATCH($A6,Data_Quality!$A$9:$A$71,0)),0) -> 0 | G6: =IFERROR(INDEX(Data_Quality!$S$9:$S$71,MATCH($A6,Data_Quality!$A$9:$A$71,0)),0) -> 0 | H6: =IFERROR(INDEX(Data_Quality!$T$9:$T$71,MATCH($A6,Data_Quality!$A$9:$A$71,0)),"") -> Excellent - FAA Backfill Pending | I6: Previously loaded airport; standard airport-level comparability review still applies.
A7: DEN | B7: =IFERROR(INDEX(Data_Quality!$B$9:$B$71,MATCH($A7,Data_Quality!$A$9:$A$71,0)),"") -> Denver International | C7: =IFERROR(INDEX(Data_Quality!$C$9:$C$71,MATCH($A7,Data_Quality!$A$9:$A$71,0)),"") -> Large | D7: =IFERROR(INDEX(Data_Quality!$D$9:$D$71,MATCH($A7,Data_Quality!$A$9:$A$71,0)),0) -> 6 | E7: =IFERROR(INDEX(Data_Quality!$R$9:$R$71,MATCH($A7,Data_Quality!$A$9:$A$71,0)),0) -> 1 | F7: =IFERROR(INDEX(Data_Quality!$Q$9:$Q$71,MATCH($A7,Data_Quality!$A$9:$A$71,0)),0) -> 0 | G7: =IFERROR(INDEX(Data_Quality!$S$9:$S$71,MATCH($A7,Data_Quality!$A$9:$A$71,0)),0) -> 0 | H7: =IFERROR(INDEX(Data_Quality!$T$9:$T$71,MATCH($A7,Data_Quality!$A$9:$A$71,0)),"") -> Excellent - FAA Backfill Pending | I7: Previously loaded airport; standard airport-level comparability review still applies.
A8: ORD | B8: =IFERROR(INDEX(Data_Quality!$B$9:$B$71,MATCH($A8,Data_Quality!$A$9:$A$71,0)),"") -> Chicago O'Hare International | C8: =IFERROR(INDEX(Data_Quality!$C$9:$C$71,MATCH($A8,Data_Quality!$A$9:$A$71,0)),"") -> Large | D8: =IFERROR(INDEX(Data_Quality!$D$9:$D$71,MATCH($A8,Data_Quality!$A$9:$A$71,0)),0) -> 6 | E8: =IFERROR(INDEX(Data_Quality!$R$9:$R$71,MATCH($A8,Data_Quality!$A$9:$A$71,0)),0) -> 1 | F8: =IFERROR(INDEX(Data_Quality!$Q$9:$Q$71,MATCH($A8,Data_Quality!$A$9:$A$71,0)),0) -> 0 | G8: =IFERROR(INDEX(Data_Quality!$S$9:$S$71,MATCH($A8,Data_Quality!$A$9:$A$71,0)),0) -> 0 | H8: =IFERROR(INDEX(Data_Quality!$T$9:$T$71,MATCH($A8,Data_Quality!$A$9:$A$71,0)),"") -> Excellent - FAA Backfill Pending | I8: Previously loaded airport; standard airport-level comparability review still applies.
A9: LAS | B9: =IFERROR(INDEX(Data_Quality!$B$9:$B$71,MATCH($A9,Data_Quality!$A$9:$A$71,0)),"") -> Harry Reid International | C9: =IFERROR(INDEX(Data_Quality!$C$9:$C$71,MATCH($A9,Data_Quality!$A$9:$A$71,0)),"") -> Large | D9: =IFERROR(INDEX(Data_Quality!$D$9:$D$71,MATCH($A9,Data_Quality!$A$9:$A$71,0)),0) -> 6 | E9: =IFERROR(INDEX(Data_Quality!$R$9:$R$71,MATCH($A9,Data_Quality!$A$9:$A$71,0)),0) -> 1 | F9: =IFERROR(INDEX(Data_Quality!$Q$9:$Q$71,MATCH($A9,Data_Quality!$A$9:$A$71,0)),0) -> 0 | G9: =IFERROR(INDEX(Data_Quality!$S$9:$S$71,MATCH($A9,Data_Quality!$A$9:$A$71,0)),0) -> 0 | H9: =IFERROR(INDEX(Data_Quality!$T$9:$T$71,MATCH($A9,Data_Quality!$A$9:$A$71,0)),"") -> Excellent - FAA Backfill Pending | I9: Previously loaded airport; standard airport-level comparability review still applies.
A10: PHX | B10: =IFERROR(INDEX(Data_Quality!$B$9:$B$71,MATCH($A10,Data_Quality!$A$9:$A$71,0)),"") -> Phoenix Sky Harbor International | C10: =IFERROR(INDEX(Data_Quality!$C$9:$C$71,MATCH($A10,Data_Quality!$A$9:$A$71,0)),"") -> Large | D10: =IFERROR(INDEX(Data_Quality!$D$9:$D$71,MATCH($A10,Data_Quality!$A$9:$A$71,0)),0) -> 6 | E10: =IFERROR(INDEX(Data_Quality!$R$9:$R$71,MATCH($A10,Data_Quality!$A$9:$A$71,0)),0) -> 1 | F10: =IFERROR(INDEX(Data_Quality!$Q$9:$Q$71,MATCH($A10,Data_Quality!$A$9:$A$71,0)),0) -> 5 | G10: =IFERROR(INDEX(Data_Quality!$S$9:$S$71,MATCH($A10,Data_Quality!$A$9:$A$71,0)),0) -> 0 | H10: =IFERROR(INDEX(Data_Quality!$T$9:$T$71,MATCH($A10,Data_Quality!$A$9:$A$71,0)),"") -> Excellent - FAA Backfill Pending | I10: Previously loaded airport; standard airport-level comparability review still applies.
A11: MIA | B11: =IFERROR(INDEX(Data_Quality!$B$9:$B$71,MATCH($A11,Data_Quality!$A$9:$A$71,0)),"") -> Miami International | C11: =IFERROR(INDEX(Data_Quality!$C$9:$C$71,MATCH($A11,Data_Quality!$A$9:$A$71,0)),"") -> Large | D11: =IFERROR(INDEX(Data_Quality!$D$9:$D$71,MATCH($A11,Data_Quality!$A$9:$A$71,0)),0) -> 6 | E11: =IFERROR(INDEX(Data_Quality!$R$9:$R$71,MATCH($A11,Data_Quality!$A$9:$A$71,0)),0) -> 1 | F11: =IFERROR(INDEX(Data_Quality!$Q$9:$Q$71,MATCH($A11,Data_Quality!$A$9:$A$71,0)),0) -> 0 | G11: =IFERROR(INDEX(Data_Quality!$S$9:$S$71,MATCH($A11,Data_Quality!$A$9:$A$71,0)),0) -> 0 | H11: =IFERROR(INDEX(Data_Quality!$T$9:$T$71,MATCH($A11,Data_Quality!$A$9:$A$71,0)),"") -> Excellent - FAA Backfill Pending | I11: Previously loaded airport; standard airport-level comparability review still applies.
A12: SFO | B12: =IFERROR(INDEX(Data_Quality!$B$9:$B$71,MATCH($A12,Data_Quality!$A$9:$A$71,0)),"") -> San Francisco International | C12: =IFERROR(INDEX(Data_Quality!$C$9:$C$71,MATCH($A12,Data_Quality!$A$9:$A$71,0)),"") -> Large | D12: =IFERROR(INDEX(Data_Quality!$D$9:$D$71,MATCH($A12,Data_Quality!$A$9:$A$71,0)),0) -> 6 | E12: =IFERROR(INDEX(Data_Quality!$R$9:$R$71,MATCH($A12,Data_Quality!$A$9:$A$71,0)),0) -> 1 | F12: =IFERROR(INDEX(Data_Quality!$Q$9:$Q$71,MATCH($A12,Data_Quality!$A$9:$A$71,0)),0) -> 0 | G12: =IFERROR(INDEX(Data_Quality!$S$9:$S$71,MATCH($A12,Data_Quality!$A$9:$A$71,0)),0) -> 0 | H12: =IFERROR(INDEX(Data_Quality!$T$9:$T$71,MATCH($A12,Data_Quality!$A$9:$A$71,0)),"") -> Excellent - FAA Backfill Pending | I12: Previously loaded airport; standard airport-level comparability review still applies.
A13: IAH | B13: =IFERROR(INDEX(Data_Quality!$B$9:$B$71,MATCH($A13,Data_Quality!$A$9:$A$71,0)),"") -> George Bush Intcntl/Houston | C13: =IFERROR(INDEX(Data_Quality!$C$9:$C$71,MATCH($A13,Data_Quality!$A$9:$A$71,0)),"") -> Large | D13: =IFERROR(INDEX(Data_Quality!$D$9:$D$71,MATCH($A13,Data_Quality!$A$9:$A$71,0)),0) -> 6 | E13: =IFERROR(INDEX(Data_Quality!$R$9:$R$71,MATCH($A13,Data_Quality!$A$9:$A$71,0)),0) -> 1 | F13: =IFERROR(INDEX(Data_Quality!$Q$9:$Q$71,MATCH($A13,Data_Quality!$A$9:$A$71,0)),0) -> 0 | G13: =IFERROR(INDEX(Data_Quality!$S$9:$S$71,MATCH($A13,Data_Quality!$A$9:$A$71,0)),0) -> 0 | H13: =IFERROR(INDEX(Data_Quality!$T$9:$T$71,MATCH($A13,Data_Quality!$A$9:$A$71,0)),"") -> Excellent - FAA Backfill Pending | I13: Previously loaded airport; standard airport-level comparability review still applies.
... A34: MDW | B34: =IFERROR(INDEX(Data_Quality!$B$9:$B$71,MATCH($A34,Data_Quality!$A$9:$A$71,0)),"") -> Chicago Midway International | C34: =IFERROR(INDEX(Data_Quality!$C$9:$C$71,MATCH($A34,Data_Quality!$A$9:$A$71,0)),"") -> Large | D34: =IFERROR(INDEX(Data_Quality!$D$9:$D$71,MATCH($A34,Data_Quality!$A$9:$A$71,0)),0) -> 6 | E34: =IFERROR(INDEX(Data_Quality!$R$9:$R$71,MATCH($A34,Data_Quality!$A$9:$A$71,0)),0) -> 1 | F34: =IFERROR(INDEX(Data_Quality!$Q$9:$Q$71,MATCH($A34,Data_Quality!$A$9:$A$71,0)),0) -> 0 | G34: =IFERROR(INDEX(Data_Quality!$S$9:$S$71,MATCH($A34,Data_Quality!$A$9:$A$71,0)),0) -> 0 | H34: =IFERROR(INDEX(Data_Quality!$T$9:$T$71,MATCH($A34,Data_Quality!$A$9:$A$71,0)),"") -> Excellent - FAA Backfill Pending | I34: Clean airport-level FAA CATS series; suitable for commercial and operating comparisons.

Sheet Final_Airport_Set
A1: Final Airport Analysis Population
A2: Final scope: all 31 FAA Large Hub airports, 2019–2024. CLE and DAL are retained only as Medium-Hub reserve/QA airports. Commercial and operating metrics are compared at airport level; pooled-authority debt/credit metrics are excluded from peer ranking.
A4: Loaded Airports | B4: Final Included | C4: Reserve / QA | D4: Analysis Years | E4: Final Airport-Years | F4: Selection Rule
A5: =COUNTA(Candidate_Set_33!$A$2:$A$34) -> 33 | B5: =COUNTIF($D$9:$D$41,"Yes") -> 31 | C5: =COUNTIF($D$9:$D$41,"Reserve") -> 2 | D5: =6 -> 6 | E5: =B5*D5 -> 186 | F5: ="All FAA Large Hubs" -> All FAA Large Hubs
A8: Airport_Code | B8: Airport_Name | C8: Hub_Size | D8: Final_Selection | E8: 2024_Rank | F8: Years_Loaded | G8: Current_Completeness_% | H8: Finance_Caveat | I8: Category_Data_Caveat | J8: Final_Use | K8: Reason
A9: =Candidate_Set_33!A2 -> ATL | B9: =Candidate_Set_33!B2 -> Hartsfield/Jackson Atlanta International | C9: =Candidate_Set_33!C2 -> Large | D9: =IF(C9="Large","Yes","Reserve") -> Yes | E9: =IFERROR(INDEX(Airport_Master!$K$2:$K$64,MATCH(A9,Airport_Master!$A$2:$A$64,0)),"") -> 1 | F9: =Candidate_Set_33!D2 -> 6 | G9: =Candidate_Set_33!E2 -> 1 | H9: Standard airport-level finance comparability | I9: No known category-specific caveat beyond normal FAA reporting differences | J9: =IF(D9="Yes","Include in dashboard & SQL analysis","Reserve / QA only") -> Include in dashboard & SQL analysis | K9: =IF(D9="Yes","Complete 2019–2024 Large-Hub peer; retained for full-population benchmarking","Medium-Hub airport retained only for validation / potential replacement") -> Complete 2019–2024 Large-Hub peer; retained for full-population benchmarking
A10: =Candidate_Set_33!A3 -> DFW | B10: =Candidate_Set_33!B3 -> Dallas-Fort Worth International | C10: =Candidate_Set_33!C3 -> Large | D10: =IF(C10="Large","Yes","Reserve") -> Yes | E10: =IFERROR(INDEX(Airport_Master!$K$2:$K$64,MATCH(A10,Airport_Master!$A$2:$A$64,0)),"") -> 2 | F10: =Candidate_Set_33!D3 -> 6 | G10: =Candidate_Set_33!E3 -> 1 | H10: Standard airport-level finance comparability | I10: No known category-specific caveat beyond normal FAA reporting differences | J10: =IF(D10="Yes","Include in dashboard & SQL analysis","Reserve / QA only") -> Include in dashboard & SQL analysis | K10: =IF(D10="Yes","Complete 2019–2024 Large-Hub peer; retained for full-population benchmarking","Medium-Hub airport retained only for validation / potential replacement") -> Complete 2019–2024 Large-Hub peer; retained for full-population benchmarking
A11: =Candidate_Set_33!A4 -> LAX | B11: =Candidate_Set_33!B4 -> Los Angeles International | C11: =Candidate_Set_33!C4 -> Large | D11: =IF(C11="Large","Yes","Reserve") -> Yes | E11: =IFERROR(INDEX(Airport_Master!$K$2:$K$64,MATCH(A11,Airport_Master!$A$2:$A$64,0)),"") -> 5 | F11: =Candidate_Set_33!D4 -> 6 | G11: =Candidate_Set_33!E4 -> 1 | H11: Standard airport-level finance comparability | I11: No known category-specific caveat beyond normal FAA reporting differences | J11: =IF(D11="Yes","Include in dashboard & SQL analysis","Reserve / QA only") -> Include in dashboard & SQL analysis | K11: =IF(D11="Yes","Complete 2019–2024 Large-Hub peer; retained for full-population benchmarking","Medium-Hub airport retained only for validation / potential replacement") -> Complete 2019–2024 Large-Hub peer; retained for full-population benchmarking
A12: =Candidate_Set_33!A5 -> SEA | B12: =Candidate_Set_33!B5 -> Seattle-Tacoma International | C12: =Candidate_Set_33!C5 -> Large | D12: =IF(C12="Large","Yes","Reserve") -> Yes | E12: =IFERROR(INDEX(Airport_Master!$K$2:$K$64,MATCH(A12,Airport_Master!$A$2:$A$64,0)),"") -> 12 | F12: =Candidate_Set_33!D5 -> 6 | G12: =Candidate_Set_33!E5 -> 1 | H12: Standard airport-level finance comparability | I12: No known category-specific caveat beyond normal FAA reporting differences | J12: =IF(D12="Yes","Include in dashboard & SQL analysis","Reserve / QA only") -> Include in dashboard & SQL analysis | K12: =IF(D12="Yes","Complete 2019–2024 Large-Hub peer; retained for full-population benchmarking","Medium-Hub airport retained only for validation / potential replacement") -> Complete 2019–2024 Large-Hub peer; retained for full-population benchmarking
A13: =Candidate_Set_33!A6 -> CLE | B13: =Candidate_Set_33!B6 -> Cleveland-Hopkins International | C13: =Candidate_Set_33!C6 -> Medium | D13: =IF(C13="Large","Yes","Reserve") -> Reserve | E13: =IFERROR(INDEX(Airport_Master!$K$2:$K$64,MATCH(A13,Airport_Master!$A$2:$A$64,0)),"") -> 47 | F13: =Candidate_Set_33!D6 -> 6 | G13: =Candidate_Set_33!E6 -> 1 | H13: Standard airport-level finance comparability | I13: No known category-specific caveat beyond normal FAA reporting differences | J13: =IF(D13="Yes","Include in dashboard & SQL analysis","Reserve / QA only") -> Reserve / QA only | K13: =IF(D13="Yes","Complete 2019–2024 Large-Hub peer; retained for full-population benchmarking","Medium-Hub airport retained only for validation / potential replacement") -> Medium-Hub airport retained only for validation / potential replacement
A14: =Candidate_Set_33!A7 -> DEN | B14: =Candidate_Set_33!B7 -> Denver International | C14: =Candidate_Set_33!C7 -> Large | D14: =IF(C14="Large","Yes","Reserve") -> Yes | E14: =IFERROR(INDEX(Airport_Master!$K$2:$K$64,MATCH(A14,Airport_Master!$A$2:$A$64,0)),"") -> 3 | F14: =Candidate_Set_33!D7 -> 6 | G14: =Candidate_Set_33!E7 -> 1 | H14: Standard airport-level finance comparability | I14: No known category-specific caveat beyond normal FAA reporting differences | J14: =IF(D14="Yes","Include in dashboard & SQL analysis","Reserve / QA only") -> Include in dashboard & SQL analysis | K14: =IF(D14="Yes","Complete 2019–2024 Large-Hub peer; retained for full-population benchmarking","Medium-Hub airport retained only for validation / potential replacement") -> Complete 2019–2024 Large-Hub peer; retained for full-population benchmarking
A15: =Candidate_Set_33!A8 -> ORD | B15: =Candidate_Set_33!B8 -> Chicago O'Hare International | C15: =Candidate_Set_33!C8 -> Large | D15: =IF(C15="Large","Yes","Reserve") -> Yes | E15: =IFERROR(INDEX(Airport_Master!$K$2:$K$64,MATCH(A15,Airport_Master!$A$2:$A$64,0)),"") -> 4 | F15: =Candidate_Set_33!D8 -> 6 | G15: =Candidate_Set_33!E8 -> 1 | H15: Standard airport-level finance comparability | I15: No known category-specific caveat beyond normal FAA reporting differences | J15: =IF(D15="Yes","Include in dashboard & SQL analysis","Reserve / QA only") -> Include in dashboard & SQL analysis | K15: =IF(D15="Yes","Complete 2019–2024 Large-Hub peer; retained for full-population benchmarking","Medium-Hub airport retained only for validation / potential replacement") -> Complete 2019–2024 Large-Hub peer; retained for full-population benchmarking
A16: =Candidate_Set_33!A9 -> LAS | B16: =Candidate_Set_33!B9 -> Harry Reid International | C16: =Candidate_Set_33!C9 -> Large | D16: =IF(C16="Large","Yes","Reserve") -> Yes | E16: =IFERROR(INDEX(Airport_Master!$K$2:$K$64,MATCH(A16,Airport_Master!$A$2:$A$64,0)),"") -> 8 | F16: =Candidate_Set_33!D9 -> 6 | G16: =Candidate_Set_33!E9 -> 1 | H16: Standard airport-level finance comparability | I16: No known category-specific caveat beyond normal FAA reporting differences | J16: =IF(D16="Yes","Include in dashboard & SQL analysis","Reserve / QA only") -> Include in dashboard & SQL analysis | K16: =IF(D16="Yes","Complete 2019–2024 Large-Hub peer; retained for full-population benchmarking","Medium-Hub airport retained only for validation / potential replacement") -> Complete 2019–2024 Large-Hub peer; retained for full-population benchmarking
A17: =Candidate_Set_33!A10 -> PHX | B17: =Candidate_Set_33!B10 -> Phoenix Sky Harbor International | C17: =Candidate_Set_33!C10 -> Large | D17: =IF(C17="Large","Yes","Reserve") -> Yes | E17: =IFERROR(INDEX(Airport_Master!$K$2:$K$64,MATCH(A17,Airport_Master!$A$2:$A$64,0)),"") -> 11 | F17: =Candidate_Set_33!D10 -> 6 | G17: =Candidate_Set_33!E10 -> 1 | H17: Standard airport-level finance comparability | I17: Terminal-service revenue has repeated reported zeros; keep airport, but review this category separately | J17: =IF(D17="Yes","Include in dashboard & SQL analysis","Reserve / QA only") -> Include in dashboard & SQL analysis | K17: =IF(D17="Yes","Complete 2019–2024 Large-Hub peer; retained for full-population benchmarking","Medium-Hub airport retained only for validation / potential replacement") -> Complete 2019–2024 Large-Hub peer; retained for full-population benchmarking
A18: =Candidate_Set_33!A11 -> MIA | B18: =Candidate_Set_33!B11 -> Miami International | C18: =Candidate_Set_33!C11 -> Large | D18: =IF(C18="Large","Yes","Reserve") -> Yes | E18: =IFERROR(INDEX(Airport_Master!$K$2:$K$64,MATCH(A18,Airport_Master!$A$2:$A$64,0)),"") -> 10 | F18: =Candidate_Set_33!D11 -> 6 | G18: =Candidate_Set_33!E11 -> 1 | H18: Standard airport-level finance comparability | I18: No known category-specific caveat beyond normal FAA reporting differences | J18: =IF(D18="Yes","Include in dashboard & SQL analysis","Reserve / QA only") -> Include in dashboard & SQL analysis | K18: =IF(D18="Yes","Complete 2019–2024 Large-Hub peer; retained for full-population benchmarking","Medium-Hub airport retained only for validation / potential replacement") -> Complete 2019–2024 Large-Hub peer; retained for full-population benchmarking
A19: =Candidate_Set_33!A12 -> SFO | B19: =Candidate_Set_33!B12 -> San Francisco International | C19: =Candidate_Set_33!C12 -> Large | D19: =IF(C19="Large","Yes","Reserve") -> Yes | E19: =IFERROR(INDEX(Airport_Master!$K$2:$K$64,MATCH(A19,Airport_Master!$A$2:$A$64,0)),"") -> 13 | F19: =Candidate_Set_33!D12 -> 6 | G19: =Candidate_Set_33!E12 -> 1 | H19: Standard airport-level finance comparability | I19: No known category-specific caveat beyond normal FAA reporting differences | J19: =IF(D19="Yes","Include in dashboard & SQL analysis","Reserve / QA only") -> Include in dashboard & SQL analysis | K19: =IF(D19="Yes","Complete 2019–2024 Large-Hub peer; retained for full-population benchmarking","Medium-Hub airport retained only for validation / potential replacement") -> Complete 2019–2024 Large-Hub peer; retained for full-population benchmarking
A20: =Candidate_Set_33!A13 -> IAH | B20: =Candidate_Set_33!B13 -> George Bush Intcntl/Houston | C20: =Candidate_Set_33!C13 -> Large | D20: =IF(C20="Large","Yes","Reserve") -> Yes | E20: =IFERROR(INDEX(Airport_Master!$K$2:$K$64,MATCH(A20,Airport_Master!$A$2:$A$64,0)),"") -> 15 | F20: =Candidate_Set_33!D13 -> 6 | G20: =Candidate_Set_33!E13 -> 1 | H20: Standard airport-level finance comparability | I20: No known category-specific caveat beyond normal FAA reporting differences | J20: =IF(D20="Yes","Include in dashboard & SQL analysis","Reserve / QA only") -> Include in dashboard & SQL analysis | K20: =IF(D20="Yes","Complete 2019–2024 Large-Hub peer; retained for full-population benchmarking","Medium-Hub airport retained only for validation / potential replacement") -> Complete 2019–2024 Large-Hub peer; retained for full-population benchmarking
... A41: =Candidate_Set_33!A34 -> MDW | B41: =Candidate_Set_33!B34 -> Chicago Midway International | C41: =Candidate_Set_33!C34 -> Large | D41: =IF(C41="Large","Yes","Reserve") -> Yes | E41: =IFERROR(INDEX(Airport_Master!$K$2:$K$64,MATCH(A41,Airport_Master!$A$2:$A$64,0)),"") -> 31 | F41: =Candidate_Set_33!D34 -> 6 | G41: =Candidate_Set_33!E34 -> 1 | H41: Standard airport-level finance comparability | I41: No known category-specific caveat beyond normal FAA reporting differences | J41: =IF(D41="Yes","Include in dashboard & SQL analysis","Reserve / QA only") -> Include in dashboard & SQL analysis | K41: =IF(D41="Yes","Complete 2019–2024 Large-Hub peer; retained for full-population benchmarking","Medium-Hub airport retained only for validation / potential replacement") -> Complete 2019–2024 Large-Hub peer; retained for full-population benchmarking
A44: Selection Principle | B44: Decision | C44: Why | D44: Impact
A45: Population | B45: Use all 31 FAA Large Hubs | C45: Avoids arbitrary cherry-picking and gives a complete peer universe | D45: Primary dashboard population
A46: Medium hubs | B46: Exclude CLE and DAL from final dashboard | C46: Different FAA hub class; not directly comparable to Large Hubs | D46: Retained only for QA / fallback
A47: Debt metrics | B47: Do not use in peer ranking | C47: Several airports belong to pooled authorities with system-level debt/credit structures | D47: Focus project on revenue, passengers, expenses, operating income, and commercial categories
A48: Commercial categories | B48: Keep PHX but flag terminal-service zeros | C48: Reported zero is not the same as missing; category reporting can differ | D48: Use category-level results with caveat, not as automatic exclusion

Sheet Airport_Financials_Clean
A1: Record_Key | B1: Airport_Code | C1: Airport_Name | D1: City | E1: State | F1: Hub_Size | G1: Year | H1: Enplanements | I1: Total_Operating_Revenue | J1: Total_Aeronautical_Revenue | K1: Total_Commercial_Revenue | L1: Food_Beverage_Revenue | M1: Retail_Revenue | N1: Rental_Car_Revenue | O1: Parking_Ground_Revenue | P1: Land_Lease_Revenue | Q1: Terminal_Service_Revenue | R1: Hotel_Revenue | S1: Other_Commercial_Revenue | T1: Operating_Expenses | U1: Operating_Income | V1: Total_Capex | W1: Total_Debt | X1: Passenger_Aero_Revenue | Y1: Known_Commercial_Component_Sum | Z1: Known_Component_Share_of_Op_Revenue | AA1: Missing_Core_Flag | AB1: Zero_Commercial_Detail_Flag | AC1: Negative_Commercial_Detail_Flag | AD1: Negative_Operating_Income_Flag | AE1: Duplicate_Key_Flag | AF1: Debt_Comparable_Flag | AG1: FAA_Backfill_Pending | AH1: Row_Quality_Status | AI1: Finance_Caveat | AJ1: Data_Source | AK1: Source_URL
A2: =B2&"-"&G2 -> ATL-2019 | B2: ATL | C2: Hartsfield/Jackson Atlanta International | D2: Atlanta | E2: GA | F2: Large | G2: 2019 | H2: 54531948 | I2: 568507000 | L2: 55845000 | M2: 52259000 | N2: 43607000 | O2: 159640000 | Q2: 12955000 | T2: 316189000 | U2: -5195000 | V2: 1077677000 | W2: 3148793000 | X2: 157871000 | Y2: =SUM(L2:S2) -> 324306000 | Z2: =IFERROR(Y2/I2,0) -> 0.57045208 | AA2: =IF(OR(H2="",I2="",T2="",U2=""),"Yes","No") -> No | AB2: =IF(OR(AND(L2<>"",L2=0),AND(M2<>"",M2=0),AND(N2<>"",N2=0),AND(O2<>"",O2=0),AND(Q2<>"",Q2=0)),"Yes","No") -> No | AC2: =IF(MIN(L2:O2,Q2)<0,"Yes","No") -> No | AD2: =IF(U2<0,"Yes","No") -> Yes | AE2: =IF(COUNTIFS($B$2:$B$187,B2,$G$2:$G$187,G2)>1,"Yes","No") -> No | AF2: Yes | AG2: =IF(OR(J2="",K2="",P2="",R2="",S2=""),"Yes","No") -> Yes | AH2: =IF(OR(AA2="Yes",AE2="Yes"),"Review - Core/Duplicate",IF(OR(AB2="Yes",AC2="Yes"),"Clean - Flagged","Clean")) -> Clean | AI2: Standard airport-level finance comparability | AJ2: DWU transcription of FAA CATS Form 127 | AK2: https://dwuconsulting.com/airports/ATL
A3: =B3&"-"&G3 -> ATL-2020 | B3: ATL | C3: Hartsfield/Jackson Atlanta International | D3: Atlanta | E3: GA | F3: Large | G3: 2020 | H3: 39747596 | I3: 442318000 | L3: 42960000 | M3: 32688000 | N3: 32001000 | O3: 117313000 | Q3: 12239000 | T3: 323202000 | U3: -153378000 | V3: 793389000 | W3: 3417948000 | X3: 132337000 | Y3: =SUM(L3:S3) -> 237201000 | Z3: =IFERROR(Y3/I3,0) -> 0.53626802 | AA3: =IF(OR(H3="",I3="",T3="",U3=""),"Yes","No") -> No | AB3: =IF(OR(AND(L3<>"",L3=0),AND(M3<>"",M3=0),AND(N3<>"",N3=0),AND(O3<>"",O3=0),AND(Q3<>"",Q3=0)),"Yes","No") -> No | AC3: =IF(MIN(L3:O3,Q3)<0,"Yes","No") -> No | AD3: =IF(U3<0,"Yes","No") -> Yes | AE3: =IF(COUNTIFS($B$2:$B$187,B3,$G$2:$G$187,G3)>1,"Yes","No") -> No | AF3: Yes | AG3: =IF(OR(J3="",K3="",P3="",R3="",S3=""),"Yes","No") -> Yes | AH3: =IF(OR(AA3="Yes",AE3="Yes"),"Review - Core/Duplicate",IF(OR(AB3="Yes",AC3="Yes"),"Clean - Flagged","Clean")) -> Clean | AI3: Standard airport-level finance comparability | AJ3: DWU transcription of FAA CATS Form 127 | AK3: https://dwuconsulting.com/airports/ATL
A4: =B4&"-"&G4 -> ATL-2021 | B4: ATL | C4: Hartsfield/Jackson Atlanta International | D4: Atlanta | E4: GA | F4: Large | G4: 2021 | H4: 24928472 | I4: 354470000 | L4: 15375000 | M4: 9696000 | N4: 33423000 | O4: 71047000 | Q4: 3468000 | T4: 318621000 | U4: -249958000 | V4: 741487000 | W4: 3366052000 | X4: 142332000 | Y4: =SUM(L4:S4) -> 133009000 | Z4: =IFERROR(Y4/I4,0) -> 0.37523345 | AA4: =IF(OR(H4="",I4="",T4="",U4=""),"Yes","No") -> No | AB4: =IF(OR(AND(L4<>"",L4=0),AND(M4<>"",M4=0),AND(N4<>"",N4=0),AND(O4<>"",O4=0),AND(Q4<>"",Q4=0)),"Yes","No") -> No | AC4: =IF(MIN(L4:O4,Q4)<0,"Yes","No") -> No | AD4: =IF(U4<0,"Yes","No") -> Yes | AE4: =IF(COUNTIFS($B$2:$B$187,B4,$G$2:$G$187,G4)>1,"Yes","No") -> No | AF4: Yes | AG4: =IF(OR(J4="",K4="",P4="",R4="",S4=""),"Yes","No") -> Yes | AH4: =IF(OR(AA4="Yes",AE4="Yes"),"Review - Core/Duplicate",IF(OR(AB4="Yes",AC4="Yes"),"Clean - Flagged","Clean")) -> Clean | AI4: Standard airport-level finance comparability | AJ4: DWU transcription of FAA CATS Form 127 | AK4: https://dwuconsulting.com/airports/ATL
A5: =B5&"-"&G5 -> ATL-2022 | B5: ATL | C5: Hartsfield/Jackson Atlanta International | D5: Atlanta | E5: GA | F5: Large | G5: 2022 | H5: 44860920 | I5: 379356000 | L5: 17315000 | M5: 11485000 | N5: 45636000 | O5: 158141000 | Q5: 4690000 | T5: 308864000 | U5: -221088000 | V5: 1081124000 | W5: 3809061000 | X5: 46714000 | Y5: =SUM(L5:S5) -> 237267000 | Z5: =IFERROR(Y5/I5,0) -> 0.62544681 | AA5: =IF(OR(H5="",I5="",T5="",U5=""),"Yes","No") -> No | AB5: =IF(OR(AND(L5<>"",L5=0),AND(M5<>"",M5=0),AND(N5<>"",N5=0),AND(O5<>"",O5=0),AND(Q5<>"",Q5=0)),"Yes","No") -> No | AC5: =IF(MIN(L5:O5,Q5)<0,"Yes","No") -> No | AD5: =IF(U5<0,"Yes","No") -> Yes | AE5: =IF(COUNTIFS($B$2:$B$187,B5,$G$2:$G$187,G5)>1,"Yes","No") -> No | AF5: Yes | AG5: =IF(OR(J5="",K5="",P5="",R5="",S5=""),"Yes","No") -> Yes | AH5: =IF(OR(AA5="Yes",AE5="Yes"),"Review - Core/Duplicate",IF(OR(AB5="Yes",AC5="Yes"),"Clean - Flagged","Clean")) -> Clean | AI5: Standard airport-level finance comparability | AJ5: DWU transcription of FAA CATS Form 127 | AK5: https://dwuconsulting.com/airports/ATL
A6: =B6&"-"&G6 -> ATL-2023 | B6: ATL | C6: Hartsfield/Jackson Atlanta International | D6: Atlanta | E6: GA | F6: Large | G6: 2023 | H6: 49691940 | I6: 508301000 | L6: 33455000 | M6: 21847000 | N6: 53039000 | O6: 176694000 | Q6: 6131000 | T6: 371155000 | U6: -167133000 | V6: 1081740000 | W6: 3471964000 | X6: 112705000 | Y6: =SUM(L6:S6) -> 291166000 | Z6: =IFERROR(Y6/I6,0) -> 0.57282201 | AA6: =IF(OR(H6="",I6="",T6="",U6=""),"Yes","No") -> No | AB6: =IF(OR(AND(L6<>"",L6=0),AND(M6<>"",M6=0),AND(N6<>"",N6=0),AND(O6<>"",O6=0),AND(Q6<>"",Q6=0)),"Yes","No") -> No | AC6: =IF(MIN(L6:O6,Q6)<0,"Yes","No") -> No | AD6: =IF(U6<0,"Yes","No") -> Yes | AE6: =IF(COUNTIFS($B$2:$B$187,B6,$G$2:$G$187,G6)>1,"Yes","No") -> No | AF6: Yes | AG6: =IF(OR(J6="",K6="",P6="",R6="",S6=""),"Yes","No") -> Yes | AH6: =IF(OR(AA6="Yes",AE6="Yes"),"Review - Core/Duplicate",IF(OR(AB6="Yes",AC6="Yes"),"Clean - Flagged","Clean")) -> Clean | AI6: Standard airport-level finance comparability | AJ6: DWU transcription of FAA CATS Form 127 | AK6: https://dwuconsulting.com/airports/ATL
A7: =B7&"-"&G7 -> ATL-2024 | B7: ATL | C7: Hartsfield/Jackson Atlanta International | D7: Atlanta | E7: GA | F7: Large | G7: 2024 | H7: 53681363 | I7: 682121000 | L7: 65475000 | M7: 47319000 | N7: 54030000 | O7: 179454000 | Q7: 14575000 | T7: 403204000 | U7: -40446000 | V7: 1593429000 | W7: 4407374000 | X7: 211157000 | Y7: =SUM(L7:S7) -> 360853000 | Z7: =IFERROR(Y7/I7,0) -> 0.52901611 | AA7: =IF(OR(H7="",I7="",T7="",U7=""),"Yes","No") -> No | AB7: =IF(OR(AND(L7<>"",L7=0),AND(M7<>"",M7=0),AND(N7<>"",N7=0),AND(O7<>"",O7=0),AND(Q7<>"",Q7=0)),"Yes","No") -> No | AC7: =IF(MIN(L7:O7,Q7)<0,"Yes","No") -> No | AD7: =IF(U7<0,"Yes","No") -> Yes | AE7: =IF(COUNTIFS($B$2:$B$187,B7,$G$2:$G$187,G7)>1,"Yes","No") -> No | AF7: Yes | AG7: =IF(OR(J7="",K7="",P7="",R7="",S7=""),"Yes","No") -> Yes | AH7: =IF(OR(AA7="Yes",AE7="Yes"),"Review - Core/Duplicate",IF(OR(AB7="Yes",AC7="Yes"),"Clean - Flagged","Clean")) -> Clean | AI7: Standard airport-level finance comparability | AJ7: DWU transcription of FAA CATS Form 127 | AK7: https://dwuconsulting.com/airports/ATL
A8: =B8&"-"&G8 -> AUS-2019 | B8: AUS | C8: Austin-Bergstrom International | D8: Austin | E8: TX | F8: Large | G8: 2019 | H8: 8464615 | I8: 180290000 | L8: 12076000 | M8: 4686000 | N8: 15693000 | O8: 47648000 | Q8: 4368000 | T8: 131753000 | U8: 13317000 | V8: 198538000 | W8: 1024367000 | X8: 75119000 | Y8: =SUM(L8:S8) -> 84471000 | Z8: =IFERROR(Y8/I8,0) -> 0.46852848 | AA8: =IF(OR(H8="",I8="",T8="",U8=""),"Yes","No") -> No | AB8: =IF(OR(AND(L8<>"",L8=0),AND(M8<>"",M8=0),AND(N8<>"",N8=0),AND(O8<>"",O8=0),AND(Q8<>"",Q8=0)),"Yes","No") -> No | AC8: =IF(MIN(L8:O8,Q8)<0,"Yes","No") -> No | AD8: =IF(U8<0,"Yes","No") -> No | AE8: =IF(COUNTIFS($B$2:$B$187,B8,$G$2:$G$187,G8)>1,"Yes","No") -> No | AF8: Yes | AG8: =IF(OR(J8="",K8="",P8="",R8="",S8=""),"Yes","No") -> Yes | AH8: =IF(OR(AA8="Yes",AE8="Yes"),"Review - Core/Duplicate",IF(OR(AB8="Yes",AC8="Yes"),"Clean - Flagged","Clean")) -> Clean | AI8: Standard airport-level finance comparability | AJ8: DWU transcription of FAA CATS Form 127 | AK8: https://dwuconsulting.com/airports/AUS
A9: =B9&"-"&G9 -> AUS-2020 | B9: AUS | C9: Austin-Bergstrom International | D9: Austin | E9: TX | F9: Large | G9: 2020 | H9: 4723544 | I9: 144637000 | L9: 7321000 | M9: 3241000 | N9: 10259000 | O9: 27322000 | Q9: 4698000 | T9: 136823000 | U9: -34656000 | V9: 106183000 | W9: 1009122000 | X9: 71440000 | Y9: =SUM(L9:S9) -> 52841000 | Z9: =IFERROR(Y9/I9,0) -> 0.36533529 | AA9: =IF(OR(H9="",I9="",T9="",U9=""),"Yes","No") -> No | AB9: =IF(OR(AND(L9<>"",L9=0),AND(M9<>"",M9=0),AND(N9<>"",N9=0),AND(O9<>"",O9=0),AND(Q9<>"",Q9=0)),"Yes","No") -> No | AC9: =IF(MIN(L9:O9,Q9)<0,"Yes","No") -> No | AD9: =IF(U9<0,"Yes","No") -> Yes | AE9: =IF(COUNTIFS($B$2:$B$187,B9,$G$2:$G$187,G9)>1,"Yes","No") -> No | AF9: Yes | AG9: =IF(OR(J9="",K9="",P9="",R9="",S9=""),"Yes","No") -> Yes | AH9: =IF(OR(AA9="Yes",AE9="Yes"),"Review - Core/Duplicate",IF(OR(AB9="Yes",AC9="Yes"),"Clean - Flagged","Clean")) -> Clean | AI9: Standard airport-level finance comparability | AJ9: DWU transcription of FAA CATS Form 127 | AK9: https://dwuconsulting.com/airports/AUS
A10: =B10&"-"&G10 -> AUS-2021 | B10: AUS | C10: Austin-Bergstrom International | D10: Austin | E10: TX | F10: Large | G10: 2021 | H10: 5207769 | I10: 155711000 | L10: 7593000 | M10: 5610000 | N10: 12851000 | O10: 31569000 | Q10: 3955000 | T10: 121776000 | U10: -10220000 | V10: 69640000 | W10: 982245000 | X10: 72777000 | Y10: =SUM(L10:S10) -> 61578000 | Z10: =IFERROR(Y10/I10,0) -> 0.39546339 | AA10: =IF(OR(H10="",I10="",T10="",U10=""),"Yes","No") -> No | AB10: =IF(OR(AND(L10<>"",L10=0),AND(M10<>"",M10=0),AND(N10<>"",N10=0),AND(O10<>"",O10=0),AND(Q10<>"",Q10=0)),"Yes","No") -> No | AC10: =IF(MIN(L10:O10,Q10)<0,"Yes","No") -> No | AD10: =IF(U10<0,"Yes","No") -> Yes | AE10: =IF(COUNTIFS($B$2:$B$187,B10,$G$2:$G$187,G10)>1,"Yes","No") -> No | AF10: Yes | AG10: =IF(OR(J10="",K10="",P10="",R10="",S10=""),"Yes","No") -> Yes | AH10: =IF(OR(AA10="Yes",AE10="Yes"),"Review - Core/Duplicate",IF(OR(AB10="Yes",AC10="Yes"),"Clean - Flagged","Clean")) -> Clean | AI10: Standard airport-level finance comparability | AJ10: DWU transcription of FAA CATS Form 127 | AK10: https://dwuconsulting.com/airports/AUS
A11: =B11&"-"&G11 -> AUS-2022 | B11: AUS | C11: Austin-Bergstrom International | D11: Austin | E11: TX | F11: Large | G11: 2022 | H11: 10133735 | I11: 231753000 | L11: 15648000 | M11: 6739000 | N11: 19901000 | O11: 67131000 | Q11: 7434000 | T11: 142496000 | U11: 41500000 | V11: 56781000 | W11: 1372080000 | X11: 96964000 | Y11: =SUM(L11:S11) -> 116853000 | Z11: =IFERROR(Y11/I11,0) -> 0.50421354 | AA11: =IF(OR(H11="",I11="",T11="",U11=""),"Yes","No") -> No | AB11: =IF(OR(AND(L11<>"",L11=0),AND(M11<>"",M11=0),AND(N11<>"",N11=0),AND(O11<>"",O11=0),AND(Q11<>"",Q11=0)),"Yes","No") -> No | AC11: =IF(MIN(L11:O11,Q11)<0,"Yes","No") -> No | AD11: =IF(U11<0,"Yes","No") -> No | AE11: =IF(COUNTIFS($B$2:$B$187,B11,$G$2:$G$187,G11)>1,"Yes","No") -> No | AF11: Yes | AG11: =IF(OR(J11="",K11="",P11="",R11="",S11=""),"Yes","No") -> Yes | AH11: =IF(OR(AA11="Yes",AE11="Yes"),"Review - Core/Duplicate",IF(OR(AB11="Yes",AC11="Yes"),"Clean - Flagged","Clean")) -> Clean | AI11: Standard airport-level finance comparability | AJ11: DWU transcription of FAA CATS Form 127 | AK11: https://dwuconsulting.com/airports/AUS
A12: =B12&"-"&G12 -> AUS-2023 | B12: AUS | C12: Austin-Bergstrom International | D12: Austin | E12: TX | F12: Large | G12: 2023 | H12: 10960717 | I12: 278512000 | L12: 18683000 | M12: 7089000 | N12: 20850000 | O12: 79408000 | Q12: 9392000 | T12: 177519000 | U12: 51827000 | V12: 216216000 | W12: 1340355000 | X12: 116282000 | Y12: =SUM(L12:S12) -> 135422000 | Z12: =IFERROR(Y12/I12,0) -> 0.48623399 | AA12: =IF(OR(H12="",I12="",T12="",U12=""),"Yes","No") -> No | AB12: =IF(OR(AND(L12<>"",L12=0),AND(M12<>"",M12=0),AND(N12<>"",N12=0),AND(O12<>"",O12=0),AND(Q12<>"",Q12=0)),"Yes","No") -> No | AC12: =IF(MIN(L12:O12,Q12)<0,"Yes","No") -> No | AD12: =IF(U12<0,"Yes","No") -> No | AE12: =IF(COUNTIFS($B$2:$B$187,B12,$G$2:$G$187,G12)>1,"Yes","No") -> No | AF12: Yes | AG12: =IF(OR(J12="",K12="",P12="",R12="",S12=""),"Yes","No") -> Yes | AH12: =IF(OR(AA12="Yes",AE12="Yes"),"Review - Core/Duplicate",IF(OR(AB12="Yes",AC12="Yes"),"Clean - Flagged","Clean")) -> Clean | AI12: Standard airport-level finance comparability | AJ12: DWU transcription of FAA CATS Form 127 | AK12: https://dwuconsulting.com/airports/AUS
A13: =B13&"-"&G13 -> AUS-2024 | B13: AUS | C13: Austin-Bergstrom International | D13: Austin | E13: TX | F13: Large | G13: 2024 | H13: 11006681 | I13: 324743000 | L13: 19978000 | M13: 6951000 | N13: 21620000 | O13: 86837000 | Q13: 10818000 | T13: 167743000 | U13: 107501000 | V13: 151055000 | W13: 1307305000 | X13: 149063000 | Y13: =SUM(L13:S13) -> 146204000 | Z13: =IFERROR(Y13/I13,0) -> 0.45021448 | AA13: =IF(OR(H13="",I13="",T13="",U13=""),"Yes","No") -> No | AB13: =IF(OR(AND(L13<>"",L13=0),AND(M13<>"",M13=0),AND(N13<>"",N13=0),AND(O13<>"",O13=0),AND(Q13<>"",Q13=0)),"Yes","No") -> No | AC13: =IF(MIN(L13:O13,Q13)<0,"Yes","No") -> No | AD13: =IF(U13<0,"Yes","No") -> No | AE13: =IF(COUNTIFS($B$2:$B$187,B13,$G$2:$G$187,G13)>1,"Yes","No") -> No | AF13: Yes | AG13: =IF(OR(J13="",K13="",P13="",R13="",S13=""),"Yes","No") -> Yes | AH13: =IF(OR(AA13="Yes",AE13="Yes"),"Review - Core/Duplicate",IF(OR(AB13="Yes",AC13="Yes"),"Clean - Flagged","Clean")) -> Clean | AI13: Standard airport-level finance comparability | AJ13: DWU transcription of FAA CATS Form 127 | AK13: https://dwuconsulting.com/airports/AUS
... A61: =B61&"-"&G61 -> DTW-2024 | B61: DTW | C61: Detroit Metro Wayne County | D61: Detroit | E61: MI | F61: Large | G61: 2024 | H61: 16453913 | I61: 396377000 | L61: 15069000 | M61: 7816000 | N61: 30869000 | O61: 119603000 | Q61: 4859000 | T61: 236232000 | U61: 41560000 | V61: 155222000 | W61: 1997805000 | X61: 146044000 | Y61: =SUM(L61:S61) -> 178216000 | Z61: =IFERROR(Y61/I61,0) -> 0.44961236 | AA61: =IF(OR(H61="",I61="",T61="",U61=""),"Yes","No") -> No | AB61: =IF(OR(AND(L61<>"",L61=0),AND(M61<>"",M61=0),AND(N61<>"",N61=0),AND(O61<>"",O61=0),AND(Q61<>"",Q61=0)),"Yes","No") -> No | AC61: =IF(MIN(L61:O61,Q61)<0,"Yes","No") -> No | AD61: =IF(U61<0,"Yes","No") -> No | AE61: =IF(COUNTIFS($B$2:$B$187,B61,$G$2:$G$187,G61)>1,"Yes","No") -> No | AF61: Yes | AG61: =IF(OR(J61="",K61="",P61="",R61="",S61=""),"Yes","No") -> Yes | AH61: =IF(OR(AA61="Yes",AE61="Yes"),"Review - Core/Duplicate",IF(OR(AB61="Yes",AC61="Yes"),"Clean - Flagged","Clean")) -> Clean | AI61: Standard airport-level finance comparability | AJ61: DWU transcription of FAA CATS Form 127 | AK61: https://dwuconsulting.com/airports/DTW
A62: =B62&"-"&G62 -> EWR-2019 | B62: EWR | C62: Newark Liberty International | D62: Newark | E62: NJ | F62: Large | G62: 2019 | H62: 23168226 | I62: 1052070000 | L62: 6532000 | M62: 33853000 | N62: 41086000 | O62: 107437000 | Q62: 1171000 | T62: 591802000 | U62: 311728000 | V62: 719703000 | X62: 634915000 | Y62: =SUM(L62:S62) -> 190079000 | Z62: =IFERROR(Y62/I62,0) -> 0.18067144 | AA62: =IF(OR(H62="",I62="",T62="",U62=""),"Yes","No") -> No | AB62: =IF(OR(AND(L62<>"",L62=0),AND(M62<>"",M62=0),AND(N62<>"",N62=0),AND(O62<>"",O62=0),AND(Q62<>"",Q62=0)),"Yes","No") -> No | AC62: =IF(MIN(L62:O62,Q62)<0,"Yes","No") -> No | AD62: =IF(U62<0,"Yes","No") -> No | AE62: =IF(COUNTIFS($B$2:$B$187,B62,$G$2:$G$187,G62)>1,"Yes","No") -> No | AF62: No | AG62: =IF(OR(J62="",K62="",P62="",R62="",S62=""),"Yes","No") -> Yes | AH62: =IF(OR(AA62="Yes",AE62="Yes"),"Review - Core/Duplicate",IF(OR(AB62="Yes",AC62="Yes"),"Clean - Flagged","Clean")) -> Clean | AI62: PANYNJ system-level debt/credit; exclude debt metrics from peer ranking | AJ62: DWU transcription of FAA CATS Form 127 | AK62: https://dwuconsulting.com/airports/EWR
A63: =B63&"-"&G63 -> EWR-2020 | B63: EWR | C63: Newark Liberty International | D63: Newark | E63: NJ | F63: Large | G63: 2020 | H63: 7973879 | I63: 739600000 | L63: 962000 | M63: 9224000 | N63: 17527000 | O63: 39875000 | Q63: 689000 | T63: 544024000 | U63: 43945000 | V63: 690772000 | X63: 472747000 | Y63: =SUM(L63:S63) -> 68277000 | Z63: =IFERROR(Y63/I63,0) -> 0.092316117 | AA63: =IF(OR(H63="",I63="",T63="",U63=""),"Yes","No") -> No | AB63: =IF(OR(AND(L63<>"",L63=0),AND(M63<>"",M63=0),AND(N63<>"",N63=0),AND(O63<>"",O63=0),AND(Q63<>"",Q63=0)),"Yes","No") -> No | AC63: =IF(MIN(L63:O63,Q63)<0,"Yes","No") -> No | AD63: =IF(U63<0,"Yes","No") -> No | AE63: =IF(COUNTIFS($B$2:$B$187,B63,$G$2:$G$187,G63)>1,"Yes","No") -> No | AF63: No | AG63: =IF(OR(J63="",K63="",P63="",R63="",S63=""),"Yes","No") -> Yes | AH63: =IF(OR(AA63="Yes",AE63="Yes"),"Review - Core/Duplicate",IF(OR(AB63="Yes",AC63="Yes"),"Clean - Flagged","Clean")) -> Clean | AI63: PANYNJ system-level debt/credit; exclude debt metrics from peer ranking | AJ63: DWU transcription of FAA CATS Form 127 | AK63: https://dwuconsulting.com/airports/EWR
A64: =B64&"-"&G64 -> EWR-2021 | B64: EWR | C64: Newark Liberty International | D64: Newark | E64: NJ | F64: Large | G64: 2021 | H64: 14472936 | I64: 976598000 | L64: 4614000 | M64: 12009000 | N64: 28383000 | O64: 91758000 | Q64: 1121000 | T64: 531396000 | U64: 289823000 | V64: 654193000 | X64: 634594000 | Y64: =SUM(L64:S64) -> 137885000 | Z64: =IFERROR(Y64/I64,0) -> 0.14118911 | AA64: =IF(OR(H64="",I64="",T64="",U64=""),"Yes","No") -> No | AB64: =IF(OR(AND(L64<>"",L64=0),AND(M64<>"",M64=0),AND(N64<>"",N64=0),AND(O64<>"",O64=0),AND(Q64<>"",Q64=0)),"Yes","No") -> No | AC64: =IF(MIN(L64:O64,Q64)<0,"Yes","No") -> No | AD64: =IF(U64<0,"Yes","No") -> No | AE64: =IF(COUNTIFS($B$2:$B$187,B64,$G$2:$G$187,G64)>1,"Yes","No") -> No | AF64: No | AG64: =IF(OR(J64="",K64="",P64="",R64="",S64=""),"Yes","No") -> Yes | AH64: =IF(OR(AA64="Yes",AE64="Yes"),"Review - Core/Duplicate",IF(OR(AB64="Yes",AC64="Yes"),"Clean - Flagged","Clean")) -> Clean | AI64: PANYNJ system-level debt/credit; exclude debt metrics from peer ranking | AJ64: DWU transcription of FAA CATS Form 127 | AK64: https://dwuconsulting.com/airports/EWR
A65: =B65&"-"&G65 -> EWR-2022 | B65: EWR | C65: Newark Liberty International | D65: Newark | E65: NJ | F65: Large | G65: 2022 | H65: 21796929 | I65: 1142687000 | L65: 6379000 | M65: 19635000 | N65: 44041000 | O65: 146273000 | Q65: 1204000 | T65: 628688000 | U65: 340431000 | V65: 515522000 | X65: 637335000 | Y65: =SUM(L65:S65) -> 217532000 | Z65: =IFERROR(Y65/I65,0) -> 0.19036884 | AA65: =IF(OR(H65="",I65="",T65="",U65=""),"Yes","No") -> No | AB65: =IF(OR(AND(L65<>"",L65=0),AND(M65<>"",M65=0),AND(N65<>"",N65=0),AND(O65<>"",O65=0),AND(Q65<>"",Q65=0)),"Yes","No") -> No | AC65: =IF(MIN(L65:O65,Q65)<0,"Yes","No") -> No | AD65: =IF(U65<0,"Yes","No") -> No | AE65: =IF(COUNTIFS($B$2:$B$187,B65,$G$2:$G$187,G65)>1,"Yes","No") -> No | AF65: No | AG65: =IF(OR(J65="",K65="",P65="",R65="",S65=""),"Yes","No") -> Yes | AH65: =IF(OR(AA65="Yes",AE65="Yes"),"Review - Core/Duplicate",IF(OR(AB65="Yes",AC65="Yes"),"Clean - Flagged","Clean")) -> Clean | AI65: PANYNJ system-level debt/credit; exclude debt metrics from peer ranking | AJ65: DWU transcription of FAA CATS Form 127 | AK65: https://dwuconsulting.com/airports/EWR
A66: =B66&"-"&G66 -> EWR-2023 | B66: EWR | C66: Newark Liberty International | D66: Newark | E66: NJ | F66: Large | G66: 2023 | H66: 24556503 | I66: 1357187000 | L66: 22009000 | M66: 35905000 | N66: 51928000 | O66: 166997000 | Q66: 1212000 | T66: 749584000 | U66: 367792000 | V66: 225818000 | X66: 751529000 | Y66: =SUM(L66:S66) -> 278051000 | Z66: =IFERROR(Y66/I66,0) -> 0.20487302 | AA66: =IF(OR(H66="",I66="",T66="",U66=""),"Yes","No") -> No | AB66: =IF(OR(AND(L66<>"",L66=0),AND(M66<>"",M66=0),AND(N66<>"",N66=0),AND(O66<>"",O66=0),AND(Q66<>"",Q66=0)),"Yes","No") -> No | AC66: =IF(MIN(L66:O66,Q66)<0,"Yes","No") -> No | AD66: =IF(U66<0,"Yes","No") -> No | AE66: =IF(COUNTIFS($B$2:$B$187,B66,$G$2:$G$187,G66)>1,"Yes","No") -> No | AF66: No | AG66: =IF(OR(J66="",K66="",P66="",R66="",S66=""),"Yes","No") -> Yes | AH66: =IF(OR(AA66="Yes",AE66="Yes"),"Review - Core/Duplicate",IF(OR(AB66="Yes",AC66="Yes"),"Clean - Flagged","Clean")) -> Clean | AI66: PANYNJ system-level debt/credit; exclude debt metrics from peer ranking | AJ66: DWU transcription of FAA CATS Form 127 | AK66: https://dwuconsulting.com/airports/EWR
A67: =B67&"-"&G67 -> EWR-2024 | B67: EWR | C67: Newark Liberty International | D67: Newark | E67: NJ | F67: Large | G67: 2024 | H67: 24426685 | I67: 1391598000 | L67: 24876000 | M67: 46193000 | N67: 57221000 | O67: 159208000 | Q67: 1217000 | T67: 785968000 | U67: 364605000 | V67: 429118000 | X67: 773528000 | Y67: =SUM(L67:S67) -> 288715000 | Z67: =IFERROR(Y67/I67,0) -> 0.20747012 | AA67: =IF(OR(H67="",I67="",T67="",U67=""),"Yes","No") -> No | AB67: =IF(OR(AND(L67<>"",L67=0),AND(M67<>"",M67=0),AND(N67<>"",N67=0),AND(O67<>"",O67=0),AND(Q67<>"",Q67=0)),"Yes","No") -> No | AC67: =IF(MIN(L67:O67,Q67)<0,"Yes","No") -> No | AD67: =IF(U67<0,"Yes","No") -> No | AE67: =IF(COUNTIFS($B$2:$B$187,B67,$G$2:$G$187,G67)>1,"Yes","No") -> No | AF67: No | AG67: =IF(OR(J67="",K67="",P67="",R67="",S67=""),"Yes","No") -> Yes | AH67: =IF(OR(AA67="Yes",AE67="Yes"),"Review - Core/Duplicate",IF(OR(AB67="Yes",AC67="Yes"),"Clean - Flagged","Clean")) -> Clean | AI67: PANYNJ system-level debt/credit; exclude debt metrics from peer ranking | AJ67: DWU transcription of FAA CATS Form 127 | AK67: https://dwuconsulting.com/airports/EWR
A68: =B68&"-"&G68 -> FLL-2019 | B68: FLL | C68: Fort Lauderdale/Hollywood International | D68: Fort Lauderdale | E68: FL | F68: Large | G68: 2019 | H68: 18164427 | I68: 306141000 | L68: 21037000 | M68: 10968000 | N68: 33001000 | O68: 61565000 | Q68: 5046000 | T68: 196692000 | U68: -16623000 | V68: 202862000 | W68: 2027095000 | X68: 125087000 | Y68: =SUM(L68:S68) -> 131617000 | Z68: =IFERROR(Y68/I68,0) -> 0.42992281 | AA68: =IF(OR(H68="",I68="",T68="",U68=""),"Yes","No") -> No | AB68: =IF(OR(AND(L68<>"",L68=0),AND(M68<>"",M68=0),AND(N68<>"",N68=0),AND(O68<>"",O68=0),AND(Q68<>"",Q68=0)),"Yes","No") -> No | AC68: =IF(MIN(L68:O68,Q68)<0,"Yes","No") -> No | AD68: =IF(U68<0,"Yes","No") -> Yes | AE68: =IF(COUNTIFS($B$2:$B$187,B68,$G$2:$G$187,G68)>1,"Yes","No") -> No | AF68: Yes | AG68: =IF(OR(J68="",K68="",P68="",R68="",S68=""),"Yes","No") -> Yes | AH68: =IF(OR(AA68="Yes",AE68="Yes"),"Review - Core/Duplicate",IF(OR(AB68="Yes",AC68="Yes"),"Clean - Flagged","Clean")) -> Clean | AI68: Standard airport-level finance comparability | AJ68: DWU transcription of FAA CATS Form 127 | AK68: https://dwuconsulting.com/airports/FLL
A69: =B69&"-"&G69 -> FLL-2020 | B69: FLL | C69: Fort Lauderdale/Hollywood International | D69: Fort Lauderdale | E69: FL | F69: Large | G69: 2020 | H69: 10683612 | I69: 342576000 | L69: 11330000 | M69: 6856000 | N69: 27851000 | O69: 33614000 | Q69: 4193000 | T69: 171342000 | U69: 46989000 | V69: 231314000 | W69: 2458865000 | X69: 115117000 | Y69: =SUM(L69:S69) -> 83844000 | Z69: =IFERROR(Y69/I69,0) -> 0.24474569 | AA69: =IF(OR(H69="",I69="",T69="",U69=""),"Yes","No") -> No | AB69: =IF(OR(AND(L69<>"",L69=0),AND(M69<>"",M69=0),AND(N69<>"",N69=0),AND(O69<>"",O69=0),AND(Q69<>"",Q69=0)),"Yes","No") -> No | AC69: =IF(MIN(L69:O69,Q69)<0,"Yes","No") -> No | AD69: =IF(U69<0,"Yes","No") -> No | AE69: =IF(COUNTIFS($B$2:$B$187,B69,$G$2:$G$187,G69)>1,"Yes","No") -> No | AF69: Yes | AG69: =IF(OR(J69="",K69="",P69="",R69="",S69=""),"Yes","No") -> Yes | AH69: =IF(OR(AA69="Yes",AE69="Yes"),"Review - Core/Duplicate",IF(OR(AB69="Yes",AC69="Yes"),"Clean - Flagged","Clean")) -> Clean | AI69: Standard airport-level finance comparability | AJ69: DWU transcription of FAA CATS Form 127 | AK69: https://dwuconsulting.com/airports/FLL
A70: =B70&"-"&G70 -> FLL-2021 | B70: FLL | C70: Fort Lauderdale/Hollywood International | D70: Fort Lauderdale | E70: FL | F70: Large | G70: 2021 | H70: 12482905 | I70: 295199000 | L70: 13658000 | M70: 9838000 | N70: 39448000 | O70: 39417000 | Q70: 5524000 | T70: 159830000 | U70: 3589000 | V70: 152635000 | W70: 2374770000 | X70: 136806000 | Y70: =SUM(L70:S70) -> 107885000 | Z70: =IFERROR(Y70/I70,0) -> 0.36546533 | AA70: =IF(OR(H70="",I70="",T70="",U70=""),"Yes","No") -> No | AB70: =IF(OR(AND(L70<>"",L70=0),AND(M70<>"",M70=0),AND(N70<>"",N70=0),AND(O70<>"",O70=0),AND(Q70<>"",Q70=0)),"Yes","No") -> No | AC70: =IF(MIN(L70:O70,Q70)<0,"Yes","No") -> No | AD70: =IF(U70<0,"Yes","No") -> No | AE70: =IF(COUNTIFS($B$2:$B$187,B70,$G$2:$G$187,G70)>1,"Yes","No") -> No | AF70: Yes | AG70: =IF(OR(J70="",K70="",P70="",R70="",S70=""),"Yes","No") -> Yes | AH70: =IF(OR(AA70="Yes",AE70="Yes"),"Review - Core/Duplicate",IF(OR(AB70="Yes",AC70="Yes"),"Clean - Flagged","Clean")) -> Clean | AI70: Standard airport-level finance comparability | AJ70: DWU transcription of FAA CATS Form 127 | AK70: https://dwuconsulting.com/airports/FLL
A71: =B71&"-"&G71 -> FLL-2022 | B71: FLL | C71: Fort Lauderdale/Hollywood International | D71: Fort Lauderdale | E71: FL | F71: Large | G71: 2022 | H71: 15397295 | I71: 313834000 | L71: 12168000 | M71: 6127000 | N71: 43914000 | O71: 61899000 | Q71: 4008000 | T71: 216975000 | U71: -41397000 | V71: 80688000 | W71: 2284115000 | X71: 123494000 | Y71: =SUM(L71:S71) -> 128116000 | Z71: =IFERROR(Y71/I71,0) -> 0.40822855 | AA71: =IF(OR(H71="",I71="",T71="",U71=""),"Yes","No") -> No | AB71: =IF(OR(AND(L71<>"",L71=0),AND(M71<>"",M71=0),AND(N71<>"",N71=0),AND(O71<>"",O71=0),AND(Q71<>"",Q71=0)),"Yes","No") -> No | AC71: =IF(MIN(L71:O71,Q71)<0,"Yes","No") -> No | AD71: =IF(U71<0,"Yes","No") -> Yes | AE71: =IF(COUNTIFS($B$2:$B$187,B71,$G$2:$G$187,G71)>1,"Yes","No") -> No | AF71: Yes | AG71: =IF(OR(J71="",K71="",P71="",R71="",S71=""),"Yes","No") -> Yes | AH71: =IF(OR(AA71="Yes",AE71="Yes"),"Review - Core/Duplicate",IF(OR(AB71="Yes",AC71="Yes"),"Clean - Flagged","Clean")) -> Clean | AI71: Standard airport-level finance comparability | AJ71: DWU transcription of FAA CATS Form 127 | AK71: https://dwuconsulting.com/airports/FLL
A72: =B72&"-"&G72 -> FLL-2023 | B72: FLL | C72: Fort Lauderdale/Hollywood International | D72: Fort Lauderdale | E72: FL | F72: Large | G72: 2023 | H72: 17116674 | I72: 304708000 | L72: 18450000 | M72: 12968000 | N72: 43418000 | O72: 70528000 | Q72: 3144000 | T72: 259352000 | U72: -115552000 | V72: 59746000 | W72: 2188870000 | X72: 125695000 | Y72: =SUM(L72:S72) -> 148508000 | Z72: =IFERROR(Y72/I72,0) -> 0.48737808 | AA72: =IF(OR(H72="",I72="",T72="",U72=""),"Yes","No") -> No | AB72: =IF(OR(AND(L72<>"",L72=0),AND(M72<>"",M72=0),AND(N72<>"",N72=0),AND(O72<>"",O72=0),AND(Q72<>"",Q72=0)),"Yes","No") -> No | AC72: =IF(MIN(L72:O72,Q72)<0,"Yes","No") -> No | AD72: =IF(U72<0,"Yes","No") -> Yes | AE72: =IF(COUNTIFS($B$2:$B$187,B72,$G$2:$G$187,G72)>1,"Yes","No") -> No | AF72: Yes | AG72: =IF(OR(J72="",K72="",P72="",R72="",S72=""),"Yes","No") -> Yes | AH72: =IF(OR(AA72="Yes",AE72="Yes"),"Review - Core/Duplicate",IF(OR(AB72="Yes",AC72="Yes"),"Clean - Flagged","Clean")) -> Clean | AI72: Standard airport-level finance comparability | AJ72: DWU transcription of FAA CATS Form 127 | AK72: https://dwuconsulting.com/airports/FLL
A73: =B73&"-"&G73 -> FLL-2024 | B73: FLL | C73: Fort Lauderdale/Hollywood International | D73: Fort Lauderdale | E73: FL | F73: Large | G73: 2024 | H73: 17741898 | I73: 340946000 | L73: 24024000 | M73: 14342000 | N73: 43438000 | O73: 71933000 | Q73: 5688000 | T73: 282626000 | U73: -98661000 | V73: 114086000 | W73: 2089210000 | X73: 181053000 | Y73: =SUM(L73:S73) -> 159425000 | Z73: =IFERROR(Y73/I73,0) -> 0.46759604 | AA73: =IF(OR(H73="",I73="",T73="",U73=""),"Yes","No") -> No | AB73: =IF(OR(AND(L73<>"",L73=0),AND(M73<>"",M73=0),AND(N73<>"",N73=0),AND(O73<>"",O73=0),AND(Q73<>"",Q73=0)),"Yes","No") -> No | AC73: =IF(MIN(L73:O73,Q73)<0,"Yes","No") -> No | AD73: =IF(U73<0,"Yes","No") -> Yes | AE73: =IF(COUNTIFS($B$2:$B$187,B73,$G$2:$G$187,G73)>1,"Yes","No") -> No | AF73: Yes | AG73: =IF(OR(J73="",K73="",P73="",R73="",S73=""),"Yes","No") -> Yes | AH73: =IF(OR(AA73="Yes",AE73="Yes"),"Review - Core/Duplicate",IF(OR(AB73="Yes",AC73="Yes"),"Clean - Flagged","Clean")) -> Clean | AI73: Standard airport-level finance comparability | AJ73: DWU transcription of FAA CATS Form 127 | AK73: https://dwuconsulting.com/airports/FLL
A74: =B74&"-"&G74 -> HNL-2019 | B74: HNL | C74: Daniel K Inouye International | D74: Honolulu | E74: HI | F74: Large | G74: 2019 | H74: 10484451 | I74: 290422000 | L74: 7138000 | M74: 11975000 | N74: 18276000 | O74: 17788000 | Q74: 5471000 | T74: 188802000 | U74: 36664000 | V74: 334076000 | W74: 2553500000 | X74: 135438000 | Y74: =SUM(L74:S74) -> 60648000 | Z74: =IFERROR(Y74/I74,0) -> 0.20882715 | AA74: =IF(OR(H74="",I74="",T74="",U74=""),"Yes","No") -> No | AB74: =IF(OR(AND(L74<>"",L74=0),AND(M74<>"",M74=0),AND(N74<>"",N74=0),AND(O74<>"",O74=0),AND(Q74<>"",Q74=0)),"Yes","No") -> No | AC74: =IF(MIN(L74:O74,Q74)<0,"Yes","No") -> No | AD74: =IF(U74<0,"Yes","No") -> No | AE74: =IF(COUNTIFS($B$2:$B$187,B74,$G$2:$G$187,G74)>1,"Yes","No") -> No | AF74: No | AG74: =IF(OR(J74="",K74="",P74="",R74="",S74=""),"Yes","No") -> Yes | AH74: =IF(OR(AA74="Yes",AE74="Yes"),"Review - Core/Duplicate",IF(OR(AB74="Yes",AC74="Yes"),"Clean - Flagged","Clean")) -> Clean | AI74: Hawaii Airports System pooled bond/credit; exclude debt metrics from peer ranking | AJ74: DWU transcription of FAA CATS Form 127 | AK74: https://dwuconsulting.com/airports/HNL
A75: =B75&"-"&G75 -> HNL-2020 | B75: HNL | C75: Daniel K Inouye International | D75: Honolulu | E75: HI | F75: Large | G75: 2020 | H75: 7981984 | I75: 250691000 | L75: 5417000 | M75: 8864000 | N75: 14318000 | O75: 14529000 | Q75: 5294000 | T75: 194207000 | U75: -15252000 | V75: 281475000 | W75: 2596230000 | X75: 122104000 | Y75: =SUM(L75:S75) -> 48422000 | Z75: =IFERROR(Y75/I75,0) -> 0.19315412 | AA75: =IF(OR(H75="",I75="",T75="",U75=""),"Yes","No") -> No | AB75: =IF(OR(AND(L75<>"",L75=0),AND(M75<>"",M75=0),AND(N75<>"",N75=0),AND(O75<>"",O75=0),AND(Q75<>"",Q75=0)),"Yes","No") -> No | AC75: =IF(MIN(L75:O75,Q75)<0,"Yes","No") -> No | AD75: =IF(U75<0,"Yes","No") -> Yes | AE75: =IF(COUNTIFS($B$2:$B$187,B75,$G$2:$G$187,G75)>1,"Yes","No") -> No | AF75: No | AG75: =IF(OR(J75="",K75="",P75="",R75="",S75=""),"Yes","No") -> Yes | AH75: =IF(OR(AA75="Yes",AE75="Yes"),"Review - Core/Duplicate",IF(OR(AB75="Yes",AC75="Yes"),"Clean - Flagged","Clean")) -> Clean | AI75: Hawaii Airports System pooled bond/credit; exclude debt metrics from peer ranking | AJ75: DWU transcription of FAA CATS Form 127 | AK75: https://dwuconsulting.com/airports/HNL
A76: =B76&"-"&G76 -> HNL-2021 | B76: HNL | C76: Daniel K Inouye International | D76: Honolulu | E76: HI | F76: Large | G76: 2021 | H76: 3143228 | I76: 173769000 | L76: 1014000 | M76: 286000 | N76: 10363000 | O76: 7091000 | Q76: 2584000 | T76: 201408000 | U76: -98269000 | V76: 330928000 | W76: 2899089000 | X76: 107021000 | Y76: =SUM(L76:S76) -> 21338000 | Z76: =IFERROR(Y76/I76,0) -> 0.12279521 | AA76: =IF(OR(H76="",I76="",T76="",U76=""),"Yes","No") -> No | AB76: =IF(OR(AND(L76<>"",L76=0),AND(M76<>"",M76=0),AND(N76<>"",N76=0),AND(O76<>"",O76=0),AND(Q76<>"",Q76=0)),"Yes","No") -> No | AC76: =IF(MIN(L76:O76,Q76)<0,"Yes","No") -> No | AD76: =IF(U76<0,"Yes","No") -> Yes | AE76: =IF(COUNTIFS($B$2:$B$187,B76,$G$2:$G$187,G76)>1,"Yes","No") -> No | AF76: No | AG76: =IF(OR(J76="",K76="",P76="",R76="",S76=""),"Yes","No") -> Yes | AH76: =IF(OR(AA76="Yes",AE76="Yes"),"Review - Core/Duplicate",IF(OR(AB76="Yes",AC76="Yes"),"Clean - Flagged","Clean")) -> Clean | AI76: Hawaii Airports System pooled bond/credit; exclude debt metrics from peer ranking | AJ76: DWU transcription of FAA CATS Form 127 | AK76: https://dwuconsulting.com/airports/HNL
A77: =B77&"-"&G77 -> HNL-2022 | B77: HNL | C77: Daniel K Inouye International | D77: Honolulu | E77: HI | F77: Large | G77: 2022 | H77: 7919496 | I77: 245087000 | L77: 3932000 | M77: 5849000 | N77: 29390000 | O77: 16729000 | Q77: 4792000 | T77: 209891000 | U77: -52724000 | V77: 132345000 | W77: 3010506000 | X77: 131017000 | Y77: =SUM(L77:S77) -> 60692000 | Z77: =IFERROR(Y77/I77,0) -> 0.24763451 | AA77: =IF(OR(H77="",I77="",T77="",U77=""),"Yes","No") -> No | AB77: =IF(OR(AND(L77<>"",L77=0),AND(M77<>"",M77=0),AND(N77<>"",N77=0),AND(O77<>"",O77=0),AND(Q77<>"",Q77=0)),"Yes","No") -> No | AC77: =IF(MIN(L77:O77,Q77)<0,"Yes","No") -> No | AD77: =IF(U77<0,"Yes","No") -> Yes | AE77: =IF(COUNTIFS($B$2:$B$187,B77,$G$2:$G$187,G77)>1,"Yes","No") -> No | AF77: No | AG77: =IF(OR(J77="",K77="",P77="",R77="",S77=""),"Yes","No") -> Yes | AH77: =IF(OR(AA77="Yes",AE77="Yes"),"Review - Core/Duplicate",IF(OR(AB77="Yes",AC77="Yes"),"Clean - Flagged","Clean")) -> Clean | AI77: Hawaii Airports System pooled bond/credit; exclude debt metrics from peer ranking | AJ77: DWU transcription of FAA CATS Form 127 | AK77: https://dwuconsulting.com/airports/HNL
A78: =B78&"-"&G78 -> HNL-2023 | B78: HNL | C78: Daniel K Inouye International | D78: Honolulu | E78: HI | F78: Large | G78: 2023 | H78: 10176286 | I78: 288119000 | L78: 6513000 | M78: 11647000 | N78: 28901000 | O78: 21964000 | Q78: 7358000 | T78: 216123000 | U78: -36813000 | V78: 128033000 | W78: 1685636000 | X78: 148940000 | Y78: =SUM(L78:S78) -> 76383000 | Z78: =IFERROR(Y78/I78,0) -> 0.26510921 | AA78: =IF(OR(H78="",I78="",T78="",U78=""),"Yes","No") -> No | AB78: =IF(OR(AND(L78<>"",L78=0),AND(M78<>"",M78=0),AND(N78<>"",N78=0),AND(O78<>"",O78=0),AND(Q78<>"",Q78=0)),"Yes","No") -> No | AC78: =IF(MIN(L78:O78,Q78)<0,"Yes","No") -> No | AD78: =IF(U78<0,"Yes","No") -> Yes | AE78: =IF(COUNTIFS($B$2:$B$187,B78,$G$2:$G$187,G78)>1,"Yes","No") -> No | AF78: No | AG78: =IF(OR(J78="",K78="",P78="",R78="",S78=""),"Yes","No") -> Yes | AH78: =IF(OR(AA78="Yes",AE78="Yes"),"Review - Core/Duplicate",IF(OR(AB78="Yes",AC78="Yes"),"Clean - Flagged","Clean")) -> Clean | AI78: Hawaii Airports System pooled bond/credit; exclude debt metrics from peer ranking | AJ78: DWU transcription of FAA CATS Form 127 | AK78: https://dwuconsulting.com/airports/HNL
A79: =B79&"-"&G79 -> HNL-2024 | B79: HNL | C79: Daniel K Inouye International | D79: Honolulu | E79: HI | F79: Large | G79: 2024 | H79: 10868465 | I79: 380805000 | L79: 5074000 | M79: 26395000 | N79: 19257000 | O79: 21422000 | Q79: 6634000 | T79: 269556000 | U79: -1646000 | V79: 204519000 | W79: 1645128000 | X79: 227370000 | Y79: =SUM(L79:S79) -> 78782000 | Z79: =IFERROR(Y79/I79,0) -> 0.20688279 | AA79: =IF(OR(H79="",I79="",T79="",U79=""),"Yes","No") -> No | AB79: =IF(OR(AND(L79<>"",L79=0),AND(M79<>"",M79=0),AND(N79<>"",N79=0),AND(O79<>"",O79=0),AND(Q79<>"",Q79=0)),"Yes","No") -> No | AC79: =IF(MIN(L79:O79,Q79)<0,"Yes","No") -> No | AD79: =IF(U79<0,"Yes","No") -> Yes | AE79: =IF(COUNTIFS($B$2:$B$187,B79,$G$2:$G$187,G79)>1,"Yes","No") -> No | AF79: No | AG79: =IF(OR(J79="",K79="",P79="",R79="",S79=""),"Yes","No") -> Yes | AH79: =IF(OR(AA79="Yes",AE79="Yes"),"Review - Core/Duplicate",IF(OR(AB79="Yes",AC79="Yes"),"Clean - Flagged","Clean")) -> Clean | AI79: Hawaii Airports System pooled bond/credit; exclude debt metrics from peer ranking | AJ79: DWU transcription of FAA CATS Form 127 | AK79: https://dwuconsulting.com/airports/HNL
... A93: =B93&"-"&G93 -> JFK-2020 | B93: JFK | C93: John F Kennedy International | D93: New York | E93: NY | F93: Large | G93: 2020 | H93: 8329975 | I93: 920388000 | L93: 1676000 | M93: 9800000 | N93: 17147000 | O93: 36201000 | Q93: 1806000 | T93: 816449000 | U93: -116729000 | V93: 234752000 | W93: 0 | X93: 553625000 | Y93: =SUM(L93:S93) -> 66630000 | Z93: =IFERROR(Y93/I93,0) -> 0.072393382 | AA93: =IF(OR(H93="",I93="",T93="",U93=""),"Yes","No") -> No | AB93: =IF(OR(AND(L93<>"",L93=0),AND(M93<>"",M93=0),AND(N93<>"",N93=0),AND(O93<>"",O93=0),AND(Q93<>"",Q93=0)),"Yes","No") -> No | AC93: =IF(MIN(L93:O93,Q93)<0,"Yes","No") -> No | AD93: =IF(U93<0,"Yes","No") -> Yes | AE93: =IF(COUNTIFS($B$2:$B$187,B93,$G$2:$G$187,G93)>1,"Yes","No") -> No | AF93: No | AG93: =IF(OR(J93="",K93="",P93="",R93="",S93=""),"Yes","No") -> Yes | AH93: =IF(OR(AA93="Yes",AE93="Yes"),"Review - Core/Duplicate",IF(OR(AB93="Yes",AC93="Yes"),"Clean - Flagged","Clean")) -> Clean | AI93: PANYNJ system-level debt/credit; exclude debt metrics from peer ranking | AJ93: DWU transcription of FAA CATS Form 127 | AK93: https://dwuconsulting.com/airports/JFK
A94: =B94&"-"&G94 -> JFK-2021 | B94: JFK | C94: John F Kennedy International | D94: New York | E94: NY | F94: Large | G94: 2021 | H94: 15311865 | I94: 1087199000 | L94: 2634000 | M94: 11304000 | N94: 24858000 | O94: 80659000 | Q94: 2987000 | T94: 722016000 | U94: 145646000 | V94: 128182000 | X94: 718440000 | Y94: =SUM(L94:S94) -> 122442000 | Z94: =IFERROR(Y94/I94,0) -> 0.11262152 | AA94: =IF(OR(H94="",I94="",T94="",U94=""),"Yes","No") -> No | AB94: =IF(OR(AND(L94<>"",L94=0),AND(M94<>"",M94=0),AND(N94<>"",N94=0),AND(O94<>"",O94=0),AND(Q94<>"",Q94=0)),"Yes","No") -> No | AC94: =IF(MIN(L94:O94,Q94)<0,"Yes","No") -> No | AD94: =IF(U94<0,"Yes","No") -> No | AE94: =IF(COUNTIFS($B$2:$B$187,B94,$G$2:$G$187,G94)>1,"Yes","No") -> No | AF94: No | AG94: =IF(OR(J94="",K94="",P94="",R94="",S94=""),"Yes","No") -> Yes | AH94: =IF(OR(AA94="Yes",AE94="Yes"),"Review - Core/Duplicate",IF(OR(AB94="Yes",AC94="Yes"),"Clean - Flagged","Clean")) -> Clean | AI94: PANYNJ system-level debt/credit; exclude debt metrics from peer ranking | AJ94: DWU transcription of FAA CATS Form 127 | AK94: https://dwuconsulting.com/airports/JFK
A95: =B95&"-"&G95 -> JFK-2022 | B95: JFK | C95: John F Kennedy International | D95: New York | E95: NY | F95: Large | G95: 2022 | H95: 27459554 | I95: 1486589000 | L95: 10443000 | M95: 22210000 | N95: 34122000 | O95: 135362000 | Q95: 3680000 | T95: 839989000 | U95: 425762000 | V95: 235006000 | X95: 897200000 | Y95: =SUM(L95:S95) -> 205817000 | Z95: =IFERROR(Y95/I95,0) -> 0.13844916 | AA95: =IF(OR(H95="",I95="",T95="",U95=""),"Yes","No") -> No | AB95: =IF(OR(AND(L95<>"",L95=0),AND(M95<>"",M95=0),AND(N95<>"",N95=0),AND(O95<>"",O95=0),AND(Q95<>"",Q95=0)),"Yes","No") -> No | AC95: =IF(MIN(L95:O95,Q95)<0,"Yes","No") -> No | AD95: =IF(U95<0,"Yes","No") -> No | AE95: =IF(COUNTIFS($B$2:$B$187,B95,$G$2:$G$187,G95)>1,"Yes","No") -> No | AF95: No | AG95: =IF(OR(J95="",K95="",P95="",R95="",S95=""),"Yes","No") -> Yes | AH95: =IF(OR(AA95="Yes",AE95="Yes"),"Review - Core/Duplicate",IF(OR(AB95="Yes",AC95="Yes"),"Clean - Flagged","Clean")) -> Clean | AI95: PANYNJ system-level debt/credit; exclude debt metrics from peer ranking | AJ95: DWU transcription of FAA CATS Form 127 | AK95: https://dwuconsulting.com/airports/JFK
A96: =B96&"-"&G96 -> JFK-2023 | B96: JFK | C96: John F Kennedy International | D96: New York | E96: NY | F96: Large | G96: 2023 | H96: 31025194 | I96: 1679745000 | L96: 5992000 | M96: 32974000 | N96: 35315000 | O96: 151458000 | Q96: 5231000 | T96: 944776000 | U96: 521580000 | V96: 558920000 | X96: 1044113000 | Y96: =SUM(L96:S96) -> 230970000 | Z96: =IFERROR(Y96/I96,0) -> 0.13750301 | AA96: =IF(OR(H96="",I96="",T96="",U96=""),"Yes","No") -> No | AB96: =IF(OR(AND(L96<>"",L96=0),AND(M96<>"",M96=0),AND(N96<>"",N96=0),AND(O96<>"",O96=0),AND(Q96<>"",Q96=0)),"Yes","No") -> No | AC96: =IF(MIN(L96:O96,Q96)<0,"Yes","No") -> No | AD96: =IF(U96<0,"Yes","No") -> No | AE96: =IF(COUNTIFS($B$2:$B$187,B96,$G$2:$G$187,G96)>1,"Yes","No") -> No | AF96: No | AG96: =IF(OR(J96="",K96="",P96="",R96="",S96=""),"Yes","No") -> Yes | AH96: =IF(OR(AA96="Yes",AE96="Yes"),"Review - Core/Duplicate",IF(OR(AB96="Yes",AC96="Yes"),"Clean - Flagged","Clean")) -> Clean | AI96: PANYNJ system-level debt/credit; exclude debt metrics from peer ranking | AJ96: DWU transcription of FAA CATS Form 127 | AK96: https://dwuconsulting.com/airports/JFK
A97: =B97&"-"&G97 -> JFK-2024 | B97: JFK | C97: John F Kennedy International | D97: New York | E97: NY | F97: Large | G97: 2024 | H97: 31632992 | I97: 1898669000 | L97: 4954000 | M97: 35744000 | N97: 39060000 | O97: 140686000 | Q97: 5192000 | T97: 1018209000 | U97: 676106000 | V97: 779180000 | X97: 1139224000 | Y97: =SUM(L97:S97) -> 225636000 | Z97: =IFERROR(Y97/I97,0) -> 0.11883904 | AA97: =IF(OR(H97="",I97="",T97="",U97=""),"Yes","No") -> No | AB97: =IF(OR(AND(L97<>"",L97=0),AND(M97<>"",M97=0),AND(N97<>"",N97=0),AND(O97<>"",O97=0),AND(Q97<>"",Q97=0)),"Yes","No") -> No | AC97: =IF(MIN(L97:O97,Q97)<0,"Yes","No") -> No | AD97: =IF(U97<0,"Yes","No") -> No | AE97: =IF(COUNTIFS($B$2:$B$187,B97,$G$2:$G$187,G97)>1,"Yes","No") -> No | AF97: No | AG97: =IF(OR(J97="",K97="",P97="",R97="",S97=""),"Yes","No") -> Yes | AH97: =IF(OR(AA97="Yes",AE97="Yes"),"Review - Core/Duplicate",IF(OR(AB97="Yes",AC97="Yes"),"Clean - Flagged","Clean")) -> Clean | AI97: PANYNJ system-level debt/credit; exclude debt metrics from peer ranking | AJ97: DWU transcription of FAA CATS Form 127 | AK97: https://dwuconsulting.com/airports/JFK
A98: =B98&"-"&G98 -> LAS-2019 | B98: LAS | C98: Harry Reid International | D98: Las Vegas | E98: NV | F98: Large | G98: 2019 | H98: 25223715 | I98: 537781000 | L98: 28565000 | M98: 30567000 | N98: 42351000 | O98: 71893000 | Q98: 54095000 | T98: 271118000 | U98: 76584000 | V98: 61409000 | W98: 3751690000 | X98: 253718000 | Y98: =SUM(L98:S98) -> 227471000 | Z98: =IFERROR(Y98/I98,0) -> 0.42298073 | AA98: =IF(OR(H98="",I98="",T98="",U98=""),"Yes","No") -> No | AB98: =IF(OR(AND(L98<>"",L98=0),AND(M98<>"",M98=0),AND(N98<>"",N98=0),AND(O98<>"",O98=0),AND(Q98<>"",Q98=0)),"Yes","No") -> No | AC98: =IF(MIN(L98:O98,Q98)<0,"Yes","No") -> No | AD98: =IF(U98<0,"Yes","No") -> No | AE98: =IF(COUNTIFS($B$2:$B$187,B98,$G$2:$G$187,G98)>1,"Yes","No") -> No | AF98: Yes | AG98: =IF(OR(J98="",K98="",P98="",R98="",S98=""),"Yes","No") -> Yes | AH98: =IF(OR(AA98="Yes",AE98="Yes"),"Review - Core/Duplicate",IF(OR(AB98="Yes",AC98="Yes"),"Clean - Flagged","Clean")) -> Clean | AI98: Standard airport-level finance comparability | AJ98: DWU transcription of FAA CATS Form 127 | AK98: https://dwuconsulting.com/airports/LAS
A99: =B99&"-"&G99 -> LAS-2020 | B99: LAS | C99: Harry Reid International | D99: Las Vegas | E99: NV | F99: Large | G99: 2020 | H99: 19040295 | I99: 475703000 | L99: 21111000 | M99: 22808000 | N99: 33879000 | O99: 59169000 | Q99: 43673000 | T99: 278542000 | U99: 7324000 | V99: 72540000 | W99: 3239535000 | X99: 243503000 | Y99: =SUM(L99:S99) -> 180640000 | Z99: =IFERROR(Y99/I99,0) -> 0.37973273 | AA99: =IF(OR(H99="",I99="",T99="",U99=""),"Yes","No") -> No | AB99: =IF(OR(AND(L99<>"",L99=0),AND(M99<>"",M99=0),AND(N99<>"",N99=0),AND(O99<>"",O99=0),AND(Q99<>"",Q99=0)),"Yes","No") -> No | AC99: =IF(MIN(L99:O99,Q99)<0,"Yes","No") -> No | AD99: =IF(U99<0,"Yes","No") -> No | AE99: =IF(COUNTIFS($B$2:$B$187,B99,$G$2:$G$187,G99)>1,"Yes","No") -> No | AF99: Yes | AG99: =IF(OR(J99="",K99="",P99="",R99="",S99=""),"Yes","No") -> Yes | AH99: =IF(OR(AA99="Yes",AE99="Yes"),"Review - Core/Duplicate",IF(OR(AB99="Yes",AC99="Yes"),"Clean - Flagged","Clean")) -> Clean | AI99: Standard airport-level finance comparability | AJ99: DWU transcription of FAA CATS Form 127 | AK99: https://dwuconsulting.com/airports/LAS
A100: =B100&"-"&G100 -> LAS-2021 | B100: LAS | C100: Harry Reid International | D100: Las Vegas | E100: NV | F100: Large | G100: 2021 | H100: 13187187 | I100: 397585000 | L100: 12504000 | M100: 13302000 | N100: 30806000 | O100: 46524000 | Q100: 28847000 | T100: 226541000 | U100: -20137000 | V100: 43315000 | W100: 3019895000 | X100: 220377000 | Y100: =SUM(L100:S100) -> 131983000 | Z100: =IFERROR(Y100/I100,0) -> 0.33196172 | AA100: =IF(OR(H100="",I100="",T100="",U100=""),"Yes","No") -> No | AB100: =IF(OR(AND(L100<>"",L100=0),AND(M100<>"",M100=0),AND(N100<>"",N100=0),AND(O100<>"",O100=0),AND(Q100<>"",Q100=0)),"Yes","No") -> No | AC100: =IF(MIN(L100:O100,Q100)<0,"Yes","No") -> No | AD100: =IF(U100<0,"Yes","No") -> Yes | AE100: =IF(COUNTIFS($B$2:$B$187,B100,$G$2:$G$187,G100)>1,"Yes","No") -> No | AF100: Yes | AG100: =IF(OR(J100="",K100="",P100="",R100="",S100=""),"Yes","No") -> Yes | AH100: =IF(OR(AA100="Yes",AE100="Yes"),"Review - Core/Duplicate",IF(OR(AB100="Yes",AC100="Yes"),"Clean - Flagged","Clean")) -> Clean | AI100: Standard airport-level finance comparability | AJ100: DWU transcription of FAA CATS Form 127 | AK100: https://dwuconsulting.com/airports/LAS
A101: =B101&"-"&G101 -> LAS-2022 | B101: LAS | C101: Harry Reid International | D101: Las Vegas | E101: NV | F101: Large | G101: 2022 | H101: 24025401 | I101: 487722000 | L101: 27693000 | M101: 27781000 | N101: 50080000 | O101: 83159000 | Q101: 72774000 | T101: 216244000 | U101: 75340000 | V101: 151422000 | W101: 2779475000 | X101: 170249000 | Y101: =SUM(L101:S101) -> 261487000 | Z101: =IFERROR(Y101/I101,0) -> 0.53613944 | AA101: =IF(OR(H101="",I101="",T101="",U101=""),"Yes","No") -> No | AB101: =IF(OR(AND(L101<>"",L101=0),AND(M101<>"",M101=0),AND(N101<>"",N101=0),AND(O101<>"",O101=0),AND(Q101<>"",Q101=0)),"Yes","No") -> No | AC101: =IF(MIN(L101:O101,Q101)<0,"Yes","No") -> No | AD101: =IF(U101<0,"Yes","No") -> No | AE101: =IF(COUNTIFS($B$2:$B$187,B101,$G$2:$G$187,G101)>1,"Yes","No") -> No | AF101: Yes | AG101: =IF(OR(J101="",K101="",P101="",R101="",S101=""),"Yes","No") -> Yes | AH101: =IF(OR(AA101="Yes",AE101="Yes"),"Review - Core/Duplicate",IF(OR(AB101="Yes",AC101="Yes"),"Clean - Flagged","Clean")) -> Clean | AI101: Standard airport-level finance comparability | AJ101: DWU transcription of FAA CATS Form 127 | AK101: https://dwuconsulting.com/airports/LAS
A102: =B102&"-"&G102 -> LAS-2023 | B102: LAS | C102: Harry Reid International | D102: Las Vegas | E102: NV | F102: Large | G102: 2023 | H102: 28276384 | I102: 560700000 | L102: 29543000 | M102: 29658000 | N102: 54253000 | O102: 100241000 | Q102: 84749000 | T102: 296087000 | U102: 71205000 | V102: 68674000 | W102: 2440045000 | X102: 202647000 | Y102: =SUM(L102:S102) -> 298444000 | Z102: =IFERROR(Y102/I102,0) -> 0.53227038 | AA102: =IF(OR(H102="",I102="",T102="",U102=""),"Yes","No") -> No | AB102: =IF(OR(AND(L102<>"",L102=0),AND(M102<>"",M102=0),AND(N102<>"",N102=0),AND(O102<>"",O102=0),AND(Q102<>"",Q102=0)),"Yes","No") -> No | AC102: =IF(MIN(L102:O102,Q102)<0,"Yes","No") -> No | AD102: =IF(U102<0,"Yes","No") -> No | AE102: =IF(COUNTIFS($B$2:$B$187,B102,$G$2:$G$187,G102)>1,"Yes","No") -> No | AF102: Yes | AG102: =IF(OR(J102="",K102="",P102="",R102="",S102=""),"Yes","No") -> Yes | AH102: =IF(OR(AA102="Yes",AE102="Yes"),"Review - Core/Duplicate",IF(OR(AB102="Yes",AC102="Yes"),"Clean - Flagged","Clean")) -> Clean | AI102: Standard airport-level finance comparability | AJ102: DWU transcription of FAA CATS Form 127 | AK102: https://dwuconsulting.com/airports/LAS
A103: =B103&"-"&G103 -> LAS-2024 | B103: LAS | C103: Harry Reid International | D103: Las Vegas | E103: NV | F103: Large | G103: 2024 | H103: 29145881 | I103: 549697000 | L103: 37858000 | M103: 37084000 | N103: 53239000 | O103: 105644000 | Q103: 94997000 | T103: 326789000 | U103: 31848000 | V103: 511090000 | W103: 2408090000 | X103: 156323000 | Y103: =SUM(L103:S103) -> 328822000 | Z103: =IFERROR(Y103/I103,0) -> 0.59818773 | AA103: =IF(OR(H103="",I103="",T103="",U103=""),"Yes","No") -> No | AB103: =IF(OR(AND(L103<>"",L103=0),AND(M103<>"",M103=0),AND(N103<>"",N103=0),AND(O103<>"",O103=0),AND(Q103<>"",Q103=0)),"Yes","No") -> No | AC103: =IF(MIN(L103:O103,Q103)<0,"Yes","No") -> No | AD103: =IF(U103<0,"Yes","No") -> No | AE103: =IF(COUNTIFS($B$2:$B$187,B103,$G$2:$G$187,G103)>1,"Yes","No") -> No | AF103: Yes | AG103: =IF(OR(J103="",K103="",P103="",R103="",S103=""),"Yes","No") -> Yes | AH103: =IF(OR(AA103="Yes",AE103="Yes"),"Review - Core/Duplicate",IF(OR(AB103="Yes",AC103="Yes"),"Clean - Flagged","Clean")) -> Clean | AI103: Standard airport-level finance comparability | AJ103: DWU transcription of FAA CATS Form 127 | AK103: https://dwuconsulting.com/airports/LAS
A104: =B104&"-"&G104 -> LAX-2019 | B104: LAX | C104: Los Angeles International | D104: Los Angeles | E104: CA | F104: Large | G104: 2019 | H104: 44207464 | I104: 1517731000 | L104: 58179000 | M104: 118176000 | N104: 82607000 | O104: 189875000 | Q104: 52330000 | T104: 798374000 | U104: 316711000 | V104: 1343899000 | W104: 7239791000 | X104: 777059000 | Y104: =SUM(L104:S104) -> 501167000 | Z104: =IFERROR(Y104/I104,0) -> 0.33020805 | AA104: =IF(OR(H104="",I104="",T104="",U104=""),"Yes","No") -> No | AB104: =IF(OR(AND(L104<>"",L104=0),AND(M104<>"",M104=0),AND(N104<>"",N104=0),AND(O104<>"",O104=0),AND(Q104<>"",Q104=0)),"Yes","No") -> No | AC104: =IF(MIN(L104:O104,Q104)<0,"Yes","No") -> No | AD104: =IF(U104<0,"Yes","No") -> No | AE104: =IF(COUNTIFS($B$2:$B$187,B104,$G$2:$G$187,G104)>1,"Yes","No") -> No | AF104: Yes | AG104: =IF(OR(J104="",K104="",P104="",R104="",S104=""),"Yes","No") -> Yes | AH104: =IF(OR(AA104="Yes",AE104="Yes"),"Review - Core/Duplicate",IF(OR(AB104="Yes",AC104="Yes"),"Clean - Flagged","Clean")) -> Clean | AI104: Standard airport-level finance comparability | AJ104: DWU transcription of FAA CATS Form 127 | AK104: https://dwuconsulting.com/airports/LAX
A105: =B105&"-"&G105 -> LAX-2020 | B105: LAX | C105: Los Angeles International | D105: Los Angeles | E105: CA | F105: Large | G105: 2020 | H105: 31429457 | I105: 1345112000 | L105: 43390000 | M105: 80230000 | N105: 65181000 | O105: 146125000 | Q105: 45404000 | T105: 888840000 | U105: 10385000 | V105: 1685625000 | W105: 7226367000 | X105: 717144000 | Y105: =SUM(L105:S105) -> 380330000 | Z105: =IFERROR(Y105/I105,0) -> 0.28274969 | AA105: =IF(OR(H105="",I105="",T105="",U105=""),"Yes","No") -> No | AB105: =IF(OR(AND(L105<>"",L105=0),AND(M105<>"",M105=0),AND(N105<>"",N105=0),AND(O105<>"",O105=0),AND(Q105<>"",Q105=0)),"Yes","No") -> No | AC105: =IF(MIN(L105:O105,Q105)<0,"Yes","No") -> No | AD105: =IF(U105<0,"Yes","No") -> No | AE105: =IF(COUNTIFS($B$2:$B$187,B105,$G$2:$G$187,G105)>1,"Yes","No") -> No | AF105: Yes | AG105: =IF(OR(J105="",K105="",P105="",R105="",S105=""),"Yes","No") -> Yes | AH105: =IF(OR(AA105="Yes",AE105="Yes"),"Review - Core/Duplicate",IF(OR(AB105="Yes",AC105="Yes"),"Clean - Flagged","Clean")) -> Clean | AI105: Standard airport-level finance comparability | AJ105: DWU transcription of FAA CATS Form 127 | AK105: https://dwuconsulting.com/airports/LAX
A106: =B106&"-"&G106 -> LAX-2021 | B106: LAX | C106: Los Angeles International | D106: Los Angeles | E106: CA | F106: Large | G106: 2021 | H106: 14593791 | I106: 1051209000 | L106: 11987000 | M106: 14702000 | N106: 33686000 | O106: 84389000 | Q106: 16658000 | T106: 772041000 | U106: -160179000 | V106: 2600905000 | W106: 8322826000 | X106: 638190000 | Y106: =SUM(L106:S106) -> 161422000 | Z106: =IFERROR(Y106/I106,0) -> 0.15355843 | AA106: =IF(OR(H106="",I106="",T106="",U106=""),"Yes","No") -> No | AB106: =IF(OR(AND(L106<>"",L106=0),AND(M106<>"",M106=0),AND(N106<>"",N106=0),AND(O106<>"",O106=0),AND(Q106<>"",Q106=0)),"Yes","No") -> No | AC106: =IF(MIN(L106:O106,Q106)<0,"Yes","No") -> No | AD106: =IF(U106<0,"Yes","No") -> Yes | AE106: =IF(COUNTIFS($B$2:$B$187,B106,$G$2:$G$187,G106)>1,"Yes","No") -> No | AF106: Yes | AG106: =IF(OR(J106="",K106="",P106="",R106="",S106=""),"Yes","No") -> Yes | AH106: =IF(OR(AA106="Yes",AE106="Yes"),"Review - Core/Duplicate",IF(OR(AB106="Yes",AC106="Yes"),"Clean - Flagged","Clean")) -> Clean | AI106: Standard airport-level finance comparability | AJ106: DWU transcription of FAA CATS Form 127 | AK106: https://dwuconsulting.com/airports/LAX
A107: =B107&"-"&G107 -> LAX-2022 | B107: LAX | C107: Los Angeles International | D107: Los Angeles | E107: CA | F107: Large | G107: 2022 | H107: 30253056 | I107: 1385437000 | L107: 34668000 | M107: 44958000 | N107: 78249000 | O107: 166880000 | Q107: 41557000 | T107: 723951000 | U107: 39583000 | V107: 1058035000 | W107: 9702746000 | X107: 769276000 | Y107: =SUM(L107:S107) -> 366312000 | Z107: =IFERROR(Y107/I107,0) -> 0.26440177 | AA107: =IF(OR(H107="",I107="",T107="",U107=""),"Yes","No") -> No | AB107: =IF(OR(AND(L107<>"",L107=0),AND(M107<>"",M107=0),AND(N107<>"",N107=0),AND(O107<>"",O107=0),AND(Q107<>"",Q107=0)),"Yes","No") -> No | AC107: =IF(MIN(L107:O107,Q107)<0,"Yes","No") -> No | AD107: =IF(U107<0,"Yes","No") -> No | AE107: =IF(COUNTIFS($B$2:$B$187,B107,$G$2:$G$187,G107)>1,"Yes","No") -> No | AF107: Yes | AG107: =IF(OR(J107="",K107="",P107="",R107="",S107=""),"Yes","No") -> Yes | AH107: =IF(OR(AA107="Yes",AE107="Yes"),"Review - Core/Duplicate",IF(OR(AB107="Yes",AC107="Yes"),"Clean - Flagged","Clean")) -> Clean | AI107: Standard airport-level finance comparability | AJ107: DWU transcription of FAA CATS Form 127 | AK107: https://dwuconsulting.com/airports/LAX
A108: =B108&"-"&G108 -> LAX-2023 | B108: LAX | C108: Los Angeles International | D108: Los Angeles | E108: CA | F108: Large | G108: 2023 | H108: 35525350 | I108: 1730329000 | L108: 48295000 | M108: 65670000 | N108: 83827000 | O108: 205600000 | Q108: 44086000 | T108: 832384000 | U108: 208179000 | V108: 2254326000 | W108: 11337226000 | X108: 1024547000 | Y108: =SUM(L108:S108) -> 447478000 | Z108: =IFERROR(Y108/I108,0) -> 0.25860862 | AA108: =IF(OR(H108="",I108="",T108="",U108=""),"Yes","No") -> No | AB108: =IF(OR(AND(L108<>"",L108=0),AND(M108<>"",M108=0),AND(N108<>"",N108=0),AND(O108<>"",O108=0),AND(Q108<>"",Q108=0)),"Yes","No") -> No | AC108: =IF(MIN(L108:O108,Q108)<0,"Yes","No") -> No | AD108: =IF(U108<0,"Yes","No") -> No | AE108: =IF(COUNTIFS($B$2:$B$187,B108,$G$2:$G$187,G108)>1,"Yes","No") -> No | AF108: Yes | AG108: =IF(OR(J108="",K108="",P108="",R108="",S108=""),"Yes","No") -> Yes | AH108: =IF(OR(AA108="Yes",AE108="Yes"),"Review - Core/Duplicate",IF(OR(AB108="Yes",AC108="Yes"),"Clean - Flagged","Clean")) -> Clean | AI108: Standard airport-level finance comparability | AJ108: DWU transcription of FAA CATS Form 127 | AK108: https://dwuconsulting.com/airports/LAX
A109: =B109&"-"&G109 -> LAX-2024 | B109: LAX | C109: Los Angeles International | D109: Los Angeles | E109: CA | F109: Large | G109: 2024 | H109: 38339553 | I109: 1929017000 | L109: 50814000 | M109: 97257000 | N109: 82795000 | O109: 230851000 | Q109: 50677000 | T109: 939987000 | U109: 231398000 | V109: 1889873000 | W109: 11771377000 | X109: 1156406000 | Y109: =SUM(L109:S109) -> 512394000 | Z109: =IFERROR(Y109/I109,0) -> 0.26562441 | AA109: =IF(OR(H109="",I109="",T109="",U109=""),"Yes","No") -> No | AB109: =IF(OR(AND(L109<>"",L109=0),AND(M109<>"",M109=0),AND(N109<>"",N109=0),AND(O109<>"",O109=0),AND(Q109<>"",Q109=0)),"Yes","No") -> No | AC109: =IF(MIN(L109:O109,Q109)<0,"Yes","No") -> No | AD109: =IF(U109<0,"Yes","No") -> No | AE109: =IF(COUNTIFS($B$2:$B$187,B109,$G$2:$G$187,G109)>1,"Yes","No") -> No | AF109: Yes | AG109: =IF(OR(J109="",K109="",P109="",R109="",S109=""),"Yes","No") -> Yes | AH109: =IF(OR(AA109="Yes",AE109="Yes"),"Review - Core/Duplicate",IF(OR(AB109="Yes",AC109="Yes"),"Clean - Flagged","Clean")) -> Clean | AI109: Standard airport-level finance comparability | AJ109: DWU transcription of FAA CATS Form 127 | AK109: https://dwuconsulting.com/airports/LAX
A110: =B110&"-"&G110 -> LGA-2019 | B110: LGA | C110: Laguardia | D110: New York | E110: NY | F110: Large | G110: 2019 | H110: 15542447 | I110: 429046000 | L110: 1351000 | M110: 3005000 | N110: 15476000 | O110: 41928000 | Q110: 234000 | T110: 370045000 | U110: -65008000 | V110: 732177000 | X110: 318825000 | Y110: =SUM(L110:S110) -> 61994000 | Z110: =IFERROR(Y110/I110,0) -> 0.14449267 | AA110: =IF(OR(H110="",I110="",T110="",U110=""),"Yes","No") -> No | AB110: =IF(OR(AND(L110<>"",L110=0),AND(M110<>"",M110=0),AND(N110<>"",N110=0),AND(O110<>"",O110=0),AND(Q110<>"",Q110=0)),"Yes","No") -> No | AC110: =IF(MIN(L110:O110,Q110)<0,"Yes","No") -> No | AD110: =IF(U110<0,"Yes","No") -> Yes | AE110: =IF(COUNTIFS($B$2:$B$187,B110,$G$2:$G$187,G110)>1,"Yes","No") -> No | AF110: No | AG110: =IF(OR(J110="",K110="",P110="",R110="",S110=""),"Yes","No") -> Yes | AH110: =IF(OR(AA110="Yes",AE110="Yes"),"Review - Core/Duplicate",IF(OR(AB110="Yes",AC110="Yes"),"Clean - Flagged","Clean")) -> Clean | AI110: PANYNJ system-level debt/credit; exclude debt metrics from peer ranking | AJ110: DWU transcription of FAA CATS Form 127 | AK110: https://dwuconsulting.com/airports/LGA
A111: =B111&"-"&G111 -> LGA-2020 | B111: LGA | C111: Laguardia | D111: New York | E111: NY | F111: Large | G111: 2020 | H111: 4184418 | I111: 326552000 | L111: 559000 | M111: 988000 | N111: 9386000 | O111: 23878000 | Q111: 606000 | T111: 342727000 | U111: -184847000 | V111: 433558000 | X111: 259370000 | Y111: =SUM(L111:S111) -> 35417000 | Z111: =IFERROR(Y111/I111,0) -> 0.10845746 | AA111: =IF(OR(H111="",I111="",T111="",U111=""),"Yes","No") -> No | AB111: =IF(OR(AND(L111<>"",L111=0),AND(M111<>"",M111=0),AND(N111<>"",N111=0),AND(O111<>"",O111=0),AND(Q111<>"",Q111=0)),"Yes","No") -> No | AC111: =IF(MIN(L111:O111,Q111)<0,"Yes","No") -> No | AD111: =IF(U111<0,"Yes","No") -> Yes | AE111: =IF(COUNTIFS($B$2:$B$187,B111,$G$2:$G$187,G111)>1,"Yes","No") -> No | AF111: No | AG111: =IF(OR(J111="",K111="",P111="",R111="",S111=""),"Yes","No") -> Yes | AH111: =IF(OR(AA111="Yes",AE111="Yes"),"Review - Core/Duplicate",IF(OR(AB111="Yes",AC111="Yes"),"Clean - Flagged","Clean")) -> Clean | AI111: PANYNJ system-level debt/credit; exclude debt metrics from peer ranking | AJ111: DWU transcription of FAA CATS Form 127 | AK111: https://dwuconsulting.com/airports/LGA
A112: =B112&"-"&G112 -> LGA-2021 | B112: LGA | C112: Laguardia | D112: New York | E112: NY | F112: Large | G112: 2021 | H112: 7870201 | I112: 391705000 | L112: 945000 | M112: 1710000 | N112: 13804000 | O112: 47769000 | Q112: 354000 | T112: 313622000 | U112: -116674000 | V112: 362179000 | X112: 285282000 | Y112: =SUM(L112:S112) -> 64582000 | Z112: =IFERROR(Y112/I112,0) -> 0.16487408 | AA112: =IF(OR(H112="",I112="",T112="",U112=""),"Yes","No") -> No | AB112: =IF(OR(AND(L112<>"",L112=0),AND(M112<>"",M112=0),AND(N112<>"",N112=0),AND(O112<>"",O112=0),AND(Q112<>"",Q112=0)),"Yes","No") -> No | AC112: =IF(MIN(L112:O112,Q112)<0,"Yes","No") -> No | AD112: =IF(U112<0,"Yes","No") -> Yes | AE112: =IF(COUNTIFS($B$2:$B$187,B112,$G$2:$G$187,G112)>1,"Yes","No") -> No | AF112: No | AG112: =IF(OR(J112="",K112="",P112="",R112="",S112=""),"Yes","No") -> Yes | AH112: =IF(OR(AA112="Yes",AE112="Yes"),"Review - Core/Duplicate",IF(OR(AB112="Yes",AC112="Yes"),"Clean - Flagged","Clean")) -> Clean | AI112: PANYNJ system-level debt/credit; exclude debt metrics from peer ranking | AJ112: DWU transcription of FAA CATS Form 127 | AK112: https://dwuconsulting.com/airports/LGA
A113: =B113&"-"&G113 -> LGA-2022 | B113: LGA | C113: Laguardia | D113: New York | E113: NY | F113: Large | G113: 2022 | H113: 14453348 | I113: 526043000 | L113: 2968000 | M113: 1663000 | N113: 18225000 | O113: 79947000 | Q113: 333000 | T113: 372416000 | U113: -113745000 | V113: 476148000 | X113: 374476000 | Y113: =SUM(L113:S113) -> 103136000 | Z113: =IFERROR(Y113/I113,0) -> 0.19606002 | AA113: =IF(OR(H113="",I113="",T113="",U113=""),"Yes","No") -> No | AB113: =IF(OR(AND(L113<>"",L113=0),AND(M113<>"",M113=0),AND(N113<>"",N113=0),AND(O113<>"",O113=0),AND(Q113<>"",Q113=0)),"Yes","No") -> No | AC113: =IF(MIN(L113:O113,Q113)<0,"Yes","No") -> No | AD113: =IF(U113<0,"Yes","No") -> Yes | AE113: =IF(COUNTIFS($B$2:$B$187,B113,$G$2:$G$187,G113)>1,"Yes","No") -> No | AF113: No | AG113: =IF(OR(J113="",K113="",P113="",R113="",S113=""),"Yes","No") -> Yes | AH113: =IF(OR(AA113="Yes",AE113="Yes"),"Review - Core/Duplicate",IF(OR(AB113="Yes",AC113="Yes"),"Clean - Flagged","Clean")) -> Clean | AI113: PANYNJ system-level debt/credit; exclude debt metrics from peer ranking | AJ113: DWU transcription of FAA CATS Form 127 | AK113: https://dwuconsulting.com/airports/LGA
A114: =B114&"-"&G114 -> LGA-2023 | B114: LGA | C114: Laguardia | D114: New York | E114: NY | F114: Large | G114: 2023 | H114: 16172875 | I114: 544156000 | L114: 5006000 | M114: 1777000 | N114: 18747000 | O114: 92401000 | Q114: 336000 | T114: 447274000 | U114: -120330000 | V114: 96927000 | X114: 370260000 | Y114: =SUM(L114:S114) -> 118267000 | Z114: =IFERROR(Y114/I114,0) -> 0.21734025 | AA114: =IF(OR(H114="",I114="",T114="",U114=""),"Yes","No") -> No | AB114: =IF(OR(AND(L114<>"",L114=0),AND(M114<>"",M114=0),AND(N114<>"",N114=0),AND(O114<>"",O114=0),AND(Q114<>"",Q114=0)),"Yes","No") -> No | AC114: =IF(MIN(L114:O114,Q114)<0,"Yes","No") -> No | AD114: =IF(U114<0,"Yes","No") -> Yes | AE114: =IF(COUNTIFS($B$2:$B$187,B114,$G$2:$G$187,G114)>1,"Yes","No") -> No | AF114: No | AG114: =IF(OR(J114="",K114="",P114="",R114="",S114=""),"Yes","No") -> Yes | AH114: =IF(OR(AA114="Yes",AE114="Yes"),"Review - Core/Duplicate",IF(OR(AB114="Yes",AC114="Yes"),"Clean - Flagged","Clean")) -> Clean | AI114: PANYNJ system-level debt/credit; exclude debt metrics from peer ranking | AJ114: DWU transcription of FAA CATS Form 127 | AK114: https://dwuconsulting.com/airports/LGA
A115: =B115&"-"&G115 -> LGA-2024 | B115: LGA | C115: Laguardia | D115: New York | E115: NY | F115: Large | G115: 2024 | H115: 16771972 | I115: 579390000 | L115: 7327000 | M115: 3313000 | N115: 19271000 | O115: 94983000 | Q115: 287000 | T115: 461223000 | U115: -104238000 | V115: 80847000 | X115: 389160000 | Y115: =SUM(L115:S115) -> 125181000 | Z115: =IFERROR(Y115/I115,0) -> 0.21605654 | AA115: =IF(OR(H115="",I115="",T115="",U115=""),"Yes","No") -> No | AB115: =IF(OR(AND(L115<>"",L115=0),AND(M115<>"",M115=0),AND(N115<>"",N115=0),AND(O115<>"",O115=0),AND(Q115<>"",Q115=0)),"Yes","No") -> No | AC115: =IF(MIN(L115:O115,Q115)<0,"Yes","No") -> No | AD115: =IF(U115<0,"Yes","No") -> Yes | AE115: =IF(COUNTIFS($B$2:$B$187,B115,$G$2:$G$187,G115)>1,"Yes","No") -> No | AF115: No | AG115: =IF(OR(J115="",K115="",P115="",R115="",S115=""),"Yes","No") -> Yes | AH115: =IF(OR(AA115="Yes",AE115="Yes"),"Review - Core/Duplicate",IF(OR(AB115="Yes",AC115="Yes"),"Clean - Flagged","Clean")) -> Clean | AI115: PANYNJ system-level debt/credit; exclude debt metrics from peer ranking | AJ115: DWU transcription of FAA CATS Form 127 | AK115: https://dwuconsulting.com/airports/LGA
A116: =B116&"-"&G116 -> MCO-2019 | B116: MCO | C116: Orlando International | D116: Orlando | E116: FL | F116: Large | G116: 2019 | H116: 24846842 | I116: 501031000 | L116: 31553000 | M116: 21513000 | N116: 107254000 | O116: 93122000 | Q116: 18792000 | T116: 326069000 | U116: -6072000 | V116: 720989000 | W116: 2424672000 | X116: 141526000 | Y116: =SUM(L116:S116) -> 272234000 | Z116: =IFERROR(Y116/I116,0) -> 0.54334762 | AA116: =IF(OR(H116="",I116="",T116="",U116=""),"Yes","No") -> No | AB116: =IF(OR(AND(L116<>"",L116=0),AND(M116<>"",M116=0),AND(N116<>"",N116=0),AND(O116<>"",O116=0),AND(Q116<>"",Q116=0)),"Yes","No") -> No | AC116: =IF(MIN(L116:O116,Q116)<0,"Yes","No") -> No | AD116: =IF(U116<0,"Yes","No") -> Yes | AE116: =IF(COUNTIFS($B$2:$B$187,B116,$G$2:$G$187,G116)>1,"Yes","No") -> No | AF116: Yes | AG116: =IF(OR(J116="",K116="",P116="",R116="",S116=""),"Yes","No") -> Yes | AH116: =IF(OR(AA116="Yes",AE116="Yes"),"Review - Core/Duplicate",IF(OR(AB116="Yes",AC116="Yes"),"Clean - Flagged","Clean")) -> Clean | AI116: Standard airport-level finance comparability | AJ116: DWU transcription of FAA CATS Form 127 | AK116: https://dwuconsulting.com/airports/MCO
A117: =B117&"-"&G117 -> MCO-2020 | B117: MCO | C117: Orlando International | D117: Orlando | E117: FL | F117: Large | G117: 2020 | H117: 14538126 | I117: 434226000 | L117: 21489000 | M117: 13911000 | N117: 87741000 | O117: 56345000 | Q117: 15157000 | T117: 283657000 | U117: -38151000 | V117: 973288000 | W117: 3193491000 | X117: 170283000 | Y117: =SUM(L117:S117) -> 194643000 | Z117: =IFERROR(Y117/I117,0) -> 0.44825275 | AA117: =IF(OR(H117="",I117="",T117="",U117=""),"Yes","No") -> No | AB117: =IF(OR(AND(L117<>"",L117=0),AND(M117<>"",M117=0),AND(N117<>"",N117=0),AND(O117<>"",O117=0),AND(Q117<>"",Q117=0)),"Yes","No") -> No | AC117: =IF(MIN(L117:O117,Q117)<0,"Yes","No") -> No | AD117: =IF(U117<0,"Yes","No") -> Yes | AE117: =IF(COUNTIFS($B$2:$B$187,B117,$G$2:$G$187,G117)>1,"Yes","No") -> No | AF117: Yes | AG117: =IF(OR(J117="",K117="",P117="",R117="",S117=""),"Yes","No") -> Yes | AH117: =IF(OR(AA117="Yes",AE117="Yes"),"Review - Core/Duplicate",IF(OR(AB117="Yes",AC117="Yes"),"Clean - Flagged","Clean")) -> Clean | AI117: Standard airport-level finance comparability | AJ117: DWU transcription of FAA CATS Form 127 | AK117: https://dwuconsulting.com/airports/MCO
A118: =B118&"-"&G118 -> MCO-2021 | B118: MCO | C118: Orlando International | D118: Orlando | E118: FL | F118: Large | G118: 2021 | H118: 16984242 | I118: 396006000 | L118: 22289000 | M118: 12117000 | N118: 92927000 | O118: 59235000 | Q118: 12471000 | T118: 255221000 | U118: -41564000 | V118: 626480000 | W118: 3132861000 | X118: 131021000 | Y118: =SUM(L118:S118) -> 199039000 | Z118: =IFERROR(Y118/I118,0) -> 0.50261612 | AA118: =IF(OR(H118="",I118="",T118="",U118=""),"Yes","No") -> No | AB118: =IF(OR(AND(L118<>"",L118=0),AND(M118<>"",M118=0),AND(N118<>"",N118=0),AND(O118<>"",O118=0),AND(Q118<>"",Q118=0)),"Yes","No") -> No | AC118: =IF(MIN(L118:O118,Q118)<0,"Yes","No") -> No | AD118: =IF(U118<0,"Yes","No") -> Yes | AE118: =IF(COUNTIFS($B$2:$B$187,B118,$G$2:$G$187,G118)>1,"Yes","No") -> No | AF118: Yes | AG118: =IF(OR(J118="",K118="",P118="",R118="",S118=""),"Yes","No") -> Yes | AH118: =IF(OR(AA118="Yes",AE118="Yes"),"Review - Core/Duplicate",IF(OR(AB118="Yes",AC118="Yes"),"Clean - Flagged","Clean")) -> Clean | AI118: Standard airport-level finance comparability | AJ118: DWU transcription of FAA CATS Form 127 | AK118: https://dwuconsulting.com/airports/MCO
A119: =B119&"-"&G119 -> MCO-2022 | B119: MCO | C119: Orlando International | D119: Orlando | E119: FL | F119: Large | G119: 2022 | H119: 24220932 | I119: 510017000 | L119: 28594000 | M119: 16879000 | N119: 130762000 | O119: 97899000 | Q119: 16394000 | T119: 312883000 | U119: 28373000 | V119: 400063000 | W119: 2965011000 | X119: 118825000 | Y119: =SUM(L119:S119) -> 290528000 | Z119: =IFERROR(Y119/I119,0) -> 0.56964376 | AA119: =IF(OR(H119="",I119="",T119="",U119=""),"Yes","No") -> No | AB119: =IF(OR(AND(L119<>"",L119=0),AND(M119<>"",M119=0),AND(N119<>"",N119=0),AND(O119<>"",O119=0),AND(Q119<>"",Q119=0)),"Yes","No") -> No | AC119: =IF(MIN(L119:O119,Q119)<0,"Yes","No") -> No | AD119: =IF(U119<0,"Yes","No") -> No | AE119: =IF(COUNTIFS($B$2:$B$187,B119,$G$2:$G$187,G119)>1,"Yes","No") -> No | AF119: Yes | AG119: =IF(OR(J119="",K119="",P119="",R119="",S119=""),"Yes","No") -> Yes | AH119: =IF(OR(AA119="Yes",AE119="Yes"),"Review - Core/Duplicate",IF(OR(AB119="Yes",AC119="Yes"),"Clean - Flagged","Clean")) -> Clean | AI119: Standard airport-level finance comparability | AJ119: DWU transcription of FAA CATS Form 127 | AK119: https://dwuconsulting.com/airports/MCO
A120: =B120&"-"&G120 -> MCO-2023 | B120: MCO | C120: Orlando International | D120: Orlando | E120: FL | F120: Large | G120: 2023 | H120: 27919698 | I120: 651684000 | L120: 37424000 | M120: 23238000 | N120: 129324000 | O120: 117967000 | Q120: 19924000 | T120: 452636000 | U120: -32909000 | V120: 176346000 | W120: 2806240000 | X120: 213316000 | Y120: =SUM(L120:S120) -> 327877000 | Z120: =IFERROR(Y120/I120,0) -> 0.50312268 | AA120: =IF(OR(H120="",I120="",T120="",U120=""),"Yes","No") -> No | AB120: =IF(OR(AND(L120<>"",L120=0),AND(M120<>"",M120=0),AND(N120<>"",N120=0),AND(O120<>"",O120=0),AND(Q120<>"",Q120=0)),"Yes","No") -> No | AC120: =IF(MIN(L120:O120,Q120)<0,"Yes","No") -> No | AD120: =IF(U120<0,"Yes","No") -> Yes | AE120: =IF(COUNTIFS($B$2:$B$187,B120,$G$2:$G$187,G120)>1,"Yes","No") -> No | AF120: Yes | AG120: =IF(OR(J120="",K120="",P120="",R120="",S120=""),"Yes","No") -> Yes | AH120: =IF(OR(AA120="Yes",AE120="Yes"),"Review - Core/Duplicate",IF(OR(AB120="Yes",AC120="Yes"),"Clean - Flagged","Clean")) -> Clean | AI120: Standard airport-level finance comparability | AJ120: DWU transcription of FAA CATS Form 127 | AK120: https://dwuconsulting.com/airports/MCO
A121: =B121&"-"&G121 -> MCO-2024 | B121: MCO | C121: Orlando International | D121: Orlando | E121: FL | F121: Large | G121: 2024 | H121: 29080689 | I121: 721005000 | L121: 45304000 | M121: 23897000 | N121: 129030000 | O121: 142808000 | Q121: 25917000 | T121: 491337000 | U121: -573000 | V121: 329351000 | W121: 2660996000 | X121: 237852000 | Y121: =SUM(L121:S121) -> 366956000 | Z121: =IFERROR(Y121/I121,0) -> 0.5089507 | AA121: =IF(OR(H121="",I121="",T121="",U121=""),"Yes","No") -> No | AB121: =IF(OR(AND(L121<>"",L121=0),AND(M121<>"",M121=0),AND(N121<>"",N121=0),AND(O121<>"",O121=0),AND(Q121<>"",Q121=0)),"Yes","No") -> No | AC121: =IF(MIN(L121:O121,Q121)<0,"Yes","No") -> No | AD121: =IF(U121<0,"Yes","No") -> Yes | AE121: =IF(COUNTIFS($B$2:$B$187,B121,$G$2:$G$187,G121)>1,"Yes","No") -> No | AF121: Yes | AG121: =IF(OR(J121="",K121="",P121="",R121="",S121=""),"Yes","No") -> Yes | AH121: =IF(OR(AA121="Yes",AE121="Yes"),"Review - Core/Duplicate",IF(OR(AB121="Yes",AC121="Yes"),"Clean - Flagged","Clean")) -> Clean | AI121: Standard airport-level finance comparability | AJ121: DWU transcription of FAA CATS Form 127 | AK121: https://dwuconsulting.com/airports/MCO
A122: =B122&"-"&G122 -> MDW-2019 | B122: MDW | C122: Chicago Midway International | D122: Chicago | E122: IL | F122: Large | G122: 2019 | H122: 10417815 | I122: 227534000 | L122: 16227000 | M122: 7597000 | N122: 11636000 | O122: 34430000 | Q122: 109000 | T122: 188182000 | U122: -12655000 | V122: 144065000 | W122: 1773987000 | X122: 123170000 | Y122: =SUM(L122:S122) -> 69999000 | Z122: =IFERROR(Y122/I122,0) -> 0.30764193 | AA122: =IF(OR(H122="",I122="",T122="",U122=""),"Yes","No") -> No | AB122: =IF(OR(AND(L122<>"",L122=0),AND(M122<>"",M122=0),AND(N122<>"",N122=0),AND(O122<>"",O122=0),AND(Q122<>"",Q122=0)),"Yes","No") -> No | AC122: =IF(MIN(L122:O122,Q122)<0,"Yes","No") -> No | AD122: =IF(U122<0,"Yes","No") -> Yes | AE122: =IF(COUNTIFS($B$2:$B$187,B122,$G$2:$G$187,G122)>1,"Yes","No") -> No | AF122: Yes | AG122: =IF(OR(J122="",K122="",P122="",R122="",S122=""),"Yes","No") -> Yes | AH122: =IF(OR(AA122="Yes",AE122="Yes"),"Review - Core/Duplicate",IF(OR(AB122="Yes",AC122="Yes"),"Clean - Flagged","Clean")) -> Clean | AI122: Standard airport-level finance comparability | AJ122: DWU transcription of FAA CATS Form 127 | AK122: https://dwuconsulting.com/airports/MDW
